[
  {
    "departement": "GEA",
    "semestres": [
      {
        "url": "/fr/formation/parcours/1165/3/1",
        "ecs": [
          {
            "UE": "Enseignements Transversaux (GEA-3-UE31)",
            "url": "http://planete.insa-lyon.fr/scolpeda/f/ects?id=38562&_lang=fr",
            "detail": {
              "code": "GEA-3-MA0",
              "ects": "2.0",
              "cours": "26.0 h",
              "td": "26.0 h",
              "tp": "0.0 h",
              "projet": "0.0 h",
              "perso": "0.0 h",
              "nom": "Mathématiques : Mathématiques pour l'ingénieur - Remise à niveau",
              "competencesBrutes": "Cet EC relève de l'unité d'enseignement  (UE31) et contribue aux compétences suivantes :  -- Analyser un système (ou un problème) réel ou virtuel (niveau 2)  --- Capacité : Utiliser et mettre en oeuvre outils mathématiques fondamentaux --- Capacité : Maitriser les outils mathématiques fondamentaux liés au Génie Electrique  --- Connaissance : Complexes, Etudes de fonctions --- Connaissance : Polynomes, Fonctions rationnelles, Développement limités --- Connaissance : Matrices, Résolution de systèmes  -- Mettre en œuvre une démarche expérimentale (niveau 2)  --- Capacité : Analyser un problème, le formaliser  et savoir le mettre en équation --- Capacité : Maitriser des méthodes de calcul mathématique  --- Connaissance : Complexes, Etudes de fonctions --- Connaissance : Polynomes, Fonctions rationnelles, Développement limités --- Connaissance : Matrices, Résolution de systèmes",
              "capacite": [
                "Capacité : Utiliser et mettre en oeuvre outils mathématiques fondamentaux",
                "Capacité : Maitriser les outils mathématiques fondamentaux liés au Génie Electrique",
                "Capacité : Analyser un problème, le formaliser  et savoir le mettre en équation",
                "Capacité : Maitriser des méthodes de calcul mathématique"
              ],
              "connaissance": [
                "Connaissance : Complexes, Etudes de fonctions",
                "Connaissance : Polynomes, Fonctions rationnelles, Développement limités",
                "Connaissance : Matrices, Résolution de systèmes  -- Mettre en œuvre une démarche expérimentale (niveau 2)",
                "Connaissance : Complexes, Etudes de fonctions",
                "Connaissance : Polynomes, Fonctions rationnelles, Développement limités",
                "Connaissance : Matrices, Résolution de systèmes"
              ],
              "competenceToCapaciteEtConnaissance": {
                "A1": [
                  "Capacité : Utiliser et mettre en oeuvre outils mathématiques fondamentaux",
                  "Capacité : Maitriser les outils mathématiques fondamentaux liés au Génie Electrique",
                  "Connaissance : Complexes, Etudes de fonctions",
                  "Connaissance : Polynomes, Fonctions rationnelles, Développement limités",
                  "Connaissance : Matrices, Résolution de systèmes  -- Mettre en œuvre une démarche expérimentale (niveau 2)",
                  "Capacité : Analyser un problème, le formaliser  et savoir le mettre en équation",
                  "Capacité : Maitriser des méthodes de calcul mathématique",
                  "Connaissance : Complexes, Etudes de fonctions",
                  "Connaissance : Polynomes, Fonctions rationnelles, Développement limités",
                  "Connaissance : Matrices, Résolution de systèmes"
                ]
              },
              "listeComp": [
                {
                  "code": "A1",
                  "val": "Analyser un système (ou un problème) réel ou virtuel",
                  "valAnglais": "Analyze a real or virtual system (or problem)",
                  "bs": "1",
                  "niveau": "2"
                }
              ]
            }
          },
          {
            "UE": "Enseignements Transversaux (GEA-3-UE31)",
            "url": "http://planete.insa-lyon.fr/scolpeda/f/ects?id=38563&_lang=fr",
            "detail": {
              "code": "GEA-3-SSMT",
              "ects": "3.0",
              "cours": "23.5 h",
              "td": "23.5 h",
              "tp": "3.0 h",
              "projet": "0.0 h",
              "perso": "0.0 h",
              "nom": "Mathématiques pour l'ingénieur - Signaux et systèmes, Mathématiques : des transformées",
              "competencesBrutes": "Cet EC relève de l'unité d'enseignement  (UE31) et contribue aux compétences suivantes :  - Spécifier, modéliser et concevoir les méthodes et algorithmes pour le traitement et la gestion de l'information véhiculée par les signaux et les images (niveau 2)  --- Capacité : Etre capable de comprendre et d'appliquer les transformées de Fourier, Laplace et z  --- Connaissance : Savoir manipuler les signaux et calculer les grandeurs caractéristiques de ces signaux --- Connaissance : Savoir calculer les transformées de signaux usuels --- Connaissance : Savoir appliquer les transformées de Laplace et z à la résolution des équations différentielles et aux différences  - Mettre en œuvre les étapes permettant le contrôle du fonctionnement d'un système discret ou continu (niveau 2)  --- Capacité : Etre capable de déterminer les propriétés d'un système discret ou continu --- Capacité : Etre capable d'analyser le comportement interne du système en temps et en fréquence  --- Connaissance : Comprendre l'interaction entrée sortie du système --- Connaissance : Savoir mettre en équation un système continu ou discret --- Connaissance : Savoir déterminer la réponse impulsionnelle d'un système et sa réponse harmonique --- Connaissance : Savoir déterminer le régime forcé, le régime libre, la fonction de transfert, la stabilité d'un système  De plus, elle nécessite de mobiliser les compétences suivantes :  -- Analyser un système (ou un problème) réel ou virtuel -- Exploiter un modèle d'un système réel ou virtuel -- Mettre en œuvre une démarche expérimentale -- Concevoir un système répondant à un cahier des charges -- Traiter des données -- Communiquer une analyse ou une démarche scientifique -- Se connaître, se gérer physiquement et mentalement -- Travailler, apprendre, évoluer de manière autonome -- Interagir avec les autres, travailler en équipe",
              "capacite": [
                "Capacité : Etre capable de comprendre et d'appliquer les transformées de Fourier, Laplace et z",
                "Capacité : Etre capable de déterminer les propriétés d'un système discret ou continu",
                "Capacité : Etre capable d'analyser le comportement interne du système en temps et en fréquence"
              ],
              "connaissance": [
                "Connaissance : Savoir manipuler les signaux et calculer les grandeurs caractéristiques de ces signaux",
                "Connaissance : Savoir calculer les transformées de signaux usuels",
                "Connaissance : Savoir appliquer les transformées de Laplace et z à la résolution des équations différentielles et aux différences",
                "Connaissance : Comprendre l'interaction entrée sortie du système",
                "Connaissance : Savoir mettre en équation un système continu ou discret",
                "Connaissance : Savoir déterminer la réponse impulsionnelle d'un système et sa réponse harmonique",
                "Connaissance : Savoir déterminer le régime forcé, le régime libre, la fonction de transfert, la stabilité d'un système"
              ],
              "competenceToCapaciteEtConnaissance": {
                "GEA-C4": [
                  "Capacité : Etre capable de comprendre et d'appliquer les transformées de Fourier, Laplace et z",
                  "Connaissance : Savoir manipuler les signaux et calculer les grandeurs caractéristiques de ces signaux",
                  "Connaissance : Savoir calculer les transformées de signaux usuels",
                  "Connaissance : Savoir appliquer les transformées de Laplace et z à la résolution des équations différentielles et aux différences"
                ],
                "GEA-C6": [
                  "Capacité : Etre capable de déterminer les propriétés d'un système discret ou continu",
                  "Capacité : Etre capable d'analyser le comportement interne du système en temps et en fréquence",
                  "Connaissance : Comprendre l'interaction entrée sortie du système",
                  "Connaissance : Savoir mettre en équation un système continu ou discret",
                  "Connaissance : Savoir déterminer la réponse impulsionnelle d'un système et sa réponse harmonique",
                  "Connaissance : Savoir déterminer le régime forcé, le régime libre, la fonction de transfert, la stabilité d'un système"
                ]
              },
              "listeComp": [
                {
                  "code": "C4",
                  "val": "Spécifier, modéliser et concevoir les méthodes et algorithmes pour le traitement et la gestion de l'information véhiculée par les signaux et les images",
                  "valAnglais": "Specify, model and design methods and algorithms for the processing and management of information conveyed by signals and images",
                  "niveau": "2"
                },
                {
                  "code": "C6",
                  "val": "Mettre en œuvre les étapes permettant le contrôle du fonctionnement d'un système discret ou continu",
                  "valAnglais": "Implement steps to control the operation of a discrete or continuous system",
                  "niveau": "2"
                }
              ],
              "listeCompMobilise": [
                "Analyser un système (ou un problème) réel ou virtuel",
                "Exploiter un modèle d'un système réel ou virtuel",
                "Mettre en œuvre une démarche expérimentale",
                "Concevoir un système répondant à un cahier des charges",
                "Traiter des données",
                "Communiquer une analyse ou une démarche scientifique",
                "Se connaître, se gérer physiquement et mentalement",
                "Travailler, apprendre, évoluer de manière autonome",
                "Interagir avec les autres, travailler en équipe"
              ]
            }
          },
          {
            "UE": "Enseignements Transversaux (GEA-3-UE31)",
            "url": "http://planete.insa-lyon.fr/scolpeda/f/ects?id=39474&_lang=fr",
            "detail": {
              "code": "GEA-3-TC0",
              "ects": "1.0",
              "cours": "4.0 h",
              "td": "4.0 h",
              "tp": "4.0 h",
              "projet": "0.0 h",
              "perso": "0.0 h",
              "nom": "Télécommunications : Télécommunications et Réseaux - Remise à niveau",
              "competencesBrutes": "Cet EC relève de l'unité d'enseignement  (UE31) et contribue aux compétences suivantes :  - Concevoir et réaliser des systèmes électroniques pour l'acquisition, le traitement, la commande et la communication de données (niveau 2)  --- Capacité : Mettre en œuvre une liaison série asynchrone --- Capacité : Appréhender les appects physiques des transmissions numériques --- Capacité : Appréhender le rôle des différentes couches du modèle réseau TCP/IP --- Capacité : Analyser un plan d'adressage IP  --- Connaissance : Caractéristiques du format asynchrone de transmission --- Connaissance : Aspects physique, contrôle de flux --- Connaissance : Caractéristiques d'une trame Ethernet --- Connaissance : Modèles OSI et TCP/IP, Encapsulation des données, Principaux protocoles réseaux --- Connaissance : Adressage IP, masques, classes réseau, ¿",
              "capacite": [
                "Capacité : Mettre en œuvre une liaison série asynchrone",
                "Capacité : Appréhender les appects physiques des transmissions numériques",
                "Capacité : Appréhender le rôle des différentes couches du modèle réseau TCP/IP",
                "Capacité : Analyser un plan d'adressage IP"
              ],
              "connaissance": [
                "Connaissance : Caractéristiques du format asynchrone de transmission",
                "Connaissance : Aspects physique, contrôle de flux",
                "Connaissance : Caractéristiques d'une trame Ethernet",
                "Connaissance : Modèles OSI et TCP/IP, Encapsulation des données, Principaux protocoles réseaux",
                "Connaissance : Adressage IP, masques, classes réseau, '"
              ],
              "competenceToCapaciteEtConnaissance": {
                "GEA-C5": [
                  "Capacité : Mettre en œuvre une liaison série asynchrone",
                  "Capacité : Appréhender les appects physiques des transmissions numériques",
                  "Capacité : Appréhender le rôle des différentes couches du modèle réseau TCP/IP",
                  "Capacité : Analyser un plan d'adressage IP",
                  "Connaissance : Caractéristiques du format asynchrone de transmission",
                  "Connaissance : Aspects physique, contrôle de flux",
                  "Connaissance : Caractéristiques d'une trame Ethernet",
                  "Connaissance : Modèles OSI et TCP/IP, Encapsulation des données, Principaux protocoles réseaux",
                  "Connaissance : Adressage IP, masques, classes réseau, '"
                ]
              },
              "listeComp": [
                {
                  "code": "C5",
                  "val": "Concevoir et réaliser des systèmes électroniques pour l'acquisition, le traitement, la commande et la communication de données",
                  "valAnglais": "Design and build electronic systems for data acquisition, processing, control and communication",
                  "niveau": "2"
                }
              ]
            }
          },
          {
            "UE": "Enseignements Transversaux (GEA-3-UE31)",
            "url": "http://planete.insa-lyon.fr/scolpeda/f/ects?id=39237&_lang=fr",
            "detail": {
              "code": "GEA-3-IF0",
              "ects": "1.0",
              "cours": "15.0 h",
              "td": "15.0 h",
              "tp": "0.0 h",
              "projet": "0.0 h",
              "perso": "0.0 h",
              "nom": "Informatique Industrielle : Informatique industrielle - Remise à niveau",
              "competencesBrutes": "Cet EC relève de l'unité d'enseignement  (UE31) et contribue aux compétences suivantes :  - Mettre en œuvre des composants électroniques analogiques et/ou numériques et identifier leur fonction au sein d'un montage (niveau 1)  --- Capacité : Etre capable de concevoir et d'analyser des systèmes en logique combinatoire --- Capacité : Etre capable de réaliser des fonctions de multiplexage et démultiplexage  --- Connaissance : Algèbre booléenne, Opérateurs et fonctions logiques de base, leurs propriétés --- Connaissance : Fonctions séquentielles et leurs synthèses --- Connaissance : Technologie des composants  - Concevoir et réaliser des systèmes électroniques pour l'acquisition, le traitement, la commande et la communication de données (niveau 2)  --- Capacité : Etre capable de formaliser et simplifier des systèmes en logique combinatoire --- Capacité : Etre capable de concevoir et d'analyser des systèmes en logique combinatoire --- Capacité : Etre capable de réaliser des fonctions en logique combinatoire avec des composants standards --- Capacité : Etre capable de réaliser des fonctions de multiplexage et démultiplexage --- Capacité : Etre capable de formaliser et simplifier des systèmes en logique séquentielle --- Capacité : Etre capable de concevoir et analyser des systèmes en logique séquentielle  --- Connaissance : Algèbre booléenne, Opérateurs et fonctions logiques de base, leurs propriétés --- Connaissance : Systèmes de numérations, bases --- Connaissance : Fonctions séquentielles et leurs synthèses --- Connaissance : Eléments constitutifs des systèmes logiques séquentiels  - Concevoir et développer des logiciels haut et bas niveau pour des systèmes (traitement et gestion de l'information) (niveau 1)  --- Capacité : Etre capable d'appréhender les outils informatiques de l'ingénieur --- Capacité : Etre capable de développer des logiciels de haut niveau  --- Connaissance : Syntaxe élémentaire du langage C/C++ --- Connaissance : Algorithmes standards  (tri, manipulation de tableaux et matrices)",
              "capacite": [
                "Capacité : Etre capable de concevoir et d'analyser des systèmes en logique combinatoire",
                "Capacité : Etre capable de réaliser des fonctions de multiplexage et démultiplexage",
                "Capacité : Etre capable de formaliser et simplifier des systèmes en logique combinatoire",
                "Capacité : Etre capable de concevoir et d'analyser des systèmes en logique combinatoire",
                "Capacité : Etre capable de réaliser des fonctions en logique combinatoire avec des composants standards",
                "Capacité : Etre capable de réaliser des fonctions de multiplexage et démultiplexage",
                "Capacité : Etre capable de formaliser et simplifier des systèmes en logique séquentielle",
                "Capacité : Etre capable de concevoir et analyser des systèmes en logique séquentielle",
                "Capacité : Etre capable d'appréhender les outils informatiques de l'ingénieur",
                "Capacité : Etre capable de développer des logiciels de haut niveau"
              ],
              "connaissance": [
                "Connaissance : Algèbre booléenne, Opérateurs et fonctions logiques de base, leurs propriétés",
                "Connaissance : Fonctions séquentielles et leurs synthèses",
                "Connaissance : Technologie des composants",
                "Connaissance : Algèbre booléenne, Opérateurs et fonctions logiques de base, leurs propriétés",
                "Connaissance : Systèmes de numérations, bases",
                "Connaissance : Fonctions séquentielles et leurs synthèses",
                "Connaissance : Eléments constitutifs des systèmes logiques séquentiels",
                "Connaissance : Syntaxe élémentaire du langage C/C++",
                "Connaissance : Algorithmes standards  (tri, manipulation de tableaux et matrices)"
              ],
              "competenceToCapaciteEtConnaissance": {
                "GEA-C1": [
                  "Capacité : Etre capable de concevoir et d'analyser des systèmes en logique combinatoire",
                  "Capacité : Etre capable de réaliser des fonctions de multiplexage et démultiplexage",
                  "Connaissance : Algèbre booléenne, Opérateurs et fonctions logiques de base, leurs propriétés",
                  "Connaissance : Fonctions séquentielles et leurs synthèses",
                  "Connaissance : Technologie des composants"
                ],
                "GEA-C5": [
                  "Capacité : Etre capable de formaliser et simplifier des systèmes en logique combinatoire",
                  "Capacité : Etre capable de concevoir et d'analyser des systèmes en logique combinatoire",
                  "Capacité : Etre capable de réaliser des fonctions en logique combinatoire avec des composants standards",
                  "Capacité : Etre capable de réaliser des fonctions de multiplexage et démultiplexage",
                  "Capacité : Etre capable de formaliser et simplifier des systèmes en logique séquentielle",
                  "Capacité : Etre capable de concevoir et analyser des systèmes en logique séquentielle",
                  "Connaissance : Algèbre booléenne, Opérateurs et fonctions logiques de base, leurs propriétés",
                  "Connaissance : Systèmes de numérations, bases",
                  "Connaissance : Fonctions séquentielles et leurs synthèses",
                  "Connaissance : Eléments constitutifs des systèmes logiques séquentiels"
                ],
                "GEA-C7": [
                  "Capacité : Etre capable d'appréhender les outils informatiques de l'ingénieur",
                  "Capacité : Etre capable de développer des logiciels de haut niveau",
                  "Connaissance : Syntaxe élémentaire du langage C/C++",
                  "Connaissance : Algorithmes standards  (tri, manipulation de tableaux et matrices)"
                ]
              },
              "listeComp": [
                {
                  "code": "C1",
                  "val": "Mettre en œuvre des composants électroniques analogiques et/ou numériques et identifier leur fonction au sein d'un montage",
                  "valAnglais": "Implement analog and / or digital electronic components and identify their function within an assembly",
                  "niveau": "1"
                },
                {
                  "code": "C5",
                  "val": "Concevoir et réaliser des systèmes électroniques pour l'acquisition, le traitement, la commande et la communication de données",
                  "valAnglais": "Design and build electronic systems for data acquisition, processing, control and communication",
                  "niveau": "2"
                },
                {
                  "code": "C7",
                  "val": "Concevoir et développer des logiciels haut et bas niveau pour des systèmes (traitement et gestion de l'information)",
                  "valAnglais": "Design and develop high and low level software for systems (information processing and management)",
                  "niveau": "1"
                }
              ]
            }
          },
          {
            "UE": "Enseignements techniques (GEA-3-UE32)",
            "url": "http://planete.insa-lyon.fr/scolpeda/f/ects?id=39236&_lang=fr",
            "detail": {
              "code": "GEA-3-ETEP0",
              "ects": "1.0",
              "cours": "15.0 h",
              "td": "15.0 h",
              "tp": "0.0 h",
              "projet": "0.0 h",
              "perso": "0.0 h",
              "nom": "Electrotechnique et Electronique de Puissance : Electrotechnique et Electronique de puissance - Remise à niveau",
              "competencesBrutes": "Cet EC relève de l'unité d'enseignement  (UE32) et contribue aux compétences suivantes :  - Mettre en œuvre les propriétés physiques des matériaux pour le domaine du génie électrique (niveau 2)  --- Capacité : Mettre en œuvre des matériaux ferromagnétiques en régime continu --- Capacité : Modéliser un circuit magnétique en régime continu --- Capacité : Mettre en œuvre des aimants permanents dans des circuits magnétiques --- Capacité : Mettre en œuvre et dimensionner une inductance  --- Connaissance : Relations qui couplent l'électrocinétique et le magnétisme --- Connaissance : Relations qui expliquent les forces d'interaction  - Mettre en œuvre les différents éléments de production d'énergie, de transport d'énergie électrique et de conversion d'énergie (niveau 1)  --- Capacité : Mettre en œuvre différents dipôles linéaires dans un circuit en monophasé et triphasé --- Capacité : Mettre en œuvre des circuits à une ou plusieurs mailles en monophasé et triphasé --- Capacité : Mettre en œuvre des circuits à une ou plusieurs mailles en monophasé et triphasé --- Capacité : Identifier les schémas de mise à la terre (SLT)  --- Connaissance : Calculs des courants de ligne, des puissances apparentes, actives et réactives en monophasé et triphasé --- Connaissance : Caractérisation et classification des schémas de mise à la terre",
              "capacite": [
                "Capacité : Mettre en œuvre des matériaux ferromagnétiques en régime continu",
                "Capacité : Modéliser un circuit magnétique en régime continu",
                "Capacité : Mettre en œuvre des aimants permanents dans des circuits magnétiques",
                "Capacité : Mettre en œuvre et dimensionner une inductance",
                "Capacité : Mettre en œuvre différents dipôles linéaires dans un circuit en monophasé et triphasé",
                "Capacité : Mettre en œuvre des circuits à une ou plusieurs mailles en monophasé et triphasé",
                "Capacité : Mettre en œuvre des circuits à une ou plusieurs mailles en monophasé et triphasé",
                "Capacité : Identifier les schémas de mise à la terre (SLT)"
              ],
              "connaissance": [
                "Connaissance : Relations qui couplent l'électrocinétique et le magnétisme",
                "Connaissance : Relations qui expliquent les forces d'interaction",
                "Connaissance : Calculs des courants de ligne, des puissances apparentes, actives et réactives en monophasé et triphasé",
                "Connaissance : Caractérisation et classification des schémas de mise à la terre"
              ],
              "competenceToCapaciteEtConnaissance": {
                "GEA-C2": [
                  "Capacité : Mettre en œuvre des matériaux ferromagnétiques en régime continu",
                  "Capacité : Modéliser un circuit magnétique en régime continu",
                  "Capacité : Mettre en œuvre des aimants permanents dans des circuits magnétiques",
                  "Capacité : Mettre en œuvre et dimensionner une inductance",
                  "Connaissance : Relations qui couplent l'électrocinétique et le magnétisme",
                  "Connaissance : Relations qui expliquent les forces d'interaction"
                ],
                "GEA-C3": [
                  "Capacité : Mettre en œuvre différents dipôles linéaires dans un circuit en monophasé et triphasé",
                  "Capacité : Mettre en œuvre des circuits à une ou plusieurs mailles en monophasé et triphasé",
                  "Capacité : Mettre en œuvre des circuits à une ou plusieurs mailles en monophasé et triphasé",
                  "Capacité : Identifier les schémas de mise à la terre (SLT)",
                  "Connaissance : Calculs des courants de ligne, des puissances apparentes, actives et réactives en monophasé et triphasé",
                  "Connaissance : Caractérisation et classification des schémas de mise à la terre"
                ]
              },
              "listeComp": [
                {
                  "code": "C2",
                  "val": "Mettre en œuvre les propriétés physiques des matériaux pour le domaine du génie électrique",
                  "valAnglais": "Implement the physical properties of materials for the field of electrical engineering",
                  "niveau": "2"
                },
                {
                  "code": "C3",
                  "val": "Mettre en œuvre les différents éléments de production d'énergie, de transport d'énergie électrique et de conversion d'énergie",
                  "valAnglais": "Implement the various elements of energy production, transport of electrical energy and energy conversion",
                  "niveau": "1"
                }
              ]
            }
          },
          {
            "UE": "Enseignements techniques (GEA-3-UE32)",
            "url": "http://planete.insa-lyon.fr/scolpeda/f/ects?id=39238&_lang=fr",
            "detail": {
              "code": "GEA-3-EC0",
              "ects": "2.0",
              "cours": "15.0 h",
              "td": "15.0 h",
              "tp": "12.0 h",
              "projet": "0.0 h",
              "perso": "0.0 h",
              "nom": "Electronique : Electronique et capteurs - Remise à niveau",
              "competencesBrutes": "Cet EC relève de l'unité d'enseignement (UE32) et contribue aux compétences suivantes :  - Mettre en œuvre des composants électroniques analogiques et/ou numériques et identifier leur fonction au sein d'un montage (niveau 2)  --- Capacité : Appliquer les lois fondamentales de l'électricité --- Capacité : Représenter sous la forme de quadripôle --- Capacité : Simuler des circuits électroniques --- Capacité : Mesurer des quantités électriques au sein des circuits électroniques --- Capacité : Analyser et concevoir des montages amplificateurs avec AOP --- Capacité : Appréhender l'adaptation en impédance des circuits électroniques --- Capacité : Analyser des filtres --- Capacité : Concevoir des filtres --- Capacité : Représenter sous la forme d'un diagramme de Bode  ---  Connaissance : Identifier la structure fonctionnelle d'une chaîne électronique ---  Connaissance : Types de filtre",
              "capacite": [
                "Capacité : Appliquer les lois fondamentales de l'électricité",
                "Capacité : Représenter sous la forme de quadripôle",
                "Capacité : Simuler des circuits électroniques",
                "Capacité : Mesurer des quantités électriques au sein des circuits électroniques",
                "Capacité : Analyser et concevoir des montages amplificateurs avec AOP",
                "Capacité : Appréhender l'adaptation en impédance des circuits électroniques",
                "Capacité : Analyser des filtres",
                "Capacité : Concevoir des filtres",
                "Capacité : Représenter sous la forme d'un diagramme de Bode"
              ],
              "connaissance": [
                "Connaissance : Identifier la structure fonctionnelle d'une chaîne électronique",
                "Connaissance : Types de filtre"
              ],
              "competenceToCapaciteEtConnaissance": {
                "GEA-C1": [
                  "Capacité : Appliquer les lois fondamentales de l'électricité",
                  "Capacité : Représenter sous la forme de quadripôle",
                  "Capacité : Simuler des circuits électroniques",
                  "Capacité : Mesurer des quantités électriques au sein des circuits électroniques",
                  "Capacité : Analyser et concevoir des montages amplificateurs avec AOP",
                  "Capacité : Appréhender l'adaptation en impédance des circuits électroniques",
                  "Capacité : Analyser des filtres",
                  "Capacité : Concevoir des filtres",
                  "Capacité : Représenter sous la forme d'un diagramme de Bode",
                  "Connaissance : Identifier la structure fonctionnelle d'une chaîne électronique",
                  "Connaissance : Types de filtre"
                ]
              },
              "listeComp": [
                {
                  "code": "C1",
                  "val": "Mettre en œuvre des composants électroniques analogiques et/ou numériques et identifier leur fonction au sein d'un montage",
                  "valAnglais": "Implement analog and / or digital electronic components and identify their function within an assembly",
                  "niveau": "2"
                }
              ]
            }
          },
          {
            "UE": "Enseignements techniques (GEA-3-UE32)",
            "url": "http://planete.insa-lyon.fr/scolpeda/f/ects?id=39239&_lang=fr",
            "detail": {
              "code": "GEA-3-ETEP1",
              "ects": "2.0",
              "cours": "12.0 h",
              "td": "12.0 h",
              "tp": "12.0 h",
              "projet": "0.0 h",
              "perso": "0.0 h",
              "nom": "Electrotechnique et Electronique de Puissance : Electrotechnique et Electronique de puissance - Niveau 1",
              "competencesBrutes": "Cet EC relève de l'unité d'enseignement  (UE32) et contribue aux compétences suivantes :  - Mettre en œuvre des composants électroniques analogiques et/ou numériques et identifier leur fonction au sein d'un montage (niveau 2)  --- Capacité : Mettre en œuvre un redresseur fonctionnant en quatre quadrants --- Capacité : Caractériser les séquences de fonctionnement en conduction continue ou discontinue --- Capacité : Choisir les composants de puissance à mettre en œuvre dans un redresseur  --- Connaissance : Topologie des montages redresseur à diode ou thyristor --- Connaissance : Perturbations harmoniques induites par un redresseur --- Connaissance : Principales méthodes de commande d'un redresseur à thyristors.  - Mettre en œuvre les différents éléments de production d'énergie, de transport d'énergie électrique et de conversion d'énergie (niveau 2)  -- Sous compétence : Mettre en œuvre les machines à courant continu : Machines à excitation shunt et série  --- Capacité : Modéliser le fonctionnement en régime permanent d'un système entrainé par une machine électrique --- Capacité : Calculer les grandeurs électriques dans les  enroulements d'une machine --- Capacité : Câbler, démarrer, contôler la vitesse d'une machine électrique  --- Connaissance : Connaitre  la constitution et le principe de fonctionnement --- Connaissance : Comprendre les interaction entre la machine tournante et le système mécanique associé dans les quatre quadrants --- Connaissance : Connaitre les schémas équivalents en régime permanent  De plus, elle nécessite de mobiliser les compétences suivantes :  -- Analyser un système (ou un problème) réel ou virtuel -- Exploiter un modèle d'un système réel ou virtuel -- Mettre en œuvre une démarche expérimentale -- Concevoir un système répondant à un cahier des charges -- Traiter des données -- Communiquer une analyse ou une démarche scientifique -- Se connaître, se gérer physiquement et mentalement -- Travailler, apprendre, évoluer de manière autonome -- Interagir avec les autres, travailler en équipe -- Faire preuve de créativité, innover, entreprendre -- Travailler dans un contexte international et interculturel",
              "capacite": [
                "Capacité : Mettre en œuvre un redresseur fonctionnant en quatre quadrants",
                "Capacité : Caractériser les séquences de fonctionnement en conduction continue ou discontinue",
                "Capacité : Choisir les composants de puissance à mettre en œuvre dans un redresseur",
                "Capacité : Modéliser le fonctionnement en régime permanent d'un système entrainé par une machine électrique",
                "Capacité : Calculer les grandeurs électriques dans les  enroulements d'une machine",
                "Capacité : Câbler, démarrer, contôler la vitesse d'une machine électrique"
              ],
              "connaissance": [
                "Connaissance : Topologie des montages redresseur à diode ou thyristor",
                "Connaissance : Perturbations harmoniques induites par un redresseur",
                "Connaissance : Principales méthodes de commande d'un redresseur à thyristors.",
                "Connaissance : Connaitre  la constitution et le principe de fonctionnement",
                "Connaissance : Comprendre les interaction entre la machine tournante et le système mécanique associé dans les quatre quadrants",
                "Connaissance : Connaitre les schémas équivalents en régime permanent"
              ],
              "competenceToCapaciteEtConnaissance": {
                "GEA-C1": [
                  "Capacité : Mettre en œuvre un redresseur fonctionnant en quatre quadrants",
                  "Capacité : Caractériser les séquences de fonctionnement en conduction continue ou discontinue",
                  "Capacité : Choisir les composants de puissance à mettre en œuvre dans un redresseur",
                  "Connaissance : Topologie des montages redresseur à diode ou thyristor",
                  "Connaissance : Perturbations harmoniques induites par un redresseur",
                  "Connaissance : Principales méthodes de commande d'un redresseur à thyristors."
                ],
                "GEA-C3": [
                  "Capacité : Modéliser le fonctionnement en régime permanent d'un système entrainé par une machine électrique",
                  "Capacité : Calculer les grandeurs électriques dans les  enroulements d'une machine",
                  "Capacité : Câbler, démarrer, contôler la vitesse d'une machine électrique",
                  "Connaissance : Connaitre  la constitution et le principe de fonctionnement",
                  "Connaissance : Comprendre les interaction entre la machine tournante et le système mécanique associé dans les quatre quadrants",
                  "Connaissance : Connaitre les schémas équivalents en régime permanent"
                ]
              },
              "listeComp": [
                {
                  "code": "C1",
                  "val": "Mettre en œuvre des composants électroniques analogiques et/ou numériques et identifier leur fonction au sein d'un montage",
                  "valAnglais": "Implement analog and / or digital electronic components and identify their function within an assembly",
                  "niveau": "2"
                },
                {
                  "code": "C3",
                  "val": "Mettre en œuvre les différents éléments de production d'énergie, de transport d'énergie électrique et de conversion d'énergie",
                  "valAnglais": "Implement the various elements of energy production, transport of electrical energy and energy conversion",
                  "niveau": "2"
                }
              ],
              "listeCompMobilise": [
                "Analyser un système (ou un problème) réel ou virtuel",
                "Exploiter un modèle d'un système réel ou virtuel",
                "Mettre en œuvre une démarche expérimentale",
                "Concevoir un système répondant à un cahier des charges",
                "Traiter des données",
                "Communiquer une analyse ou une démarche scientifique",
                "Se connaître, se gérer physiquement et mentalement",
                "Travailler, apprendre, évoluer de manière autonome",
                "Interagir avec les autres, travailler en équipe",
                "Faire preuve de créativité, innover, entreprendre",
                "Travailler dans un contexte international et interculturel"
              ]
            }
          },
          {
            "UE": "Enseignements techniques (GEA-3-UE32)",
            "url": "http://planete.insa-lyon.fr/scolpeda/f/ects?id=37340&_lang=fr",
            "detail": {
              "code": "GEA-3-EC1",
              "ects": "2.0",
              "cours": "18.0 h",
              "td": "18.0 h",
              "tp": "9.0 h",
              "projet": "0.0 h",
              "perso": "0.0 h",
              "nom": "Electronique : Electronique et capteurs - 1ère partie",
              "competencesBrutes": "Cet EC relève de l'unité d'enseignement  (UE32) et contribue aux compétences suivantes :  - Mettre en œuvre des composants électroniques analogiques et/ou numériques et identifier leur fonction au sein d'un montage (niveau 2)  -- Sous compétence : Mettre en œuvre des circuits électroniques  --- Capacité : Appliquer les lois fondamentales de l'électricité --- Capacité : Représenter sous la forme de quadripôle --- Capacité : Simuler des circuits électroniques --- Capacité : Mesurer des quantités électriques au sein des circuits électroniques  --- Connaissance : Identifier la structure fonctionnelle d'une chaîne électronique  -- Sous compétence : Mettre en œuvre des filtres passifs  --- Capacité : Analyser des filtres --- Capacité : Représenter sous la forme d'un diagramme de Bode  --- Connaissance : Types de filtre  -- Sous compétence : Mettre en œuvre les transistors bipolaires  --- Capacité : Sélectionner, dimensionner et interfacer des montages à transistors pour répondre à un cahier des charges --- Capacité : Identifier les blocs constitutifs dans un circuit complexe à transistors et quantifier leurs performances  --- Connaissance : Circuits fondamentaux à base de transistors  - Mettre en œuvre les propriétés physiques des matériaux pour le domaine du génie électrique (niveau 1)  -- Sous compétence : Mettre en œuvre le transistor bipolaire  --- Capacité : Etablir la loi de comportement d'un composant --- Capacité : Etablir le point de fonctionnemenbt d'un composant --- Capacité : Etablir un modèle linéarisé d'un composant  --- Connaissance : Fonctionnement d'une diode et du transitor bipolaire --- Connaissance : Polarisation et régimes dynamique et petits signaux  De plus, elle nécessite de mobiliser les compétences suivantes :  -- Analyser un système (ou un problème) réel ou virtuel -- Exploiter un modèle d'un système réel ou virtuel -- Mettre en œuvre une démarche expérimentale -- Traiter des données -- Communiquer une analyse ou une démarche scientifique -- Agir de manière responsable dans un monde complexe",
              "capacite": [
                "Capacité : Appliquer les lois fondamentales de l'électricité",
                "Capacité : Représenter sous la forme de quadripôle",
                "Capacité : Simuler des circuits électroniques",
                "Capacité : Mesurer des quantités électriques au sein des circuits électroniques",
                "Capacité : Analyser des filtres",
                "Capacité : Représenter sous la forme d'un diagramme de Bode",
                "Capacité : Sélectionner, dimensionner et interfacer des montages à transistors pour répondre à un cahier des charges",
                "Capacité : Identifier les blocs constitutifs dans un circuit complexe à transistors et quantifier leurs performances",
                "Capacité : Etablir la loi de comportement d'un composant",
                "Capacité : Etablir le point de fonctionnemenbt d'un composant",
                "Capacité : Etablir un modèle linéarisé d'un composant"
              ],
              "connaissance": [
                "Connaissance : Identifier la structure fonctionnelle d'une chaîne électronique",
                "Connaissance : Types de filtre",
                "Connaissance : Circuits fondamentaux à base de transistors",
                "Connaissance : Fonctionnement d'une diode et du transitor bipolaire",
                "Connaissance : Polarisation et régimes dynamique et petits signaux"
              ],
              "competenceToCapaciteEtConnaissance": {
                "GEA-C1": [
                  "Capacité : Appliquer les lois fondamentales de l'électricité",
                  "Capacité : Représenter sous la forme de quadripôle",
                  "Capacité : Simuler des circuits électroniques",
                  "Capacité : Mesurer des quantités électriques au sein des circuits électroniques",
                  "Connaissance : Identifier la structure fonctionnelle d'une chaîne électronique",
                  "Capacité : Analyser des filtres",
                  "Capacité : Représenter sous la forme d'un diagramme de Bode",
                  "Connaissance : Types de filtre",
                  "Capacité : Sélectionner, dimensionner et interfacer des montages à transistors pour répondre à un cahier des charges",
                  "Capacité : Identifier les blocs constitutifs dans un circuit complexe à transistors et quantifier leurs performances",
                  "Connaissance : Circuits fondamentaux à base de transistors"
                ],
                "GEA-C2": [
                  "Capacité : Etablir la loi de comportement d'un composant",
                  "Capacité : Etablir le point de fonctionnemenbt d'un composant",
                  "Capacité : Etablir un modèle linéarisé d'un composant",
                  "Connaissance : Fonctionnement d'une diode et du transitor bipolaire",
                  "Connaissance : Polarisation et régimes dynamique et petits signaux"
                ]
              },
              "listeComp": [
                {
                  "code": "C1",
                  "val": "Mettre en œuvre des composants électroniques analogiques et/ou numériques et identifier leur fonction au sein d'un montage",
                  "valAnglais": "Implement analog and / or digital electronic components and identify their function within an assembly",
                  "niveau": "2"
                },
                {
                  "code": "C2",
                  "val": "Mettre en œuvre les propriétés physiques des matériaux pour le domaine du génie électrique",
                  "valAnglais": "Implement the physical properties of materials for the field of electrical engineering",
                  "niveau": "1"
                }
              ],
              "listeCompMobilise": [
                "Analyser un système (ou un problème) réel ou virtuel",
                "Exploiter un modèle d'un système réel ou virtuel",
                "Mettre en œuvre une démarche expérimentale",
                "Traiter des données",
                "Communiquer une analyse ou une démarche scientifique",
                "Agir de manière responsable dans un monde complexe"
              ]
            }
          },
          {
            "UE": "Humanités et Education sportive (GEA-3-UE33)",
            "url": "http://planete.insa-lyon.fr/scolpeda/f/ects?id=39576&_lang=fr",
            "detail": {
              "code": "GEA-3-EPS1",
              "ects": "1.0",
              "cours": "0.0 h",
              "td": "15.0 h",
              "tp": "0.0 h",
              "projet": "0.0 h",
              "perso": "0.0 h"
            }
          },
          {
            "UE": "Humanités et Education sportive (GEA-3-UE33)",
            "url": "http://planete.insa-lyon.fr/scolpeda/f/ects?id=38565&_lang=fr",
            "detail": {
              "code": "GEA-3-LA1",
              "ects": "2.0",
              "cours": "0.0 h",
              "td": "36.0 h",
              "tp": "0.0 h",
              "projet": "0.0 h",
              "perso": "0.0 h",
              "nom": "Langues Étrangères : Langues vivantes - Premier Semestre",
              "competencesBrutes": "Cet EC relève de l'unité d'enseignement  (UE33) et contribue aux compétences suivantes :  -- Travailler dans un contexte international et interculturel (niveau 2)  --- Capacité : Etre capable de présenter son entreprise son activité --- Capacité : Etre capable de présenter un sujet technique à l'oral et à l'écrit  --- Connaissance : Expression orale dans un contexte professionnel --- Connaissance : Rédaction de fiches techniques et exposés",
              "capacite": [
                "Capacité : Etre capable de présenter son entreprise son activité",
                "Capacité : Etre capable de présenter un sujet technique à l'oral et à l'écrit"
              ],
              "connaissance": [
                "Connaissance : Expression orale dans un contexte professionnel",
                "Connaissance : Rédaction de fiches techniques et exposés"
              ],
              "competenceToCapaciteEtConnaissance": {
                "B7": [
                  "Capacité : Etre capable de présenter son entreprise son activité",
                  "Capacité : Etre capable de présenter un sujet technique à l'oral et à l'écrit",
                  "Connaissance : Expression orale dans un contexte professionnel",
                  "Connaissance : Rédaction de fiches techniques et exposés"
                ]
              },
              "listeComp": [
                {
                  "code": "B7",
                  "val": "Travailler dans un contexte international et interculturel",
                  "valAnglais": "Work in an international, intercultural context",
                  "bs": "29",
                  "niveau": "2"
                }
              ]
            }
          },
          {
            "UE": "Humanités et Education sportive (GEA-3-UE33)",
            "url": "http://planete.insa-lyon.fr/scolpeda/f/ects?id=39475&_lang=fr",
            "detail": {
              "code": "GEA-3-SHS1",
              "ects": "2.0",
              "cours": "0.0 h",
              "td": "48.0 h",
              "tp": "0.0 h",
              "projet": "0.0 h",
              "perso": "0.0 h",
              "nom": "Sciences Humaines et Sociales : Approche globale de l'entreprise - Economie",
              "competencesBrutes": "Cet EC relève de l'unité d'enseignement  (UE33) et contribue aux compétences suivantes :  -- Se situer, travailler, évoluer dans une entreprise, une organisation socio-productive (niveau 1)  --- Capacité : Comprendre l'environnement économique et la nécessité de la performance --- Capacité : Comprendre la circulation des flux monétaires dans un environnement économique moderne --- Capacité : Appréhender les contraintes de l'entreprise dans la concurrence d'une économie mondialisée --- Capacité : Comprendre le fonctionnement de la bourse et de quelques mécanismes financiers permettant aux entreprises de se financer --- Capacité : Comprendre les principes fondamentaux de fonctionnement d'une entreprise --- Capacité : Comprendre et évaluer l'environnement d'une entreprise --- Capacité : Déterminer le positionnement de l'entreprise en termes de création de valeurs et de risques  --- Connaissance : Le circuit économique et les différents agents économiques --- Connaissance : Panorama de l'organisation du système productif --- Connaissance : La stratégie actuelle des entreprises face aux marchés financiers --- Connaissance : La stratégie des entreprises françaises dans le cadre de la mondialisation --- Connaissance : La régulation économique par les Etats --- Connaissance : Définition d'une entrepriseet son fonctionnement --- Connaissance : Le diagnostic global (analyse de l'environnement et de l'entreprise) : processus et outils --- Connaissance : La stratégie d'entreprise  De plus, elle nécessite de mobiliser les compétences suivantes :  -- Communiquer une analyse ou une démarche scientifique -- Se connaître, se gérer physiquement et mentalement -- Interagir avec les autres, travailler en équipe -- Agir de manière responsable dans un monde complexe",
              "capacite": [
                "Capacité : Comprendre l'environnement économique et la nécessité de la performance",
                "Capacité : Comprendre la circulation des flux monétaires dans un environnement économique moderne",
                "Capacité : Appréhender les contraintes de l'entreprise dans la concurrence d'une économie mondialisée",
                "Capacité : Comprendre le fonctionnement de la bourse et de quelques mécanismes financiers permettant aux entreprises de se financer",
                "Capacité : Comprendre les principes fondamentaux de fonctionnement d'une entreprise",
                "Capacité : Comprendre et évaluer l'environnement d'une entreprise",
                "Capacité : Déterminer le positionnement de l'entreprise en termes de création de valeurs et de risques"
              ],
              "connaissance": [
                "Connaissance : Le circuit économique et les différents agents économiques",
                "Connaissance : Panorama de l'organisation du système productif",
                "Connaissance : La stratégie actuelle des entreprises face aux marchés financiers",
                "Connaissance : La stratégie des entreprises françaises dans le cadre de la mondialisation",
                "Connaissance : La régulation économique par les Etats",
                "Connaissance : Définition d'une entrepriseet son fonctionnement",
                "Connaissance : Le diagnostic global (analyse de l'environnement et de l'entreprise) : processus et outils",
                "Connaissance : La stratégie d'entreprise"
              ],
              "competenceToCapaciteEtConnaissance": {
                "B6": [
                  "Capacité : Comprendre l'environnement économique et la nécessité de la performance",
                  "Capacité : Comprendre la circulation des flux monétaires dans un environnement économique moderne",
                  "Capacité : Appréhender les contraintes de l'entreprise dans la concurrence d'une économie mondialisée",
                  "Capacité : Comprendre le fonctionnement de la bourse et de quelques mécanismes financiers permettant aux entreprises de se financer",
                  "Capacité : Comprendre les principes fondamentaux de fonctionnement d'une entreprise",
                  "Capacité : Comprendre et évaluer l'environnement d'une entreprise",
                  "Capacité : Déterminer le positionnement de l'entreprise en termes de création de valeurs et de risques",
                  "Connaissance : Le circuit économique et les différents agents économiques",
                  "Connaissance : Panorama de l'organisation du système productif",
                  "Connaissance : La stratégie actuelle des entreprises face aux marchés financiers",
                  "Connaissance : La stratégie des entreprises françaises dans le cadre de la mondialisation",
                  "Connaissance : La régulation économique par les Etats",
                  "Connaissance : Définition d'une entrepriseet son fonctionnement",
                  "Connaissance : Le diagnostic global (analyse de l'environnement et de l'entreprise) : processus et outils",
                  "Connaissance : La stratégie d'entreprise"
                ]
              },
              "listeComp": [
                {
                  "code": "B6",
                  "val": "Se situer, travailler, évoluer dans une entreprise, une organisation socio-productive",
                  "valAnglais": "Position oneself, work, and evolve within a company or a socio-productive organization",
                  "bs": "28",
                  "niveau": "1"
                }
              ],
              "listeCompMobilise": [
                "Communiquer une analyse ou une démarche scientifique",
                "Se connaître, se gérer physiquement et mentalement",
                "Interagir avec les autres, travailler en équipe",
                "Agir de manière responsable dans un monde complexe"
              ]
            }
          },
          {
            "UE": "Acquis en entreprise (GEA-3-UE34)",
            "url": "http://planete.insa-lyon.fr/scolpeda/f/ects?id=39629&_lang=fr",
            "detail": {
              "code": "GEA-3-PE1",
              "ects": "11.0",
              "cours": "0.0 h",
              "td": "3.5 h",
              "tp": "0.0 h",
              "projet": "0.0 h",
              "perso": "0.0 h",
              "nom": "Entreprise : Période en entreprise 1",
              "competencesBrutes": "Cet EC relève de l'unité d'enseignement  (UE34) et contribue aux compétences suivantes :  -- Se situer, travailler, évoluer dans une entreprise, une organisation socio-productive (niveau 2)  --- Capacité : Comprendre le fonctionnement global de l'entreprise et du service d'accueil. Etre capable de la représenter à l'extérieur. --- Capacité : Présenter à l'écrit comme à l'oral l'entreprise, et les spécificités de son service --- Capacité : Respecter les règles de  fonctionnement du service.  --- Connaissance : Organisation d'un milieu professionnel  -- Interagir avec les autres, travailler en équipe (niveau )  --- Capacité : Etre capable de communiquer avec des spécialistes et des non spécialistes et différents niveaux de hiérarchie. --- Capacité : Etre capable de reformuler son problème de manière claire à l'écrit comme à l'oral. Faire un reporting efficient. --- Capacité : mettre en œuvre des composants et fonctions unitaires connus ou existants.  --- Connaissance : communication, reporting --- Connaissance : Relations humaines, intégration dans équipe  De plus, elle nécessite de mobiliser les compétences suivantes :  - Mettre en œuvre ses compétences scientifiques et technologiques dans le domaine de l'EEAIIT dans un cadre industriel et appliqué à des problématiques réelles en conduisant les étapes du cycle de conception",
              "capacite": [
                "Capacité : Comprendre le fonctionnement global de l'entreprise et du service d'accueil. Etre capable de la représenter à l'extérieur.",
                "Capacité : Présenter à l'écrit comme à l'oral l'entreprise, et les spécificités de son service",
                "Capacité : Respecter les règles de  fonctionnement du service.",
                "Capacité : Etre capable de communiquer avec des spécialistes et des non spécialistes et différents niveaux de hiérarchie.",
                "Capacité : Etre capable de reformuler son problème de manière claire à l'écrit comme à l'oral. Faire un reporting efficient.",
                "Capacité : mettre en œuvre des composants et fonctions unitaires connus ou existants."
              ],
              "connaissance": [
                "Connaissance : Organisation d'un milieu professionnel  -- Interagir avec les autres, travailler en équipe (niveau )",
                "Connaissance : communication, reporting",
                "Connaissance : Relations humaines, intégration dans équipe"
              ],
              "competenceToCapaciteEtConnaissance": {
                "B6": [
                  "Capacité : Comprendre le fonctionnement global de l'entreprise et du service d'accueil. Etre capable de la représenter à l'extérieur.",
                  "Capacité : Présenter à l'écrit comme à l'oral l'entreprise, et les spécificités de son service",
                  "Capacité : Respecter les règles de  fonctionnement du service.",
                  "Connaissance : Organisation d'un milieu professionnel  -- Interagir avec les autres, travailler en équipe (niveau )",
                  "Capacité : Etre capable de communiquer avec des spécialistes et des non spécialistes et différents niveaux de hiérarchie.",
                  "Capacité : Etre capable de reformuler son problème de manière claire à l'écrit comme à l'oral. Faire un reporting efficient.",
                  "Capacité : mettre en œuvre des composants et fonctions unitaires connus ou existants.",
                  "Connaissance : communication, reporting",
                  "Connaissance : Relations humaines, intégration dans équipe"
                ]
              },
              "listeComp": [
                {
                  "code": "B6",
                  "val": "Se situer, travailler, évoluer dans une entreprise, une organisation socio-productive",
                  "valAnglais": "Position oneself, work, and evolve within a company or a socio-productive organization",
                  "bs": "28",
                  "niveau": "2"
                }
              ],
              "listeCompMobilise": [
                "Mettre en œuvre ses compétences scientifiques et technologiques dans le domaine de l'EEAIIT dans un cadre industriel et appliqué à des problématiques réelles en conduisant les étapes du cycle de conception"
              ]
            }
          }
        ]
      },
      {
        "url": "/fr/formation/parcours/1165/3/2",
        "ecs": [
          {
            "UE": "Enseignements Transversaux (GEA-3-UE35)",
            "url": "http://planete.insa-lyon.fr/scolpeda/f/ects?id=39240&_lang=fr",
            "detail": {
              "code": "GEA-3-AU1",
              "ects": "2.0",
              "cours": "14.0 h",
              "td": "14.0 h",
              "tp": "18.0 h",
              "projet": "0.0 h",
              "perso": "0.0 h",
              "nom": "Automatique : Automatique, modélisation et conception 1",
              "competencesBrutes": "Cet EC relève de l'unité d'enseignement  (UE35) et contribue aux compétences suivantes :  - Concevoir et réaliser des systèmes électroniques pour l'acquisition, le traitement, la commande et la communication de données (niveau 2)  --- Capacité : Etre capable de mettre en place un régulateur PI ou PID à partir d'un système électronique analogique ou numérique  --- Connaissance : Connaître le comportement d'éléments de base utilisés pour la commande (mécanique, électrique et pneumatique)  - Mettre en œuvre les étapes permettant le contrôle du fonctionnement d'un système discret ou continu (niveau 2)  --- Capacité : Etre capable de rédiger un GRAFCET et un cahier des charges sous forme d'analyse fonctionnelle (GEMMA) --- Capacité : Etre capable de modéliser des systèmes physiques par Bond-Graph, équations différentielles, fonctions de transfert et représentations d'état --- Capacité : Etre capable d'analyser des systèmes linéaires, schémas blocs, en boucle ouverte / boucle fermée --- Capacité : Etre capable d'analyser la stabilité : carte des pôles et zéros, Critère algébrique (Routh), Lieu d'Evans --- Capacité : Etre capable de régler les paramètres d'un correcteur par calcul ou éxpérimentalement  --- Connaissance : Connaître des généralités sur l'Automatique et les technologies mécatroniques --- Connaissance : Connaître les modes de représentations et d'analyses temporelle et fréquentielle de systèmes du premier et du second ordres --- Connaissance : Connaître les critères de stabilité des systèmes bouclés : Critère de Nyquist, Critère du revers --- Connaissance : Connaître les structures élémentaires des correcteurs : P, PI, PD, avance de phase, retard de phase, PID, PID filtré  - Concevoir et développer des logiciels haut et bas niveau pour des systèmes (traitement et gestion de l'information) (niveau 1)  --- Capacité : Etre capable d'utiliser les fonctions de base du logiciel Unity pour mettre en place une commande dans un automate programmable industriel --- Capacité : Etre capable d'utiliser Matlab et Simulink pour faire des simulations temporelles simples et des analyses fréquentielles  --- Connaissance : Connaître les bases de certains outils logiciels industriels d'Automatique : Matlab-Simulink, Unity Pro --- Connaissance : Connaître les notions de base de la norme IEC 61131-3  De plus, elle nécessite de mobiliser les compétences suivantes :  -- Analyser un système (ou un problème) réel ou virtuel -- Exploiter un modèle d'un système réel ou virtuel -- Mettre en œuvre une démarche expérimentale -- Concevoir un système répondant à un cahier des charges -- Traiter des données -- Communiquer une analyse ou une démarche scientifique -- Agir de manière responsable dans un monde complexe -- Se situer, travailler, évoluer dans une entreprise, une organisation socio-productive  http://www.insa-lyon.fr   INSA LYON Campus LyonTech La Doua 20, avenue Albert Einstein - 69621 Villeurbanne cedex - France Tel. +33 (0)4 72 43 83 83 - Fax +33 (0)4 72 43 85 00 www.insa-lyon.fr  Dernière modification le : 4 octobre 2019 2",
              "capacite": [
                "Capacité : Etre capable de mettre en place un régulateur PI ou PID à partir d'un système électronique analogique ou numérique",
                "Capacité : Etre capable de rédiger un GRAFCET et un cahier des charges sous forme d'analyse fonctionnelle (GEMMA)",
                "Capacité : Etre capable de modéliser des systèmes physiques par Bond-Graph, équations différentielles, fonctions de transfert et représentations d'état",
                "Capacité : Etre capable d'analyser des systèmes linéaires, schémas blocs, en boucle ouverte / boucle fermée",
                "Capacité : Etre capable d'analyser la stabilité : carte des pôles et zéros, Critère algébrique (Routh), Lieu d'Evans",
                "Capacité : Etre capable de régler les paramètres d'un correcteur par calcul ou éxpérimentalement",
                "Capacité : Etre capable d'utiliser les fonctions de base du logiciel Unity pour mettre en place une commande dans un automate programmable industriel",
                "Capacité : Etre capable d'utiliser Matlab et Simulink pour faire des simulations temporelles simples et des analyses fréquentielles"
              ],
              "connaissance": [
                "Connaissance : Connaître le comportement d'éléments de base utilisés pour la commande (mécanique, électrique et pneumatique)",
                "Connaissance : Connaître des généralités sur l'Automatique et les technologies mécatroniques",
                "Connaissance : Connaître les modes de représentations et d'analyses temporelle et fréquentielle de systèmes du premier et du second ordres",
                "Connaissance : Connaître les critères de stabilité des systèmes bouclés : Critère de Nyquist, Critère du revers",
                "Connaissance : Connaître les structures élémentaires des correcteurs : P, PI, PD, avance de phase, retard de phase, PID, PID filtré",
                "Connaissance : Connaître les bases de certains outils logiciels industriels d'Automatique : Matlab-Simulink, Unity Pro",
                "Connaissance : Connaître les notions de base de la norme IEC 61131-3"
              ],
              "competenceToCapaciteEtConnaissance": {
                "GEA-C5": [
                  "Capacité : Etre capable de mettre en place un régulateur PI ou PID à partir d'un système électronique analogique ou numérique",
                  "Connaissance : Connaître le comportement d'éléments de base utilisés pour la commande (mécanique, électrique et pneumatique)"
                ],
                "GEA-C6": [
                  "Capacité : Etre capable de rédiger un GRAFCET et un cahier des charges sous forme d'analyse fonctionnelle (GEMMA)",
                  "Capacité : Etre capable de modéliser des systèmes physiques par Bond-Graph, équations différentielles, fonctions de transfert et représentations d'état",
                  "Capacité : Etre capable d'analyser des systèmes linéaires, schémas blocs, en boucle ouverte / boucle fermée",
                  "Capacité : Etre capable d'analyser la stabilité : carte des pôles et zéros, Critère algébrique (Routh), Lieu d'Evans",
                  "Capacité : Etre capable de régler les paramètres d'un correcteur par calcul ou éxpérimentalement",
                  "Connaissance : Connaître des généralités sur l'Automatique et les technologies mécatroniques",
                  "Connaissance : Connaître les modes de représentations et d'analyses temporelle et fréquentielle de systèmes du premier et du second ordres",
                  "Connaissance : Connaître les critères de stabilité des systèmes bouclés : Critère de Nyquist, Critère du revers",
                  "Connaissance : Connaître les structures élémentaires des correcteurs : P, PI, PD, avance de phase, retard de phase, PID, PID filtré"
                ],
                "GEA-C7": [
                  "Capacité : Etre capable d'utiliser les fonctions de base du logiciel Unity pour mettre en place une commande dans un automate programmable industriel",
                  "Capacité : Etre capable d'utiliser Matlab et Simulink pour faire des simulations temporelles simples et des analyses fréquentielles",
                  "Connaissance : Connaître les bases de certains outils logiciels industriels d'Automatique : Matlab-Simulink, Unity Pro",
                  "Connaissance : Connaître les notions de base de la norme IEC 61131-3"
                ]
              },
              "listeComp": [
                {
                  "code": "C5",
                  "val": "Concevoir et réaliser des systèmes électroniques pour l'acquisition, le traitement, la commande et la communication de données",
                  "valAnglais": "Design and build electronic systems for data acquisition, processing, control and communication",
                  "niveau": "2"
                },
                {
                  "code": "C6",
                  "val": "Mettre en œuvre les étapes permettant le contrôle du fonctionnement d'un système discret ou continu",
                  "valAnglais": "Implement steps to control the operation of a discrete or continuous system",
                  "niveau": "2"
                },
                {
                  "code": "C7",
                  "val": "Concevoir et développer des logiciels haut et bas niveau pour des systèmes (traitement et gestion de l'information)",
                  "valAnglais": "Design and develop high and low level software for systems (information processing and management)",
                  "niveau": "1"
                }
              ],
              "listeCompMobilise": [
                "Analyser un système (ou un problème) réel ou virtuel",
                "Exploiter un modèle d'un système réel ou virtuel",
                "Mettre en œuvre une démarche expérimentale",
                "Concevoir un système répondant à un cahier des charges",
                "Traiter des données",
                "Communiquer une analyse ou une démarche scientifique",
                "Agir de manière responsable dans un monde complexe",
                "Se situer, travailler, évoluer dans une entreprise, une organisation socio-productive"
              ]
            }
          },
          {
            "UE": "Enseignements Transversaux (GEA-3-UE35)",
            "url": "http://planete.insa-lyon.fr/scolpeda/f/ects?id=38568&_lang=fr",
            "detail": {
              "code": "GEA-3-MA12",
              "ects": "3.0",
              "cours": "32.5 h",
              "td": "32.5 h",
              "tp": "0.0 h",
              "projet": "0.0 h",
              "perso": "0.0 h",
              "nom": "Mathématiques : Mathématiques pour l'ingénieur - niveau 2",
              "competencesBrutes": "A l'issue de cet enseignement, l'étudiant sera capable choisir et d'utiliser des bibliothèques existantes de résolution numérique de problèmes complexes.",
              "capacite": [],
              "connaissance": [],
              "competenceToCapaciteEtConnaissance": {}
            }
          },
          {
            "UE": "Enseignements Transversaux (GEA-3-UE35)",
            "url": "http://planete.insa-lyon.fr/scolpeda/f/ects?id=38571&_lang=fr",
            "detail": {
              "code": "GEA-3-TC1",
              "ects": "1.0",
              "cours": "11.0 h",
              "td": "11.0 h",
              "tp": "3.0 h",
              "projet": "0.0 h",
              "perso": "0.0 h",
              "nom": "Télécommunications : Télécommunications et Réseaux - niveau 1",
              "competencesBrutes": "Cet EC relève de l'unité d'enseignement  (UE35) et contribue aux compétences suivantes :  - Mettre en œuvre des composants électroniques analogiques et/ou numériques et identifier leur fonction au sein d'un montage (niveau 2)  --- Capacité : Conception et analyse de lignes de transmission --- Capacité : Conception de dispositifs d'adaptation  --- Connaissance : Différents types de lignes de transmission --- Connaissance : Différents régimes: sinuisoidal, impulsionnel --- Connaissance : Différents régimes d'ondes: progressive, stationnaire, etc. --- Connaissance : Abaque de Smith  - Mettre en œuvre les propriétés physiques des matériaux pour le domaine du génie électrique (niveau 2)  --- Capacité : Déterminer les caractéristiques électriques d'une ligne de transmission à partir de ses paramètres physiques  --- Connaissance : Différents types de lignes de transmission --- Connaissance : Calculs des paramètres primaires et secondaires d'une ligne de transmission --- Connaissance : Equations des télégraphistes  - Mettre en œuvre les différents éléments de production d'énergie, de transport d'énergie électrique et de conversion d'énergie (niveau 1)  --- Capacité : Savoir évaluer le transfert de puissance sur une ligne et entre des composants hautes fréquences  --- Connaissance : Ondes de puissance, coefficients de réflexion/transmission  - Concevoir et réaliser des systèmes électroniques pour l'acquisition, le traitement, la commande et la communication de données (niveau 2)  --- Capacité : Utilisation d'outils de simulation radio-fréquences --- Capacité : Manipulation des échelles décibels  --- Connaissance : Formalisme des paramètres S d'un système --- Connaissance : Outils de mesure hautes fréquences --- Connaissance : Différents types de lignes de transmission  De plus, elle nécessite de mobiliser les compétences suivantes :  -- Analyser un système (ou un problème) réel ou virtuel -- Exploiter un modèle d'un système réel ou virtuel -- Concevoir un système répondant à un cahier des charges -- Traiter des données -- Se connaître, se gérer physiquement et mentalement -- Travailler, apprendre, évoluer de manière autonome -- Interagir avec les autres, travailler en équipe",
              "capacite": [
                "Capacité : Conception et analyse de lignes de transmission",
                "Capacité : Conception de dispositifs d'adaptation",
                "Capacité : Déterminer les caractéristiques électriques d'une ligne de transmission à partir de ses paramètres physiques",
                "Capacité : Savoir évaluer le transfert de puissance sur une ligne et entre des composants hautes fréquences",
                "Capacité : Utilisation d'outils de simulation radio-fréquences",
                "Capacité : Manipulation des échelles décibels"
              ],
              "connaissance": [
                "Connaissance : Différents types de lignes de transmission",
                "Connaissance : Différents régimes: sinuisoidal, impulsionnel",
                "Connaissance : Différents régimes d'ondes: progressive, stationnaire, etc.",
                "Connaissance : Abaque de Smith",
                "Connaissance : Différents types de lignes de transmission",
                "Connaissance : Calculs des paramètres primaires et secondaires d'une ligne de transmission",
                "Connaissance : Equations des télégraphistes",
                "Connaissance : Ondes de puissance, coefficients de réflexion/transmission",
                "Connaissance : Formalisme des paramètres S d'un système",
                "Connaissance : Outils de mesure hautes fréquences",
                "Connaissance : Différents types de lignes de transmission"
              ],
              "competenceToCapaciteEtConnaissance": {
                "GEA-C1": [
                  "Capacité : Conception et analyse de lignes de transmission",
                  "Capacité : Conception de dispositifs d'adaptation",
                  "Connaissance : Différents types de lignes de transmission",
                  "Connaissance : Différents régimes: sinuisoidal, impulsionnel",
                  "Connaissance : Différents régimes d'ondes: progressive, stationnaire, etc.",
                  "Connaissance : Abaque de Smith"
                ],
                "GEA-C2": [
                  "Capacité : Déterminer les caractéristiques électriques d'une ligne de transmission à partir de ses paramètres physiques",
                  "Connaissance : Différents types de lignes de transmission",
                  "Connaissance : Calculs des paramètres primaires et secondaires d'une ligne de transmission",
                  "Connaissance : Equations des télégraphistes"
                ],
                "GEA-C3": [
                  "Capacité : Savoir évaluer le transfert de puissance sur une ligne et entre des composants hautes fréquences",
                  "Connaissance : Ondes de puissance, coefficients de réflexion/transmission"
                ],
                "GEA-C5": [
                  "Capacité : Utilisation d'outils de simulation radio-fréquences",
                  "Capacité : Manipulation des échelles décibels",
                  "Connaissance : Formalisme des paramètres S d'un système",
                  "Connaissance : Outils de mesure hautes fréquences",
                  "Connaissance : Différents types de lignes de transmission"
                ]
              },
              "listeComp": [
                {
                  "code": "C1",
                  "val": "Mettre en œuvre des composants électroniques analogiques et/ou numériques et identifier leur fonction au sein d'un montage",
                  "valAnglais": "Implement analog and / or digital electronic components and identify their function within an assembly",
                  "niveau": "2"
                },
                {
                  "code": "C2",
                  "val": "Mettre en œuvre les propriétés physiques des matériaux pour le domaine du génie électrique",
                  "valAnglais": "Implement the physical properties of materials for the field of electrical engineering",
                  "niveau": "2"
                },
                {
                  "code": "C3",
                  "val": "Mettre en œuvre les différents éléments de production d'énergie, de transport d'énergie électrique et de conversion d'énergie",
                  "valAnglais": "Implement the various elements of energy production, transport of electrical energy and energy conversion",
                  "niveau": "1"
                },
                {
                  "code": "C5",
                  "val": "Concevoir et réaliser des systèmes électroniques pour l'acquisition, le traitement, la commande et la communication de données",
                  "valAnglais": "Design and build electronic systems for data acquisition, processing, control and communication",
                  "niveau": "2"
                }
              ],
              "listeCompMobilise": [
                "Analyser un système (ou un problème) réel ou virtuel",
                "Exploiter un modèle d'un système réel ou virtuel",
                "Concevoir un système répondant à un cahier des charges",
                "Traiter des données",
                "Se connaître, se gérer physiquement et mentalement",
                "Travailler, apprendre, évoluer de manière autonome",
                "Interagir avec les autres, travailler en équipe"
              ]
            }
          },
          {
            "UE": "Enseignements techniques (GEA-3-UE36)",
            "url": "http://planete.insa-lyon.fr/scolpeda/f/ects?id=38564&_lang=fr",
            "detail": {
              "code": "GEA-3-EC2",
              "ects": "4.0",
              "cours": "24.0 h",
              "td": "24.0 h",
              "tp": "21.0 h",
              "projet": "0.0 h",
              "perso": "0.0 h",
              "nom": "Electronique : Electronique et capteurs - 2ème partie",
              "competencesBrutes": "Cet EC relève de l'unité d'enseignement  (UE36) et contribue aux compétences suivantes :  - Mettre en œuvre des composants électroniques analogiques et/ou numériques et identifier leur fonction au sein d'un montage (niveau 2)  -- Sous compétence : Mettre en oeuvre des amplificateurs opérationnels et identifier leur fonction au sein d'un montage  --- Capacité : Sélectionner, dimensionner et interfacer des montages à amplificateurs opérationnels pour répondre à un cahier des charges --- Capacité : Identifier les blocs constitutifs dans un circuit complexe à amplificateurs opérationnels et quantifier leurs performances --- Capacité : Analyser et appliquer une documentation technique  --- Connaissance : Architecture et principe de fonctionnement d'amplificateurs opérationnels --- Connaissance : Approximations courantes du fonctionnement d'un amplificateur opérationnel --- Connaissance : Circuits fondamentaux à base d'AOPs --- Connaissance : Limites et défauts de l'amplificateur opérationnel réel  - Concevoir et réaliser des systèmes électroniques pour l'acquisition, le traitement, la commande et la communication de données (niveau 2)  -- Sous compétence : Sélectionner, concevoir et réaliser des capteurs et leur interfaçage  --- Capacité : Choisir un capteur adapté à une application --- Capacité : Dimensionner un capteur et/ou son interface pour une application --- Capacité : Evaluer les incertitudes de mesure et le bruit dans une chaîne électronique  --- Connaissance : Types de capteurs, leurs principes physiques et leurs caractéristiques statiques et dynamiques --- Connaissance : Topologie élémentaire d'une interface d'acquisition et les éléments la constituant --- Connaissance : Paramètres de base de l'acquisition d'un signal  - Mettre en œuvre les étapes permettant le contrôle du fonctionnement d'un système discret ou continu (niveau 1)  -- Sous compétence : Mettre en oeuvre l'amplificateur opérationnel en fonctionnement linéaire  --- Capacité : Définir le type de contre-réaction --- Capacité : Quantifier l'impact d'un type de contre-réaction sur les caractéristiques d'un bloc électronique  --- Connaissance : Types de contre-réaction et leurs conséquences --- Connaissance : Application des principes de contre-réaction aux amplificateurs opérationnels  De plus, elle nécessite de mobiliser les compétences suivantes :   -- Analyser un système (ou un problème) réel ou virtuel -- Exploiter un modèle d'un système réel ou virtuel -- Mettre en œuvre une démarche expérimentale -- Concevoir un système répondant à un cahier des charges -- Traiter des données -- Communiquer une analyse ou une démarche scientifique -- Travailler, apprendre, évoluer de manière autonome -- Interagir avec les autres, travailler en équipe -- Faire preuve de créativité, innover, entreprendre",
              "capacite": [
                "Capacité : Sélectionner, dimensionner et interfacer des montages à amplificateurs opérationnels pour répondre à un cahier des charges",
                "Capacité : Identifier les blocs constitutifs dans un circuit complexe à amplificateurs opérationnels et quantifier leurs performances",
                "Capacité : Analyser et appliquer une documentation technique",
                "Capacité : Choisir un capteur adapté à une application",
                "Capacité : Dimensionner un capteur et/ou son interface pour une application",
                "Capacité : Evaluer les incertitudes de mesure et le bruit dans une chaîne électronique",
                "Capacité : Définir le type de contre-réaction",
                "Capacité : Quantifier l'impact d'un type de contre-réaction sur les caractéristiques d'un bloc électronique"
              ],
              "connaissance": [
                "Connaissance : Architecture et principe de fonctionnement d'amplificateurs opérationnels",
                "Connaissance : Approximations courantes du fonctionnement d'un amplificateur opérationnel",
                "Connaissance : Circuits fondamentaux à base d'AOPs",
                "Connaissance : Limites et défauts de l'amplificateur opérationnel réel",
                "Connaissance : Types de capteurs, leurs principes physiques et leurs caractéristiques statiques et dynamiques",
                "Connaissance : Topologie élémentaire d'une interface d'acquisition et les éléments la constituant",
                "Connaissance : Paramètres de base de l'acquisition d'un signal",
                "Connaissance : Types de contre-réaction et leurs conséquences",
                "Connaissance : Application des principes de contre-réaction aux amplificateurs opérationnels"
              ],
              "competenceToCapaciteEtConnaissance": {
                "GEA-C1": [
                  "Capacité : Sélectionner, dimensionner et interfacer des montages à amplificateurs opérationnels pour répondre à un cahier des charges",
                  "Capacité : Identifier les blocs constitutifs dans un circuit complexe à amplificateurs opérationnels et quantifier leurs performances",
                  "Capacité : Analyser et appliquer une documentation technique",
                  "Connaissance : Architecture et principe de fonctionnement d'amplificateurs opérationnels",
                  "Connaissance : Approximations courantes du fonctionnement d'un amplificateur opérationnel",
                  "Connaissance : Circuits fondamentaux à base d'AOPs",
                  "Connaissance : Limites et défauts de l'amplificateur opérationnel réel"
                ],
                "GEA-C5": [
                  "Capacité : Choisir un capteur adapté à une application",
                  "Capacité : Dimensionner un capteur et/ou son interface pour une application",
                  "Capacité : Evaluer les incertitudes de mesure et le bruit dans une chaîne électronique",
                  "Connaissance : Types de capteurs, leurs principes physiques et leurs caractéristiques statiques et dynamiques",
                  "Connaissance : Topologie élémentaire d'une interface d'acquisition et les éléments la constituant",
                  "Connaissance : Paramètres de base de l'acquisition d'un signal"
                ],
                "GEA-C6": [
                  "Capacité : Définir le type de contre-réaction",
                  "Capacité : Quantifier l'impact d'un type de contre-réaction sur les caractéristiques d'un bloc électronique",
                  "Connaissance : Types de contre-réaction et leurs conséquences",
                  "Connaissance : Application des principes de contre-réaction aux amplificateurs opérationnels"
                ]
              },
              "listeComp": [
                {
                  "code": "C1",
                  "val": "Mettre en œuvre des composants électroniques analogiques et/ou numériques et identifier leur fonction au sein d'un montage",
                  "valAnglais": "Implement analog and / or digital electronic components and identify their function within an assembly",
                  "niveau": "2"
                },
                {
                  "code": "C5",
                  "val": "Concevoir et réaliser des systèmes électroniques pour l'acquisition, le traitement, la commande et la communication de données",
                  "valAnglais": "Design and build electronic systems for data acquisition, processing, control and communication",
                  "niveau": "2"
                },
                {
                  "code": "C6",
                  "val": "Mettre en œuvre les étapes permettant le contrôle du fonctionnement d'un système discret ou continu",
                  "valAnglais": "Implement steps to control the operation of a discrete or continuous system",
                  "niveau": "1"
                }
              ],
              "listeCompMobilise": [
                "Analyser un système (ou un problème) réel ou virtuel",
                "Exploiter un modèle d'un système réel ou virtuel",
                "Mettre en œuvre une démarche expérimentale",
                "Concevoir un système répondant à un cahier des charges",
                "Traiter des données",
                "Communiquer une analyse ou une démarche scientifique",
                "Travailler, apprendre, évoluer de manière autonome",
                "Interagir avec les autres, travailler en équipe",
                "Faire preuve de créativité, innover, entreprendre"
              ]
            }
          },
          {
            "UE": "Enseignements techniques (GEA-3-UE36)",
            "url": "http://planete.insa-lyon.fr/scolpeda/f/ects?id=38566&_lang=fr",
            "detail": {
              "code": "GEA-3-ETEP2",
              "ects": "3.0",
              "cours": "19.0 h",
              "td": "19.0 h",
              "tp": "69.0 h",
              "projet": "0.0 h",
              "perso": "0.0 h",
              "nom": "Electrotechnique et Electronique de Puissance : Electrotechnique et Electronique de puissance - Niveau 2",
              "competencesBrutes": "Cet EC relève de l'unité d'enseignement  (UE36) et contribue aux compétences suivantes :  - Mettre en œuvre les propriétés physiques des matériaux pour le domaine du génie électrique (niveau 2)  -- Sous compétence : Mettre en œuvre les matériaux magnétiques dans les transformateurs et machines électriques tournantes  --- Capacité : Modéliser le circuit magnétique d'un transformateur ou d'une machine électrique --- Capacité : Mettre en œuvre et modéliser le couplage magnétique entre deux circuits électriques.  --- Connaissance : Pertes magnétiques dans un transformateur --- Connaissance : Relations entre grandeurs électriques et grandeurs magnétiques au sein d'un transformateur  - Mettre en œuvre les différents éléments de production d'énergie, de transport d'énergie électrique et de conversion d'énergie (niveau 2)  -- Sous compétence : Mettre en œuvre les machines à courant alternatif : Machine Synchrone et  Asynchrone triphasée  --- Capacité : Modéliser le fonctionnement en régime permanent d'un système entrainé par une machine électrique --- Capacité : Calculer les grandeurs électriques dans les  enroulements d'une machine --- Capacité : Câbler, démarrer, contôler la vitesse d'une machine électrique  --- Connaissance : Connaitre  la constitution et le principe de fonctionnement --- Connaissance : Comprendre les interactions entre la machine tournante et le système mécanique associé dans les quatre quadrants --- Connaissance : Connaitre les schémas équivalents en régime permanent et les diagrammes vectoriels associés  -- Sous compétence : Mettre en œuvre les transformateurs électriques à couplage magnétique monophasé et triphasé  --- Capacité : Modéliser le fonctionnement en régime permanent --- Capacité : Calculer les grandeurs électriques dans les différnets enroulements --- Capacité : Schématiser, Caractériser le fonctionnement en régime permanent  --- Connaissance : Connaitre  la constitution et le principe de fonctionnement --- Connaissance : Connaissance du schéma équivalent d'un transformateur  -- Sous compétence : Mettre en œuvre la méthode des composantes symétriques pour étudier le fonctionnement d'un réseau triphasé déséquilibré  --- Capacité : Utiliser les composantes symétriques pour modéliser un système triphasé déséquilibré --- Capacité : Calculer et mesurer les impédances cycliques d'un système triphasé simple --- Capacité : Calculer les courants de court-circuit aux bornes d'un système triphasé simple  --- Connaissance : Connaissance des transformations de Fortescue --- Connaissance : Connaissance des impédances cycliques d'un système triphasé  De plus, elle nécessite de mobiliser les compétences suivantes :   -- Analyser un système (ou un problème) réel ou virtuel -- Exploiter un modèle d'un système réel ou virtuel -- Mettre en œuvre une démarche expérimentale -- Concevoir un système répondant à un cahier des charges -- Travailler, apprendre, évoluer de manière autonome -- Agir de manière responsable dans un monde complexe",
              "capacite": [
                "Capacité : Modéliser le circuit magnétique d'un transformateur ou d'une machine électrique",
                "Capacité : Mettre en œuvre et modéliser le couplage magnétique entre deux circuits électriques.",
                "Capacité : Modéliser le fonctionnement en régime permanent d'un système entrainé par une machine électrique",
                "Capacité : Calculer les grandeurs électriques dans les  enroulements d'une machine",
                "Capacité : Câbler, démarrer, contôler la vitesse d'une machine électrique",
                "Capacité : Modéliser le fonctionnement en régime permanent",
                "Capacité : Calculer les grandeurs électriques dans les différnets enroulements",
                "Capacité : Schématiser, Caractériser le fonctionnement en régime permanent",
                "Capacité : Utiliser les composantes symétriques pour modéliser un système triphasé déséquilibré",
                "Capacité : Calculer et mesurer les impédances cycliques d'un système triphasé simple",
                "Capacité : Calculer les courants de court-circuit aux bornes d'un système triphasé simple"
              ],
              "connaissance": [
                "Connaissance : Pertes magnétiques dans un transformateur",
                "Connaissance : Relations entre grandeurs électriques et grandeurs magnétiques au sein d'un transformateur",
                "Connaissance : Connaitre  la constitution et le principe de fonctionnement",
                "Connaissance : Comprendre les interactions entre la machine tournante et le système mécanique associé dans les quatre quadrants",
                "Connaissance : Connaitre les schémas équivalents en régime permanent et les diagrammes vectoriels associés",
                "Connaissance : Connaitre  la constitution et le principe de fonctionnement",
                "Connaissance : Connaissance du schéma équivalent d'un transformateur",
                "Connaissance : Connaissance des transformations de Fortescue",
                "Connaissance : Connaissance des impédances cycliques d'un système triphasé"
              ],
              "competenceToCapaciteEtConnaissance": {
                "GEA-C2": [
                  "Capacité : Modéliser le circuit magnétique d'un transformateur ou d'une machine électrique",
                  "Capacité : Mettre en œuvre et modéliser le couplage magnétique entre deux circuits électriques.",
                  "Connaissance : Pertes magnétiques dans un transformateur",
                  "Connaissance : Relations entre grandeurs électriques et grandeurs magnétiques au sein d'un transformateur"
                ],
                "GEA-C3": [
                  "Capacité : Modéliser le fonctionnement en régime permanent d'un système entrainé par une machine électrique",
                  "Capacité : Calculer les grandeurs électriques dans les  enroulements d'une machine",
                  "Capacité : Câbler, démarrer, contôler la vitesse d'une machine électrique",
                  "Connaissance : Connaitre  la constitution et le principe de fonctionnement",
                  "Connaissance : Comprendre les interactions entre la machine tournante et le système mécanique associé dans les quatre quadrants",
                  "Connaissance : Connaitre les schémas équivalents en régime permanent et les diagrammes vectoriels associés",
                  "Capacité : Modéliser le fonctionnement en régime permanent",
                  "Capacité : Calculer les grandeurs électriques dans les différnets enroulements",
                  "Capacité : Schématiser, Caractériser le fonctionnement en régime permanent",
                  "Connaissance : Connaitre  la constitution et le principe de fonctionnement",
                  "Connaissance : Connaissance du schéma équivalent d'un transformateur",
                  "Capacité : Utiliser les composantes symétriques pour modéliser un système triphasé déséquilibré",
                  "Capacité : Calculer et mesurer les impédances cycliques d'un système triphasé simple",
                  "Capacité : Calculer les courants de court-circuit aux bornes d'un système triphasé simple",
                  "Connaissance : Connaissance des transformations de Fortescue",
                  "Connaissance : Connaissance des impédances cycliques d'un système triphasé"
                ]
              },
              "listeComp": [
                {
                  "code": "C2",
                  "val": "Mettre en œuvre les propriétés physiques des matériaux pour le domaine du génie électrique",
                  "valAnglais": "Implement the physical properties of materials for the field of electrical engineering",
                  "niveau": "2"
                },
                {
                  "code": "C3",
                  "val": "Mettre en œuvre les différents éléments de production d'énergie, de transport d'énergie électrique et de conversion d'énergie",
                  "valAnglais": "Implement the various elements of energy production, transport of electrical energy and energy conversion",
                  "niveau": "2"
                }
              ],
              "listeCompMobilise": [
                "Analyser un système (ou un problème) réel ou virtuel",
                "Exploiter un modèle d'un système réel ou virtuel",
                "Mettre en œuvre une démarche expérimentale",
                "Concevoir un système répondant à un cahier des charges",
                "Travailler, apprendre, évoluer de manière autonome",
                "Agir de manière responsable dans un monde complexe"
              ]
            }
          },
          {
            "UE": "Enseignements techniques (GEA-3-UE36)",
            "url": "http://planete.insa-lyon.fr/scolpeda/f/ects?id=39484&_lang=fr",
            "detail": {
              "code": "GEA-3-IF1",
              "ects": "2.0",
              "cours": "11.0 h",
              "td": "11.0 h",
              "tp": "6.0 h",
              "projet": "0.0 h",
              "perso": "0.0 h",
              "nom": "Informatique Industrielle : Informatique industrielle - niveau 1",
              "competencesBrutes": "Cet EC relève de l'unité d'enseignement  (UE36) et contribue aux compétences suivantes :  - Mettre en œuvre des composants électroniques analogiques et/ou numériques et identifier leur fonction au sein d'un montage (niveau 2)  --- Capacité : Etre capable de concevoir et d'analyser des systèmes en logique combinatoire --- Capacité : Etre capable de réaliser des fonctions de multiplexage et démultiplexage  --- Connaissance : Algèbre booléenne, Opérateurs et fonctions logiques de base, leurs propriétés --- Connaissance : Fonctions séquentielles et leurs synthèses --- Connaissance : Technologie des composants  - Concevoir et réaliser des systèmes électroniques pour l'acquisition, le traitement, la commande et la communication de données (niveau 2)  --- Capacité : Etre capable de formaliser et simplifier des systèmes en logique combinatoire --- Capacité : Etre capable de concevoir et d'analyser des systèmes en logique combinatoire --- Capacité : Etre capable de réaliser des fonctions en logique combinatoire avec des composants standards --- Capacité : Etre capable de réaliser des fonctions de multiplexage et démultiplexage --- Capacité : Etre capable de formaliser et simplifier des systèmes en logique séquentielle --- Capacité : Etre capable de concevoir et analyser des systèmes en logique séquentielle  --- Connaissance : Algèbre booléenne, Opérateurs et fonctions logiques de base, leurs propriétés --- Connaissance : Systèmes de numérations, bases --- Connaissance : Fonctions séquentielles et leurs synthèses --- Connaissance : Eléments constitutifs des systèmes logiques séquentiels  - Concevoir et développer des logiciels haut et bas niveau pour des systèmes (traitement et gestion de l'information) (niveau 2)  --- Capacité : Etre capable d'appréhender les outils informatiques de l'ingénieur --- Capacité : Etre capable de développer des logiciels de haut niveau sur des systèmes informatiques à ressources contraintes --- Capacité : Etre capable d'analyser et concevoir un projet informatique  --- Connaissance : Syntaxe élémentaire du langage C/C++ --- Connaissance : Algorithmes standards  (tri, manipulation de tableaux et matrices) --- Connaissance : Notions fondamentales des Systèmes d'Exploitation et de la compilation --- Connaissance : Notions fondamentales de la compilation  De plus, elle nécessite de mobiliser les compétences suivantes :  -- Analyser un système (ou un problème) réel ou virtuel -- Exploiter un modèle d'un système réel ou virtuel -- Mettre en œuvre une démarche expérimentale -- Concevoir un système répondant à un cahier des charges -- Traiter des données -- Communiquer une analyse ou une démarche scientifique -- Interagir avec les autres, travailler en équipe -- Se situer, travailler, évoluer dans une entreprise, une organisation socio-productive",
              "capacite": [
                "Capacité : Etre capable de concevoir et d'analyser des systèmes en logique combinatoire",
                "Capacité : Etre capable de réaliser des fonctions de multiplexage et démultiplexage",
                "Capacité : Etre capable de formaliser et simplifier des systèmes en logique combinatoire",
                "Capacité : Etre capable de concevoir et d'analyser des systèmes en logique combinatoire",
                "Capacité : Etre capable de réaliser des fonctions en logique combinatoire avec des composants standards",
                "Capacité : Etre capable de réaliser des fonctions de multiplexage et démultiplexage",
                "Capacité : Etre capable de formaliser et simplifier des systèmes en logique séquentielle",
                "Capacité : Etre capable de concevoir et analyser des systèmes en logique séquentielle",
                "Capacité : Etre capable d'appréhender les outils informatiques de l'ingénieur",
                "Capacité : Etre capable de développer des logiciels de haut niveau sur des systèmes informatiques à ressources contraintes",
                "Capacité : Etre capable d'analyser et concevoir un projet informatique"
              ],
              "connaissance": [
                "Connaissance : Algèbre booléenne, Opérateurs et fonctions logiques de base, leurs propriétés",
                "Connaissance : Fonctions séquentielles et leurs synthèses",
                "Connaissance : Technologie des composants",
                "Connaissance : Algèbre booléenne, Opérateurs et fonctions logiques de base, leurs propriétés",
                "Connaissance : Systèmes de numérations, bases",
                "Connaissance : Fonctions séquentielles et leurs synthèses",
                "Connaissance : Eléments constitutifs des systèmes logiques séquentiels",
                "Connaissance : Syntaxe élémentaire du langage C/C++",
                "Connaissance : Algorithmes standards  (tri, manipulation de tableaux et matrices)",
                "Connaissance : Notions fondamentales des Systèmes d'Exploitation et de la compilation",
                "Connaissance : Notions fondamentales de la compilation"
              ],
              "competenceToCapaciteEtConnaissance": {
                "GEA-C1": [
                  "Capacité : Etre capable de concevoir et d'analyser des systèmes en logique combinatoire",
                  "Capacité : Etre capable de réaliser des fonctions de multiplexage et démultiplexage",
                  "Connaissance : Algèbre booléenne, Opérateurs et fonctions logiques de base, leurs propriétés",
                  "Connaissance : Fonctions séquentielles et leurs synthèses",
                  "Connaissance : Technologie des composants"
                ],
                "GEA-C5": [
                  "Capacité : Etre capable de formaliser et simplifier des systèmes en logique combinatoire",
                  "Capacité : Etre capable de concevoir et d'analyser des systèmes en logique combinatoire",
                  "Capacité : Etre capable de réaliser des fonctions en logique combinatoire avec des composants standards",
                  "Capacité : Etre capable de réaliser des fonctions de multiplexage et démultiplexage",
                  "Capacité : Etre capable de formaliser et simplifier des systèmes en logique séquentielle",
                  "Capacité : Etre capable de concevoir et analyser des systèmes en logique séquentielle",
                  "Connaissance : Algèbre booléenne, Opérateurs et fonctions logiques de base, leurs propriétés",
                  "Connaissance : Systèmes de numérations, bases",
                  "Connaissance : Fonctions séquentielles et leurs synthèses",
                  "Connaissance : Eléments constitutifs des systèmes logiques séquentiels"
                ],
                "GEA-C7": [
                  "Capacité : Etre capable d'appréhender les outils informatiques de l'ingénieur",
                  "Capacité : Etre capable de développer des logiciels de haut niveau sur des systèmes informatiques à ressources contraintes",
                  "Capacité : Etre capable d'analyser et concevoir un projet informatique",
                  "Connaissance : Syntaxe élémentaire du langage C/C++",
                  "Connaissance : Algorithmes standards  (tri, manipulation de tableaux et matrices)",
                  "Connaissance : Notions fondamentales des Systèmes d'Exploitation et de la compilation",
                  "Connaissance : Notions fondamentales de la compilation"
                ]
              },
              "listeComp": [
                {
                  "code": "C1",
                  "val": "Mettre en œuvre des composants électroniques analogiques et/ou numériques et identifier leur fonction au sein d'un montage",
                  "valAnglais": "Implement analog and / or digital electronic components and identify their function within an assembly",
                  "niveau": "2"
                },
                {
                  "code": "C5",
                  "val": "Concevoir et réaliser des systèmes électroniques pour l'acquisition, le traitement, la commande et la communication de données",
                  "valAnglais": "Design and build electronic systems for data acquisition, processing, control and communication",
                  "niveau": "2"
                },
                {
                  "code": "C7",
                  "val": "Concevoir et développer des logiciels haut et bas niveau pour des systèmes (traitement et gestion de l'information)",
                  "valAnglais": "Design and develop high and low level software for systems (information processing and management)",
                  "niveau": "2"
                }
              ],
              "listeCompMobilise": [
                "Analyser un système (ou un problème) réel ou virtuel",
                "Exploiter un modèle d'un système réel ou virtuel",
                "Mettre en œuvre une démarche expérimentale",
                "Concevoir un système répondant à un cahier des charges",
                "Traiter des données",
                "Communiquer une analyse ou une démarche scientifique",
                "Interagir avec les autres, travailler en équipe",
                "Se situer, travailler, évoluer dans une entreprise, une organisation socio-productive"
              ]
            }
          },
          {
            "UE": "Humanités et Education sportive (GEA-3-UE37)",
            "url": "http://planete.insa-lyon.fr/scolpeda/f/ects?id=38570&_lang=fr",
            "detail": {
              "code": "GEA-3-SHS2",
              "ects": "3.0",
              "cours": "0.0 h",
              "td": "77.0 h",
              "tp": "0.0 h",
              "projet": "0.0 h",
              "perso": "0.0 h",
              "nom": "Sciences Humaines et Sociales : Communication - Management de projet - Développement Durable",
              "competencesBrutes": "Cet EC relève de l'unité d'enseignement  (UE37) et contribue aux compétences suivantes :  -- Se connaître, se gérer physiquement et mentalement (niveau 2)  --- Capacité : Etre à l'écoute des autres --- Capacité : Découvrir ses propres ressources --- Capacité : Prendre la parole --- Capacité :  Apprendre à motiver l'intérêt, l'écoute, l'implication¿ de l'autre  --- Connaissance : (Théatre) --- Connaissance : Concept d'intention positive ou comment nourrir les attentes ou les valeurs de l'autre. --- Connaissance : Identifier son canal sensoriel dominant et celui de son interlocuteur  -- Interagir avec les autres, travailler en équipe (niveau 2)  --- Capacité : Parler devant un groupe --- Capacité : Avoir confiance en soi et aux autres --- Capacité : Savoir se situer et situer les collaborateurs dans un travail en équipe --- Capacité :  Apprendre à motiver l'intérêt, l'écoute, l'implication¿ de l'autre --- Capacité : Donner du sens fort à sa communication --- Capacité : Savoir planifier un projet et modéliser des problématiques, --- Capacité : Etre capable de mettre en œuvre une démarche rationnelle dans le traitement d'un problème, --- Capacité : Appréhender les différentes composantes d'un projet, --- Capacité : Savoir se situer et situer ses équipes dans une démarche projet, --- Capacité : comprendre les enjeux environnementaux de l'entreprise sur les plans réglementaire, économique et technique. --- Capacité : Comprendre la notion de Développement durable  --- Connaissance : Communication --- Connaissance : Concept d'intention positive ou comment nourrir les attentes ou les valeurs de l'autre. --- Connaissance : Identifier son canal sensoriel dominant et celui de son interlocuteur --- Connaissance : Les bases et factuers clés d'une gestion de projet réussi. --- Connaissance : Identifier les ressources nécessaires à chaque tâche, --- Connaissance :  Les interactions entre les services et/ou intervenants, --- Connaissance : Les procédures de prise de décision, de constitution d'équipe, --- Connaissance : Environnement: bases de réglementation environnementale --- Connaissance : Le développement durable --- Connaissance : Notion de développement durable --- Connaissance : La gestion de l'environnement mondiale, en Europe et en France  -- Se situer, travailler, évoluer dans une entreprise, une organisation socio-productive (niveau 1)  --- Capacité : comprendre les enjeux environnementaux de l'entreprise sur les plans réglementaire, économique et technique --- Capacité : Comprendre la notion de Développement durable --- Capacité : Inter-agir avec des ressources complémentaires --- Capacité : Savoir se situer et situer ses équipes dans une démarche projet,  --- Connaissance : Le processus de déroulement et ses phases, --- Connaissance : Les interactions entre les services et/ou intervenants --- Connaissance : L'organigramme des tâches,   -- Travailler dans un contexte international et interculturel (niveau 1)  --- Capacité : Appréhender les différentes composantes d'un projet --- Capacité : Mettre en œuvre une démarche rationnelle dans le traitement d'un problème dans un un environnement interculturel et international  --- Connaissance : Management de projet: les facteurs clés de réussite, l'analyse des risques / ressources humaines et plan de communication  De plus, elle nécessite de mobiliser les compétences suivantes :  -- Concevoir un système répondant à un cahier des charges -- Traiter des données -- Communiquer une analyse ou une démarche scientifique -- Agir de manière responsable dans un monde complexe",
              "capacite": [
                "Capacité : Etre à l'écoute des autres",
                "Capacité : Découvrir ses propres ressources",
                "Capacité : Prendre la parole",
                "Capacité :  Apprendre à motiver l'intérêt, l'écoute, l'implication' de l'autre",
                "Capacité : Parler devant un groupe",
                "Capacité : Avoir confiance en soi et aux autres",
                "Capacité : Savoir se situer et situer les collaborateurs dans un travail en équipe",
                "Capacité :  Apprendre à motiver l'intérêt, l'écoute, l'implication' de l'autre",
                "Capacité : Donner du sens fort à sa communication",
                "Capacité : Savoir planifier un projet et modéliser des problématiques,",
                "Capacité : Etre capable de mettre en œuvre une démarche rationnelle dans le traitement d'un problème,",
                "Capacité : Appréhender les différentes composantes d'un projet,",
                "Capacité : Savoir se situer et situer ses équipes dans une démarche projet,",
                "Capacité : comprendre les enjeux environnementaux de l'entreprise sur les plans réglementaire, économique et technique.",
                "Capacité : Comprendre la notion de Développement durable",
                "Capacité : comprendre les enjeux environnementaux de l'entreprise sur les plans réglementaire, économique et technique",
                "Capacité : Comprendre la notion de Développement durable",
                "Capacité : Inter-agir avec des ressources complémentaires",
                "Capacité : Savoir se situer et situer ses équipes dans une démarche projet,",
                "Capacité : Appréhender les différentes composantes d'un projet",
                "Capacité : Mettre en œuvre une démarche rationnelle dans le traitement d'un problème dans un un environnement interculturel et international"
              ],
              "connaissance": [
                "Connaissance : (Théatre)",
                "Connaissance : Concept d'intention positive ou comment nourrir les attentes ou les valeurs de l'autre.",
                "Connaissance : Identifier son canal sensoriel dominant et celui de son interlocuteur  -- Interagir avec les autres, travailler en équipe (niveau 2)",
                "Connaissance : Communication",
                "Connaissance : Concept d'intention positive ou comment nourrir les attentes ou les valeurs de l'autre.",
                "Connaissance : Identifier son canal sensoriel dominant et celui de son interlocuteur",
                "Connaissance : Les bases et factuers clés d'une gestion de projet réussi.",
                "Connaissance : Identifier les ressources nécessaires à chaque tâche,",
                "Connaissance :  Les interactions entre les services et/ou intervenants,",
                "Connaissance : Les procédures de prise de décision, de constitution d'équipe,",
                "Connaissance : Environnement: bases de réglementation environnementale",
                "Connaissance : Le développement durable",
                "Connaissance : Notion de développement durable",
                "Connaissance : La gestion de l'environnement mondiale, en Europe et en France  -- Se situer, travailler, évoluer dans une entreprise, une organisation socio-productive (niveau 1)",
                "Connaissance : Le processus de déroulement et ses phases,",
                "Connaissance : Les interactions entre les services et/ou intervenants",
                "Connaissance : L'organigramme des tâches,   -- Travailler dans un contexte international et interculturel (niveau 1)",
                "Connaissance : Management de projet: les facteurs clés de réussite, l'analyse des risques / ressources humaines et plan de communication"
              ],
              "competenceToCapaciteEtConnaissance": {
                "B1": [
                  "Capacité : Etre à l'écoute des autres",
                  "Capacité : Découvrir ses propres ressources",
                  "Capacité : Prendre la parole",
                  "Capacité :  Apprendre à motiver l'intérêt, l'écoute, l'implication' de l'autre",
                  "Connaissance : (Théatre)",
                  "Connaissance : Concept d'intention positive ou comment nourrir les attentes ou les valeurs de l'autre.",
                  "Connaissance : Identifier son canal sensoriel dominant et celui de son interlocuteur  -- Interagir avec les autres, travailler en équipe (niveau 2)",
                  "Capacité : Parler devant un groupe",
                  "Capacité : Avoir confiance en soi et aux autres",
                  "Capacité : Savoir se situer et situer les collaborateurs dans un travail en équipe",
                  "Capacité :  Apprendre à motiver l'intérêt, l'écoute, l'implication' de l'autre",
                  "Capacité : Donner du sens fort à sa communication",
                  "Capacité : Savoir planifier un projet et modéliser des problématiques,",
                  "Capacité : Etre capable de mettre en œuvre une démarche rationnelle dans le traitement d'un problème,",
                  "Capacité : Appréhender les différentes composantes d'un projet,",
                  "Capacité : Savoir se situer et situer ses équipes dans une démarche projet,",
                  "Capacité : comprendre les enjeux environnementaux de l'entreprise sur les plans réglementaire, économique et technique.",
                  "Capacité : Comprendre la notion de Développement durable",
                  "Connaissance : Communication",
                  "Connaissance : Concept d'intention positive ou comment nourrir les attentes ou les valeurs de l'autre.",
                  "Connaissance : Identifier son canal sensoriel dominant et celui de son interlocuteur",
                  "Connaissance : Les bases et factuers clés d'une gestion de projet réussi.",
                  "Connaissance : Identifier les ressources nécessaires à chaque tâche,",
                  "Connaissance :  Les interactions entre les services et/ou intervenants,",
                  "Connaissance : Les procédures de prise de décision, de constitution d'équipe,",
                  "Connaissance : Environnement: bases de réglementation environnementale",
                  "Connaissance : Le développement durable",
                  "Connaissance : Notion de développement durable",
                  "Connaissance : La gestion de l'environnement mondiale, en Europe et en France  -- Se situer, travailler, évoluer dans une entreprise, une organisation socio-productive (niveau 1)",
                  "Capacité : comprendre les enjeux environnementaux de l'entreprise sur les plans réglementaire, économique et technique",
                  "Capacité : Comprendre la notion de Développement durable",
                  "Capacité : Inter-agir avec des ressources complémentaires",
                  "Capacité : Savoir se situer et situer ses équipes dans une démarche projet,",
                  "Connaissance : Le processus de déroulement et ses phases,",
                  "Connaissance : Les interactions entre les services et/ou intervenants",
                  "Connaissance : L'organigramme des tâches,   -- Travailler dans un contexte international et interculturel (niveau 1)",
                  "Capacité : Appréhender les différentes composantes d'un projet",
                  "Capacité : Mettre en œuvre une démarche rationnelle dans le traitement d'un problème dans un un environnement interculturel et international",
                  "Connaissance : Management de projet: les facteurs clés de réussite, l'analyse des risques / ressources humaines et plan de communication"
                ]
              },
              "listeComp": [
                {
                  "code": "B1",
                  "val": "Se connaître, se gérer physiquement et mentalement",
                  "valAnglais": "Know oneself; manage mental and physical fitness",
                  "bs": "23",
                  "niveau": "2"
                }
              ],
              "listeCompMobilise": [
                "Concevoir un système répondant à un cahier des charges",
                "Traiter des données",
                "Communiquer une analyse ou une démarche scientifique",
                "Agir de manière responsable dans un monde complexe"
              ]
            }
          },
          {
            "UE": "Humanités et Education sportive (GEA-3-UE37)",
            "url": "http://planete.insa-lyon.fr/scolpeda/f/ects?id=38567&_lang=fr",
            "detail": {
              "code": "GEA-3-LA2",
              "ects": "2.0",
              "cours": "0.0 h",
              "td": "36.0 h",
              "tp": "0.0 h",
              "projet": "0.0 h",
              "perso": "0.0 h",
              "nom": "Langues Étrangères : Langues vivantes - Deuxième Semestre",
              "competencesBrutes": "Cet EC relève de l'unité d'enseignement  (UE37) et contribue aux compétences suivantes :  -- Travailler dans un contexte international et interculturel (niveau 2)  --- Capacité : Maitriser les fondamentaux de la langue --- Capacité : Se débrouiller dans la plupart des situations rencontrées en voyage dans une région où l'anglais est parlé --- Capacité : Produire des discours simples et cohérents sur des sujets familiers et dans vos domaines d'intérêt  --- Connaissance : Lexique, syntaxe, grammaire --- Connaissance : Expression orale --- Connaissance : Expression écrite",
              "capacite": [
                "Capacité : Maitriser les fondamentaux de la langue",
                "Capacité : Se débrouiller dans la plupart des situations rencontrées en voyage dans une région où l'anglais est parlé",
                "Capacité : Produire des discours simples et cohérents sur des sujets familiers et dans vos domaines d'intérêt"
              ],
              "connaissance": [
                "Connaissance : Lexique, syntaxe, grammaire",
                "Connaissance : Expression orale",
                "Connaissance : Expression écrite"
              ],
              "competenceToCapaciteEtConnaissance": {
                "B7": [
                  "Capacité : Maitriser les fondamentaux de la langue",
                  "Capacité : Se débrouiller dans la plupart des situations rencontrées en voyage dans une région où l'anglais est parlé",
                  "Capacité : Produire des discours simples et cohérents sur des sujets familiers et dans vos domaines d'intérêt",
                  "Connaissance : Lexique, syntaxe, grammaire",
                  "Connaissance : Expression orale",
                  "Connaissance : Expression écrite"
                ]
              },
              "listeComp": [
                {
                  "code": "B7",
                  "val": "Travailler dans un contexte international et interculturel",
                  "valAnglais": "Work in an international, intercultural context",
                  "bs": "29",
                  "niveau": "2"
                }
              ]
            }
          },
          {
            "UE": "Humanités et Education sportive (GEA-3-UE37)",
            "url": "http://planete.insa-lyon.fr/scolpeda/f/ects?id=37341&_lang=fr",
            "detail": {
              "code": "GEA-3-EPS2",
              "ects": "1.0",
              "cours": "0.0 h",
              "td": "15.0 h",
              "tp": "0.0 h",
              "projet": "0.0 h",
              "perso": "0.0 h"
            }
          },
          {
            "UE": "Acquis en entreprise (GEA-3-UE38)",
            "url": "http://planete.insa-lyon.fr/scolpeda/f/ects?id=38569&_lang=fr",
            "detail": {
              "code": "GEA-3-PE2",
              "ects": "9.0",
              "cours": "0.0 h",
              "td": "3.5 h",
              "tp": "0.0 h",
              "projet": "0.0 h",
              "perso": "0.0 h",
              "nom": "Entreprise : Période en entreprise 2",
              "competencesBrutes": "Cet EC relève de l'unité d'enseignement  (UE38) et contribue aux compétences suivantes :  -- Se situer, travailler, évoluer dans une entreprise, une organisation socio-productive (niveau 2)  --- Capacité : Comprendre le fonctionnement global de l'entreprise et du service d'accueil. Etre capable de la représenter à l'extérieur. Respecter les règles de fonctionnement du service. --- Capacité : Produire le travail dans le temps imparti. Savoir chercher l'information auprès des bonnes personnes. --- Capacité : Comprendre la stratégie commerciale de l'entreprise. Participer à des rencontres avec les clients et/ou les fournisseurs  --- Connaissance : Organisation d'un milieu professionnel  -- Travailler, apprendre, évoluer de manière autonome (niveau 2)  --- Capacité : Respecter les objectifs et le planning prévisionnel fixé par le projet. --- Capacité : Formaliser avec le Maitre d'Apprentissageles objectifs avec des indicateurs de résultats et un planning prévisionnel pour son travail personnel  --- Connaissance : Gestion du temps --- Connaissance : Démarche projet  -- Interagir avec les autres, travailler en équipe (niveau )  --- Capacité : Etre capable de communiquer avec des spécialistes et des non spécialistes et différents niveaux de hiérarchie. --- Capacité : Etre capable de reformuler son problème de manière claire à l'écrit comme à l'oral. Faire un reporting efficient. --- Capacité : Faire preuve d'esprit d'équipe et de proactivité.  --- Connaissance : communication, reporting --- Connaissance : Relations humaines, intégration dans équipe  - Mettre en œuvre ses compétences scientifiques et technologiques dans le domaine de l'EEAIIT dans un cadre industriel et appliqué à des problématiques réelles en conduisant les étapes du cycle de conception (niveau )  --- Capacité : Etre associé à une étape du cycle en V --- Capacité : mettre en œuvre des composants et fonctions unitaires connus ou existants. --- Capacité : Utiliser des outils de CAO et DAO élémentaires --- Capacité : Réaliser un prototype --- Capacité : Simuler les performances attendues  --- Connaissance : Mise en œuvre de composants ou sous ensemble fonctionnels, Prototypage --- Connaissance : utilisation CAO / DAO, simulation performance.",
              "capacite": [
                "Capacité : Comprendre le fonctionnement global de l'entreprise et du service d'accueil. Etre capable de la représenter à l'extérieur. Respecter les règles de fonctionnement du service.",
                "Capacité : Produire le travail dans le temps imparti. Savoir chercher l'information auprès des bonnes personnes.",
                "Capacité : Comprendre la stratégie commerciale de l'entreprise. Participer à des rencontres avec les clients et/ou les fournisseurs",
                "Capacité : Respecter les objectifs et le planning prévisionnel fixé par le projet.",
                "Capacité : Formaliser avec le Maitre d'Apprentissageles objectifs avec des indicateurs de résultats et un planning prévisionnel pour son travail personnel",
                "Capacité : Etre capable de communiquer avec des spécialistes et des non spécialistes et différents niveaux de hiérarchie.",
                "Capacité : Etre capable de reformuler son problème de manière claire à l'écrit comme à l'oral. Faire un reporting efficient.",
                "Capacité : Faire preuve d'esprit d'équipe et de proactivité.",
                "Capacité : Etre associé à une étape du cycle en V",
                "Capacité : mettre en œuvre des composants et fonctions unitaires connus ou existants.",
                "Capacité : Utiliser des outils de CAO et DAO élémentaires",
                "Capacité : Réaliser un prototype",
                "Capacité : Simuler les performances attendues"
              ],
              "connaissance": [
                "Connaissance : Organisation d'un milieu professionnel  -- Travailler, apprendre, évoluer de manière autonome (niveau 2)",
                "Connaissance : Gestion du temps",
                "Connaissance : Démarche projet  -- Interagir avec les autres, travailler en équipe (niveau )",
                "Connaissance : communication, reporting",
                "Connaissance : Relations humaines, intégration dans équipe",
                "Connaissance : Mise en œuvre de composants ou sous ensemble fonctionnels, Prototypage",
                "Connaissance : utilisation CAO / DAO, simulation performance."
              ],
              "competenceToCapaciteEtConnaissance": {
                "B6": [
                  "Capacité : Comprendre le fonctionnement global de l'entreprise et du service d'accueil. Etre capable de la représenter à l'extérieur. Respecter les règles de fonctionnement du service.",
                  "Capacité : Produire le travail dans le temps imparti. Savoir chercher l'information auprès des bonnes personnes.",
                  "Capacité : Comprendre la stratégie commerciale de l'entreprise. Participer à des rencontres avec les clients et/ou les fournisseurs",
                  "Connaissance : Organisation d'un milieu professionnel  -- Travailler, apprendre, évoluer de manière autonome (niveau 2)",
                  "Capacité : Respecter les objectifs et le planning prévisionnel fixé par le projet.",
                  "Capacité : Formaliser avec le Maitre d'Apprentissageles objectifs avec des indicateurs de résultats et un planning prévisionnel pour son travail personnel",
                  "Connaissance : Gestion du temps",
                  "Connaissance : Démarche projet  -- Interagir avec les autres, travailler en équipe (niveau )",
                  "Capacité : Etre capable de communiquer avec des spécialistes et des non spécialistes et différents niveaux de hiérarchie.",
                  "Capacité : Etre capable de reformuler son problème de manière claire à l'écrit comme à l'oral. Faire un reporting efficient.",
                  "Capacité : Faire preuve d'esprit d'équipe et de proactivité.",
                  "Connaissance : communication, reporting",
                  "Connaissance : Relations humaines, intégration dans équipe"
                ],
                "GEA-C9": [
                  "Capacité : Etre associé à une étape du cycle en V",
                  "Capacité : mettre en œuvre des composants et fonctions unitaires connus ou existants.",
                  "Capacité : Utiliser des outils de CAO et DAO élémentaires",
                  "Capacité : Réaliser un prototype",
                  "Capacité : Simuler les performances attendues",
                  "Connaissance : Mise en œuvre de composants ou sous ensemble fonctionnels, Prototypage",
                  "Connaissance : utilisation CAO / DAO, simulation performance."
                ]
              },
              "listeComp": [
                {
                  "code": "B6",
                  "val": "Se situer, travailler, évoluer dans une entreprise, une organisation socio-productive",
                  "valAnglais": "Position oneself, work, and evolve within a company or a socio-productive organization",
                  "bs": "28",
                  "niveau": "2"
                },
                {
                  "code": "C9",
                  "val": "Mettre en œuvre ses compétences scientifiques et technologiques dans le domaine de l'EEAIIT dans un cadre industriel et appliqué à des problématiques réelles en conduisant les étapes du cycle de conception",
                  "valAnglais": "Apply scientific and technological competences in the field of the EEAIIT in an industrial framework and to real problems by leading the stages of the cycle of conception",
                  "niveau": ""
                }
              ]
            }
          }
        ]
      },
      {
        "url": "/fr/formation/parcours/1165/4/1",
        "ecs": [
          {
            "UE": "Enseignements Transversaux (GEA-4-UE41)",
            "url": "http://planete.insa-lyon.fr/scolpeda/f/ects?id=39187&_lang=fr",
            "detail": {
              "code": "GEA-4-TS",
              "ects": "2.0",
              "cours": "12.0 h",
              "td": "12.0 h",
              "tp": "8.0 h",
              "projet": "0.0 h",
              "perso": "16.0 h",
              "nom": "Traitement du Signal : Traitement du Signal",
              "competencesBrutes": "Cet EC relève de l'unité d'enseignement  (UE41) et contribue aux compétences suivantes :  - Spécifier, modéliser et concevoir les méthodes et algorithmes pour le traitement et la gestion de l'information véhiculée par les signaux et les images (niveau 2)  --- Capacité : Calculer les composants d'un filtre analogique actif à partir d'un gabarit --- Capacité : Calculer les coefficients des filtres numériques FIR et IIR à partir d'un gabarit  --- Connaissance : Modélisation des filtres linéaires invariants analogiques et numériques --- Connaissance : Corrélation et densité spectrale. --- Connaissance : Fonctions d'approximation des filtres linéaires invariants  - Concevoir et réaliser des systèmes électroniques pour l'acquisition, le traitement, la commande et la communication de données (niveau 2)  --- Capacité : Calculer les composants d'un filtre analogique actif à partir d'un gabarit --- Capacité : Calculer les coefficients des filtres numériques FIR et IIR à partir d'un gabarit  --- Connaissance : Structures des filtres analogiques actifs --- Connaissance : Structures des filtres numériques  De plus, elle nécessite de mobiliser les compétences suivantes :  -- Analyser un système (ou un problème) réel ou virtuel -- Exploiter un modèle d'un système réel ou virtuel -- Mettre en œuvre une démarche expérimentale -- Concevoir un système répondant à un cahier des charges -- Agir de manière responsable dans un monde complexe",
              "capacite": [
                "Capacité : Calculer les composants d'un filtre analogique actif à partir d'un gabarit",
                "Capacité : Calculer les coefficients des filtres numériques FIR et IIR à partir d'un gabarit",
                "Capacité : Calculer les composants d'un filtre analogique actif à partir d'un gabarit",
                "Capacité : Calculer les coefficients des filtres numériques FIR et IIR à partir d'un gabarit"
              ],
              "connaissance": [
                "Connaissance : Modélisation des filtres linéaires invariants analogiques et numériques",
                "Connaissance : Corrélation et densité spectrale.",
                "Connaissance : Fonctions d'approximation des filtres linéaires invariants",
                "Connaissance : Structures des filtres analogiques actifs",
                "Connaissance : Structures des filtres numériques"
              ],
              "competenceToCapaciteEtConnaissance": {
                "GEA-C4": [
                  "Capacité : Calculer les composants d'un filtre analogique actif à partir d'un gabarit",
                  "Capacité : Calculer les coefficients des filtres numériques FIR et IIR à partir d'un gabarit",
                  "Connaissance : Modélisation des filtres linéaires invariants analogiques et numériques",
                  "Connaissance : Corrélation et densité spectrale.",
                  "Connaissance : Fonctions d'approximation des filtres linéaires invariants"
                ],
                "GEA-C5": [
                  "Capacité : Calculer les composants d'un filtre analogique actif à partir d'un gabarit",
                  "Capacité : Calculer les coefficients des filtres numériques FIR et IIR à partir d'un gabarit",
                  "Connaissance : Structures des filtres analogiques actifs",
                  "Connaissance : Structures des filtres numériques"
                ]
              },
              "listeComp": [
                {
                  "code": "C4",
                  "val": "Spécifier, modéliser et concevoir les méthodes et algorithmes pour le traitement et la gestion de l'information véhiculée par les signaux et les images",
                  "valAnglais": "Specify, model and design methods and algorithms for the processing and management of information conveyed by signals and images",
                  "niveau": "2"
                },
                {
                  "code": "C5",
                  "val": "Concevoir et réaliser des systèmes électroniques pour l'acquisition, le traitement, la commande et la communication de données",
                  "valAnglais": "Design and build electronic systems for data acquisition, processing, control and communication",
                  "niveau": "2"
                }
              ],
              "listeCompMobilise": [
                "Analyser un système (ou un problème) réel ou virtuel",
                "Exploiter un modèle d'un système réel ou virtuel",
                "Mettre en œuvre une démarche expérimentale",
                "Concevoir un système répondant à un cahier des charges",
                "Agir de manière responsable dans un monde complexe"
              ]
            }
          },
          {
            "UE": "Enseignements Transversaux (GEA-4-UE41)",
            "url": "http://planete.insa-lyon.fr/scolpeda/f/ects?id=37461&_lang=fr",
            "detail": {
              "code": "GEA-4-AU2",
              "ects": "2.0",
              "cours": "16.0 h",
              "td": "16.0 h",
              "tp": "12.0 h",
              "projet": "0.0 h",
              "perso": "0.0 h",
              "nom": "Automatique : Automatique - Commande numérique des systèmes linéaires",
              "competencesBrutes": "Cet EC relève de l'unité d'enseignement  (UE41) et contribue aux compétences suivantes :  - Mettre en œuvre les étapes permettant le contrôle du fonctionnement d'un système discret ou continu (niveau 3)  --- Capacité : Savoir calculer les différentes marges de stabilité d'un correcteur --- Capacité : Etre capable d'analyser la robustesse d'un correcteur --- Capacité : Savoir interpréter ces fonctions de sensibilité --- Capacité : Savoir discrétiser un processus continu de base --- Capacité : Savoir analyser la stabilté d'un système échantillonné --- Capacité : Savoir traduire un cahier des charges en asservissement et en régulation --- Capacité : Savoir effectuer la synthèse par placement de pôles et de zéros : PI, PID filtré numérique, Dead-Beat --- Capacité : Savoir  effectuer la synthèse d'un correcteur pour des processus avec des zéros instables, des retards, des saturations¿ --- Capacité : Savoir synthétiser une commande par modèle interne --- Capacité : Savoir synthétiser une commande RST  --- Connaissance : Connaître la définition des différentes fonctions de sensibilité --- Connaissance : Savoir la différence entre synthèse continue et synthèse échantillonnée d'un correcteur --- Connaissance : Comprendre le fonctionnement d'une commande prédictive fonctionnelle  - Concevoir et développer des logiciels haut et bas niveau pour des systèmes (traitement et gestion de l'information) (niveau 2)  --- Capacité : Savoir simuler un système asservi échantillonné avec Matlab/Simulink --- Capacité : Savoir traduire un correcteur numérique par des équations de récurrence --- Capacité : Savoir donner un algorithme d'une commande numérique  --- Connaissance : Connaître les fonctions de base de Matlab/Simulik en continu et en discret  De plus, elle nécessite de mobiliser les compétences suivantes :  -- Analyser un système (ou un problème) réel ou virtuel -- Exploiter un modèle d'un système réel ou virtuel -- Mettre en œuvre une démarche expérimentale -- Concevoir un système répondant à un cahier des charges -- Traiter des données -- Communiquer une analyse ou une démarche scientifique -- Agir de manière responsable dans un monde complexe -- Se situer, travailler, évoluer dans une entreprise, une organisation socio-productive",
              "capacite": [
                "Capacité : Savoir calculer les différentes marges de stabilité d'un correcteur",
                "Capacité : Etre capable d'analyser la robustesse d'un correcteur",
                "Capacité : Savoir interpréter ces fonctions de sensibilité",
                "Capacité : Savoir discrétiser un processus continu de base",
                "Capacité : Savoir analyser la stabilté d'un système échantillonné",
                "Capacité : Savoir traduire un cahier des charges en asservissement et en régulation",
                "Capacité : Savoir effectuer la synthèse par placement de pôles et de zéros : PI, PID filtré numérique, Dead-Beat",
                "Capacité : Savoir  effectuer la synthèse d'un correcteur pour des processus avec des zéros instables, des retards, des saturations'",
                "Capacité : Savoir synthétiser une commande par modèle interne",
                "Capacité : Savoir synthétiser une commande RST",
                "Capacité : Savoir simuler un système asservi échantillonné avec Matlab/Simulink",
                "Capacité : Savoir traduire un correcteur numérique par des équations de récurrence",
                "Capacité : Savoir donner un algorithme d'une commande numérique"
              ],
              "connaissance": [
                "Connaissance : Connaître la définition des différentes fonctions de sensibilité",
                "Connaissance : Savoir la différence entre synthèse continue et synthèse échantillonnée d'un correcteur",
                "Connaissance : Comprendre le fonctionnement d'une commande prédictive fonctionnelle",
                "Connaissance : Connaître les fonctions de base de Matlab/Simulik en continu et en discret"
              ],
              "competenceToCapaciteEtConnaissance": {
                "GEA-C6": [
                  "Capacité : Savoir calculer les différentes marges de stabilité d'un correcteur",
                  "Capacité : Etre capable d'analyser la robustesse d'un correcteur",
                  "Capacité : Savoir interpréter ces fonctions de sensibilité",
                  "Capacité : Savoir discrétiser un processus continu de base",
                  "Capacité : Savoir analyser la stabilté d'un système échantillonné",
                  "Capacité : Savoir traduire un cahier des charges en asservissement et en régulation",
                  "Capacité : Savoir effectuer la synthèse par placement de pôles et de zéros : PI, PID filtré numérique, Dead-Beat",
                  "Capacité : Savoir  effectuer la synthèse d'un correcteur pour des processus avec des zéros instables, des retards, des saturations'",
                  "Capacité : Savoir synthétiser une commande par modèle interne",
                  "Capacité : Savoir synthétiser une commande RST",
                  "Connaissance : Connaître la définition des différentes fonctions de sensibilité",
                  "Connaissance : Savoir la différence entre synthèse continue et synthèse échantillonnée d'un correcteur",
                  "Connaissance : Comprendre le fonctionnement d'une commande prédictive fonctionnelle"
                ],
                "GEA-C7": [
                  "Capacité : Savoir simuler un système asservi échantillonné avec Matlab/Simulink",
                  "Capacité : Savoir traduire un correcteur numérique par des équations de récurrence",
                  "Capacité : Savoir donner un algorithme d'une commande numérique",
                  "Connaissance : Connaître les fonctions de base de Matlab/Simulik en continu et en discret"
                ]
              },
              "listeComp": [
                {
                  "code": "C6",
                  "val": "Mettre en œuvre les étapes permettant le contrôle du fonctionnement d'un système discret ou continu",
                  "valAnglais": "Implement steps to control the operation of a discrete or continuous system",
                  "niveau": "3"
                },
                {
                  "code": "C7",
                  "val": "Concevoir et développer des logiciels haut et bas niveau pour des systèmes (traitement et gestion de l'information)",
                  "valAnglais": "Design and develop high and low level software for systems (information processing and management)",
                  "niveau": "2"
                }
              ],
              "listeCompMobilise": [
                "Analyser un système (ou un problème) réel ou virtuel",
                "Exploiter un modèle d'un système réel ou virtuel",
                "Mettre en œuvre une démarche expérimentale",
                "Concevoir un système répondant à un cahier des charges",
                "Traiter des données",
                "Communiquer une analyse ou une démarche scientifique",
                "Agir de manière responsable dans un monde complexe",
                "Se situer, travailler, évoluer dans une entreprise, une organisation socio-productive"
              ]
            }
          },
          {
            "UE": "Enseignements Transversaux (GEA-4-UE41)",
            "url": "http://planete.insa-lyon.fr/scolpeda/f/ects?id=37641&_lang=fr",
            "detail": {
              "code": "GEA-4-TT",
              "ects": "1.0",
              "cours": "10.0 h",
              "td": "10.0 h",
              "tp": "28.0 h",
              "projet": "0.0 h",
              "perso": "15.0 h",
              "nom": "Transferts Thermiques : Transferts Thermiques",
              "competencesBrutes": "Cet EC relève de l'unité d'enseignement  (UE41) et contribue aux compétences suivantes :  - Mettre en œuvre les propriétés physiques des matériaux pour le domaine du génie électrique (niveau 2)  --- Capacité : Comprendre et dialoguer avec un spécialiste des transferts thermiques --- Capacité : Choisir des matériaux pour le contrôle thermique de systèmes électriques/ électroniques --- Capacité : Résoudre un problème simple de transfert de chaleur  --- Connaissance : Principales propriétés thermophysiques mises en jeux dans un problème de transfert de chaleur --- Connaissance : Modes de transferts de chaleur et ordre de grandeur --- Connaissance : Technologie de refroidissement passifs et actifs de systèmes électriques/ électroniques  - Mettre en œuvre des composants électroniques analogiques et/ou numériques et identifier leur fonction au sein d'un montage (niveau 1)  --- Capacité : Comprendre et dialoguer avec un spécialiste des transferts thermiques --- Capacité : Prendre en compte les contraintes thermiques dans le choix des composants --- Capacité : Prendre en compte les contraintes thermiques dans la conception d'une carte électronique --- Capacité : Comprendre et dialoguer avec un spécialiste des transferts thermiques --- Capacité : Prendre en compte les contraintes thermiques dans la conception des systèmes --- Capacité : Comprendre et dialoguer avec un spécialiste des transferts thermiques --- Capacité : Prendre en compte les contraintes thermiques dans la conception des systèmes électroniques --- Capacité : Prendre en compte les contraintes thermiques dans le choix des composants  --- Connaissance : Modèlisation thermique de composants --- Connaissance : Modes de transferts de chaleur et ordre de grandeur --- Connaissance : Technologie de refroidissement passifs et actifs des composants --- Connaissance : Modèlisation thermique des systèmes --- Connaissance : Mise en œuvre des méthodes nodales et des méthodes numériques --- Connaissance : Technologie de refroidissement passifs et actifs de systèmes --- Connaissance : Modèlisation thermique des composants --- Connaissance : Modes de transferts de chaleur et ordre de grandeur --- Connaissance : Technologie de refroidissement passifs et actifs de systèmes  De plus, elle nécessite de mobiliser les compétences suivantes :  - Mettre en œuvre les différents éléments de production d'énergie, de transport d'énergie électrique et de conversion d'énergie - Concevoir et réaliser des systèmes électroniques pour l'acquisition, le traitement, la commande et la communication de données -- Analyser un système (ou un problème) réel ou virtuel -- Exploiter un modèle d'un système réel ou virtuel -- Mettre en œuvre une démarche expérimentale -- Concevoir un système répondant à un cahier des charges -- Traiter des données -- Communiquer une analyse ou une démarche scientifique",
              "capacite": [
                "Capacité : Comprendre et dialoguer avec un spécialiste des transferts thermiques",
                "Capacité : Choisir des matériaux pour le contrôle thermique de systèmes électriques/ électroniques",
                "Capacité : Résoudre un problème simple de transfert de chaleur",
                "Capacité : Comprendre et dialoguer avec un spécialiste des transferts thermiques",
                "Capacité : Prendre en compte les contraintes thermiques dans le choix des composants",
                "Capacité : Prendre en compte les contraintes thermiques dans la conception d'une carte électronique",
                "Capacité : Comprendre et dialoguer avec un spécialiste des transferts thermiques",
                "Capacité : Prendre en compte les contraintes thermiques dans la conception des systèmes",
                "Capacité : Comprendre et dialoguer avec un spécialiste des transferts thermiques",
                "Capacité : Prendre en compte les contraintes thermiques dans la conception des systèmes électroniques",
                "Capacité : Prendre en compte les contraintes thermiques dans le choix des composants"
              ],
              "connaissance": [
                "Connaissance : Principales propriétés thermophysiques mises en jeux dans un problème de transfert de chaleur",
                "Connaissance : Modes de transferts de chaleur et ordre de grandeur",
                "Connaissance : Technologie de refroidissement passifs et actifs de systèmes électriques/ électroniques",
                "Connaissance : Modèlisation thermique de composants",
                "Connaissance : Modes de transferts de chaleur et ordre de grandeur",
                "Connaissance : Technologie de refroidissement passifs et actifs des composants",
                "Connaissance : Modèlisation thermique des systèmes",
                "Connaissance : Mise en œuvre des méthodes nodales et des méthodes numériques",
                "Connaissance : Technologie de refroidissement passifs et actifs de systèmes",
                "Connaissance : Modèlisation thermique des composants",
                "Connaissance : Modes de transferts de chaleur et ordre de grandeur",
                "Connaissance : Technologie de refroidissement passifs et actifs de systèmes"
              ],
              "competenceToCapaciteEtConnaissance": {
                "GEA-C2": [
                  "Capacité : Comprendre et dialoguer avec un spécialiste des transferts thermiques",
                  "Capacité : Choisir des matériaux pour le contrôle thermique de systèmes électriques/ électroniques",
                  "Capacité : Résoudre un problème simple de transfert de chaleur",
                  "Connaissance : Principales propriétés thermophysiques mises en jeux dans un problème de transfert de chaleur",
                  "Connaissance : Modes de transferts de chaleur et ordre de grandeur",
                  "Connaissance : Technologie de refroidissement passifs et actifs de systèmes électriques/ électroniques"
                ],
                "GEA-C1": [
                  "Capacité : Comprendre et dialoguer avec un spécialiste des transferts thermiques",
                  "Capacité : Prendre en compte les contraintes thermiques dans le choix des composants",
                  "Capacité : Prendre en compte les contraintes thermiques dans la conception d'une carte électronique",
                  "Capacité : Comprendre et dialoguer avec un spécialiste des transferts thermiques",
                  "Capacité : Prendre en compte les contraintes thermiques dans la conception des systèmes",
                  "Capacité : Comprendre et dialoguer avec un spécialiste des transferts thermiques",
                  "Capacité : Prendre en compte les contraintes thermiques dans la conception des systèmes électroniques",
                  "Capacité : Prendre en compte les contraintes thermiques dans le choix des composants",
                  "Connaissance : Modèlisation thermique de composants",
                  "Connaissance : Modes de transferts de chaleur et ordre de grandeur",
                  "Connaissance : Technologie de refroidissement passifs et actifs des composants",
                  "Connaissance : Modèlisation thermique des systèmes",
                  "Connaissance : Mise en œuvre des méthodes nodales et des méthodes numériques",
                  "Connaissance : Technologie de refroidissement passifs et actifs de systèmes",
                  "Connaissance : Modèlisation thermique des composants",
                  "Connaissance : Modes de transferts de chaleur et ordre de grandeur",
                  "Connaissance : Technologie de refroidissement passifs et actifs de systèmes"
                ]
              },
              "listeComp": [
                {
                  "code": "C2",
                  "val": "Mettre en œuvre les propriétés physiques des matériaux pour le domaine du génie électrique",
                  "valAnglais": "Implement the physical properties of materials for the field of electrical engineering",
                  "niveau": "2"
                },
                {
                  "code": "C1",
                  "val": "Mettre en œuvre des composants électroniques analogiques et/ou numériques et identifier leur fonction au sein d'un montage",
                  "valAnglais": "Implement analog and / or digital electronic components and identify their function within an assembly",
                  "niveau": "1"
                }
              ],
              "listeCompMobilise": [
                "Mettre en œuvre les différents éléments de production d'énergie, de transport d'énergie électrique et de conversion d'énergie",
                "Concevoir et réaliser des systèmes électroniques pour l'acquisition, le traitement, la commande et la communication de données",
                "Analyser un système (ou un problème) réel ou virtuel",
                "Exploiter un modèle d'un système réel ou virtuel",
                "Mettre en œuvre une démarche expérimentale",
                "Concevoir un système répondant à un cahier des charges",
                "Traiter des données",
                "Communiquer une analyse ou une démarche scientifique"
              ]
            }
          },
          {
            "UE": "Enseignements Techniques (GEA-4-UE42)",
            "url": "http://planete.insa-lyon.fr/scolpeda/f/ects?id=39186&_lang=fr",
            "detail": {
              "code": "GEA-4-TC21",
              "ects": "2.0",
              "cours": "9.0 h",
              "td": "9.0 h",
              "tp": "4.0 h",
              "projet": "0.0 h",
              "perso": "20.0 h",
              "nom": "Télécommunications : Circuits actifs RF-Antennes",
              "competencesBrutes": "Cet EC relève de l'unité d'enseignement  (UE42) et contribue aux compétences suivantes :  - Mettre en œuvre des composants électroniques analogiques et/ou numériques et identifier leur fonction au sein d'un montage (niveau 3)  --- Capacité : Décrire le fonctionnement physique d'une antenne (domaine RF) --- Capacité : Analyser une fiche technique d'antenne --- Capacité : Calculer le diagramme de rayonnement d'une antenne --- Capacité : Simuler et analyser le fonctionnement électromagnétique et électrique d'une antenne --- Capacité : Ecrire et analyser un bilan de liaison hertzienne  --- Connaissance : Principes de base du rayonnement --- Connaissance : Types d'antennes, caractéristiques physiques et électriques --- Connaissance : Identifier la structure d'un bilan de liaison hertzienne --- Connaissance : Fonctionnement physique d'une antenne  - Concevoir et réaliser des systèmes électroniques pour l'acquisition, le traitement, la commande et la communication de données (niveau 3)  --- Capacité : Concevoir et optimiser une antenne à partir d'un cahier des charges --- Capacité : Dimensionner un bilan de liaison --- Capacité : Optimiser le rendement d'une transmission radio --- Capacité : Tenir compte de l'environnement de travail d'une antenne --- Capacité : Organiser et partitionner un travail de conception et d'analyse --- Capacité : Confronter théorie et simulation --- Capacité : Respecter un cahier des charges et justifier ses choix  --- Connaissance : Couverture et planification radio --- Connaissance : Sensibilité, dynamique d'un système d'émission-réception RF --- Connaissance : Type de polarisation et impact sur le rendement --- Connaissance : Architecture générale des systèmes d'émission et de réception --- Connaissance : Apprentissage par projets - Etude de cas --- Connaissance : Utilisation d'outils spécifiques --- Connaissance : Lecture et analyse d'un cahier des charges  De plus, elle nécessite de mobiliser les compétences suivantes :  - Spécifier, modéliser et concevoir les méthodes et algorithmes pour le traitement et la gestion de l'information véhiculée par les signaux et les images -- Analyser un système (ou un problème) réel ou virtuel -- Exploiter un modèle d'un système réel ou virtuel -- Concevoir un système répondant à un cahier des charges -- Communiquer une analyse ou une démarche scientifique -- Travailler, apprendre, évoluer de manière autonome -- Interagir avec les autres, travailler en équipe",
              "capacite": [
                "Capacité : Décrire le fonctionnement physique d'une antenne (domaine RF)",
                "Capacité : Analyser une fiche technique d'antenne",
                "Capacité : Calculer le diagramme de rayonnement d'une antenne",
                "Capacité : Simuler et analyser le fonctionnement électromagnétique et électrique d'une antenne",
                "Capacité : Ecrire et analyser un bilan de liaison hertzienne",
                "Capacité : Concevoir et optimiser une antenne à partir d'un cahier des charges",
                "Capacité : Dimensionner un bilan de liaison",
                "Capacité : Optimiser le rendement d'une transmission radio",
                "Capacité : Tenir compte de l'environnement de travail d'une antenne",
                "Capacité : Organiser et partitionner un travail de conception et d'analyse",
                "Capacité : Confronter théorie et simulation",
                "Capacité : Respecter un cahier des charges et justifier ses choix"
              ],
              "connaissance": [
                "Connaissance : Principes de base du rayonnement",
                "Connaissance : Types d'antennes, caractéristiques physiques et électriques",
                "Connaissance : Identifier la structure d'un bilan de liaison hertzienne",
                "Connaissance : Fonctionnement physique d'une antenne",
                "Connaissance : Couverture et planification radio",
                "Connaissance : Sensibilité, dynamique d'un système d'émission-réception RF",
                "Connaissance : Type de polarisation et impact sur le rendement",
                "Connaissance : Architecture générale des systèmes d'émission et de réception",
                "Connaissance : Apprentissage par projets"
              ],
              "competenceToCapaciteEtConnaissance": {
                "GEA-C1": [
                  "Capacité : Décrire le fonctionnement physique d'une antenne (domaine RF)",
                  "Capacité : Analyser une fiche technique d'antenne",
                  "Capacité : Calculer le diagramme de rayonnement d'une antenne",
                  "Capacité : Simuler et analyser le fonctionnement électromagnétique et électrique d'une antenne",
                  "Capacité : Ecrire et analyser un bilan de liaison hertzienne",
                  "Connaissance : Principes de base du rayonnement",
                  "Connaissance : Types d'antennes, caractéristiques physiques et électriques",
                  "Connaissance : Identifier la structure d'un bilan de liaison hertzienne",
                  "Connaissance : Fonctionnement physique d'une antenne"
                ],
                "GEA-C5": [
                  "Capacité : Concevoir et optimiser une antenne à partir d'un cahier des charges",
                  "Capacité : Dimensionner un bilan de liaison",
                  "Capacité : Optimiser le rendement d'une transmission radio",
                  "Capacité : Tenir compte de l'environnement de travail d'une antenne",
                  "Capacité : Organiser et partitionner un travail de conception et d'analyse",
                  "Capacité : Confronter théorie et simulation",
                  "Capacité : Respecter un cahier des charges et justifier ses choix",
                  "Connaissance : Couverture et planification radio",
                  "Connaissance : Sensibilité, dynamique d'un système d'émission-réception RF",
                  "Connaissance : Type de polarisation et impact sur le rendement",
                  "Connaissance : Architecture générale des systèmes d'émission et de réception",
                  "Connaissance : Apprentissage par projets"
                ]
              },
              "listeCompMobilise": [
                "Spécifier, modéliser et concevoir les méthodes et algorithmes pour le traitement et la gestion de l'information véhiculée par les signaux et les images",
                "Analyser un système (ou un problème) réel ou virtuel",
                "Exploiter un modèle d'un système réel ou virtuel",
                "Concevoir un système répondant à un cahier des charges",
                "Communiquer une analyse ou une démarche scientifique",
                "Travailler, apprendre, évoluer de manière autonome",
                "Interagir avec les autres, travailler en équipe"
              ]
            }
          },
          {
            "UE": "Enseignements Techniques (GEA-4-UE42)",
            "url": "http://planete.insa-lyon.fr/scolpeda/f/ects?id=39185&_lang=fr",
            "detail": {
              "code": "GEA-4-IF2",
              "ects": "1.0",
              "cours": "11.0 h",
              "td": "11.0 h",
              "tp": "4.0 h",
              "projet": "0.0 h",
              "perso": "15.0 h",
              "nom": "Informatique Industrielle et Environnement PC, Modélisation orientée : objet UML",
              "competencesBrutes": "Cet EC relève de l'unité d'enseignement  (UE42) et contribue aux compétences suivantes :  - Spécifier, modéliser et concevoir les méthodes et algorithmes pour le traitement et la gestion de l'information véhiculée par les signaux et les images (niveau 2)  --- Capacité : Etre capable d'évaluer et comparer des approches mathématiques et algorithmiques --- Capacité : Etre capable de planifier et organiser une réalisation informatique en petit groupe --- Capacité : Etre capable de résoudre des problémes algorithmques pour l'interfacage et le traitement des signaux  --- Connaissance : Algorithmes de gestion des entrées et sorties --- Connaissance : Algorithmie des éléments d'analyse numérique  - Concevoir et développer des logiciels haut et bas niveau pour des systèmes (traitement et gestion de l'information) (niveau 2)  --- Capacité : Etre capable de développer des logiciels de haut niveaux (C++) --- Capacité : Etre capable de modéliser des logiciels de haut niveau (UML) --- Capacité : Etre capable de maîtriser les outils de développement (IDE) et de création d'interface (IHM)  --- Connaissance : Langage C++ --- Connaissance : IDE et compilation --- Connaissance : Gestion des bibliothèques, IHM  De plus, elle nécessite de mobiliser les compétences suivantes :  -- Analyser un système (ou un problème) réel ou virtuel -- Exploiter un modèle d'un système réel ou virtuel -- Mettre en œuvre une démarche expérimentale -- Concevoir un système répondant à un cahier des charges -- Traiter des données -- Communiquer une analyse ou une démarche scientifique -- Travailler, apprendre, évoluer de manière autonome -- Interagir avec les autres, travailler en équipe -- Agir de manière responsable dans un monde complexe -- Se situer, travailler, évoluer dans une entreprise, une organisation socio-productive",
              "capacite": [
                "Capacité : Etre capable d'évaluer et comparer des approches mathématiques et algorithmiques",
                "Capacité : Etre capable de planifier et organiser une réalisation informatique en petit groupe",
                "Capacité : Etre capable de résoudre des problémes algorithmques pour l'interfacage et le traitement des signaux",
                "Capacité : Etre capable de développer des logiciels de haut niveaux (C++)",
                "Capacité : Etre capable de modéliser des logiciels de haut niveau (UML)",
                "Capacité : Etre capable de maîtriser les outils de développement (IDE) et de création d'interface (IHM)"
              ],
              "connaissance": [
                "Connaissance : Algorithmes de gestion des entrées et sorties",
                "Connaissance : Algorithmie des éléments d'analyse numérique",
                "Connaissance : Langage C++",
                "Connaissance : IDE et compilation",
                "Connaissance : Gestion des bibliothèques, IHM"
              ],
              "competenceToCapaciteEtConnaissance": {
                "GEA-C4": [
                  "Capacité : Etre capable d'évaluer et comparer des approches mathématiques et algorithmiques",
                  "Capacité : Etre capable de planifier et organiser une réalisation informatique en petit groupe",
                  "Capacité : Etre capable de résoudre des problémes algorithmques pour l'interfacage et le traitement des signaux",
                  "Connaissance : Algorithmes de gestion des entrées et sorties",
                  "Connaissance : Algorithmie des éléments d'analyse numérique"
                ],
                "GEA-C7": [
                  "Capacité : Etre capable de développer des logiciels de haut niveaux (C++)",
                  "Capacité : Etre capable de modéliser des logiciels de haut niveau (UML)",
                  "Capacité : Etre capable de maîtriser les outils de développement (IDE) et de création d'interface (IHM)",
                  "Connaissance : Langage C++",
                  "Connaissance : IDE et compilation",
                  "Connaissance : Gestion des bibliothèques, IHM"
                ]
              },
              "listeComp": [
                {
                  "code": "C4",
                  "val": "Spécifier, modéliser et concevoir les méthodes et algorithmes pour le traitement et la gestion de l'information véhiculée par les signaux et les images",
                  "valAnglais": "Specify, model and design methods and algorithms for the processing and management of information conveyed by signals and images",
                  "niveau": "2"
                },
                {
                  "code": "C7",
                  "val": "Concevoir et développer des logiciels haut et bas niveau pour des systèmes (traitement et gestion de l'information)",
                  "valAnglais": "Design and develop high and low level software for systems (information processing and management)",
                  "niveau": "2"
                }
              ],
              "listeCompMobilise": [
                "Analyser un système (ou un problème) réel ou virtuel",
                "Exploiter un modèle d'un système réel ou virtuel",
                "Mettre en œuvre une démarche expérimentale",
                "Concevoir un système répondant à un cahier des charges",
                "Traiter des données",
                "Communiquer une analyse ou une démarche scientifique",
                "Travailler, apprendre, évoluer de manière autonome",
                "Interagir avec les autres, travailler en équipe",
                "Agir de manière responsable dans un monde complexe",
                "Se situer, travailler, évoluer dans une entreprise, une organisation socio-productive"
              ]
            }
          },
          {
            "UE": "Enseignements Techniques (GEA-4-UE42)",
            "url": "http://planete.insa-lyon.fr/scolpeda/f/ects?id=39184&_lang=fr",
            "detail": {
              "code": "GEA-4-IF3",
              "ects": "1.0",
              "cours": "10.0 h",
              "td": "14.0 h",
              "tp": "4.0 h",
              "projet": "0.0 h",
              "perso": "15.0 h",
              "nom": "Informatique Industrielle : Informatique Industrielle et Environnement PC",
              "competencesBrutes": "Cet EC relève de l'unité d'enseignement  (UE42) et contribue aux compétences suivantes :  - Spécifier, modéliser et concevoir les méthodes et algorithmes pour le traitement et la gestion de l'information véhiculée par les signaux et les images (niveau 3)  --- Capacité : Etre capable de concevoir et développer des logiciels de bas niveau interruptibles  --- Connaissance : Structure et mécanismes des routines d'interruption et des échanges d'information --- Connaissance : Architecture des microcontroleurs --- Connaissance : Programmation en C  - Concevoir et développer des logiciels haut et bas niveau pour des systèmes (traitement et gestion de l'information) (niveau 3)  --- Capacité : Etre capable de concevoir et développer des logiciels de bas niveau interruptibles --- Capacité : Etre capable d'observer, d'identifier et d'expérimenter l'éxécution d'un programme en langage machine avec interruption --- Capacité : Etre capable d'écrire et tester un programme en langage C sur un microcontroleur --- Capacité : Etre capable d'implémenter une application en langage C --- Capacité : Etre capable d'écrire et tester un programme en langage C  --- Connaissance : Structure des applications informatiques gérant des interruptions --- Connaissance : Principe et fonctionnement des interruptions vectorisées --- Connaissance : Notions de bas sur le fonctionnement et la programmation en langage C des microcontroleur --- Connaissance : Notions sur la compilation et le développement langage C  - Mettre en œuvre des principes et stratégies d'ordonnancements des tâches et de gestion (niveau 2)  --- Capacité : Etre capable de concevoir et développer des logiciels de bas niveau interruptibles --- Capacité : Etre capable d'observer, d'identifier et d'expérimenter l'éxécution d'un programme en langage machine avec interruption --- Capacité : Etre capable d'écrire et tester un programme en langage C sur un microcontroleur  --- Connaissance : Structure des applications informatiques gérant des interruptions --- Connaissance : Principe et fonctionnement des interruptions vectorisées  De plus, elle nécessite de mobiliser les compétences suivantes :  -- Analyser un système (ou un problème) réel ou virtuel -- Exploiter un modèle d'un système réel ou virtuel -- Mettre en œuvre une démarche expérimentale -- Concevoir un système répondant à un cahier des charges",
              "capacite": [
                "Capacité : Etre capable de concevoir et développer des logiciels de bas niveau interruptibles",
                "Capacité : Etre capable de concevoir et développer des logiciels de bas niveau interruptibles",
                "Capacité : Etre capable d'observer, d'identifier et d'expérimenter l'éxécution d'un programme en langage machine avec interruption",
                "Capacité : Etre capable d'écrire et tester un programme en langage C sur un microcontroleur",
                "Capacité : Etre capable d'implémenter une application en langage C",
                "Capacité : Etre capable d'écrire et tester un programme en langage C",
                "Capacité : Etre capable de concevoir et développer des logiciels de bas niveau interruptibles",
                "Capacité : Etre capable d'observer, d'identifier et d'expérimenter l'éxécution d'un programme en langage machine avec interruption",
                "Capacité : Etre capable d'écrire et tester un programme en langage C sur un microcontroleur"
              ],
              "connaissance": [
                "Connaissance : Structure et mécanismes des routines d'interruption et des échanges d'information",
                "Connaissance : Architecture des microcontroleurs",
                "Connaissance : Programmation en C",
                "Connaissance : Structure des applications informatiques gérant des interruptions",
                "Connaissance : Principe et fonctionnement des interruptions vectorisées",
                "Connaissance : Notions de bas sur le fonctionnement et la programmation en langage C des microcontroleur",
                "Connaissance : Notions sur la compilation et le développement langage C",
                "Connaissance : Structure des applications informatiques gérant des interruptions",
                "Connaissance : Principe et fonctionnement des interruptions vectorisées"
              ],
              "competenceToCapaciteEtConnaissance": {
                "GEA-C4": [
                  "Capacité : Etre capable de concevoir et développer des logiciels de bas niveau interruptibles",
                  "Connaissance : Structure et mécanismes des routines d'interruption et des échanges d'information",
                  "Connaissance : Architecture des microcontroleurs",
                  "Connaissance : Programmation en C"
                ],
                "GEA-C7": [
                  "Capacité : Etre capable de concevoir et développer des logiciels de bas niveau interruptibles",
                  "Capacité : Etre capable d'observer, d'identifier et d'expérimenter l'éxécution d'un programme en langage machine avec interruption",
                  "Capacité : Etre capable d'écrire et tester un programme en langage C sur un microcontroleur",
                  "Capacité : Etre capable d'implémenter une application en langage C",
                  "Capacité : Etre capable d'écrire et tester un programme en langage C",
                  "Connaissance : Structure des applications informatiques gérant des interruptions",
                  "Connaissance : Principe et fonctionnement des interruptions vectorisées",
                  "Connaissance : Notions de bas sur le fonctionnement et la programmation en langage C des microcontroleur",
                  "Connaissance : Notions sur la compilation et le développement langage C"
                ],
                "GEA-C8": [
                  "Capacité : Etre capable de concevoir et développer des logiciels de bas niveau interruptibles",
                  "Capacité : Etre capable d'observer, d'identifier et d'expérimenter l'éxécution d'un programme en langage machine avec interruption",
                  "Capacité : Etre capable d'écrire et tester un programme en langage C sur un microcontroleur",
                  "Connaissance : Structure des applications informatiques gérant des interruptions",
                  "Connaissance : Principe et fonctionnement des interruptions vectorisées"
                ]
              },
              "listeComp": [
                {
                  "code": "C4",
                  "val": "Spécifier, modéliser et concevoir les méthodes et algorithmes pour le traitement et la gestion de l'information véhiculée par les signaux et les images",
                  "valAnglais": "Specify, model and design methods and algorithms for the processing and management of information conveyed by signals and images",
                  "niveau": "3"
                },
                {
                  "code": "C7",
                  "val": "Concevoir et développer des logiciels haut et bas niveau pour des systèmes (traitement et gestion de l'information)",
                  "valAnglais": "Design and develop high and low level software for systems (information processing and management)",
                  "niveau": "3"
                },
                {
                  "code": "C8",
                  "val": "Mettre en œuvre des principes et stratégies d'ordonnancements des tâches et de gestion",
                  "valAnglais": "Implement principles and strategies for scheduling tasks and managing",
                  "niveau": "2"
                }
              ],
              "listeCompMobilise": [
                "Analyser un système (ou un problème) réel ou virtuel",
                "Exploiter un modèle d'un système réel ou virtuel",
                "Mettre en œuvre une démarche expérimentale",
                "Concevoir un système répondant à un cahier des charges"
              ]
            }
          },
          {
            "UE": "Enseignements Techniques (GEA-4-UE42)",
            "url": "http://planete.insa-lyon.fr/scolpeda/f/ects?id=39188&_lang=fr",
            "detail": {
              "code": "GEA-4-EC3",
              "ects": "2.0",
              "cours": "10.0 h",
              "td": "10.0 h",
              "tp": "16.0 h",
              "projet": "0.0 h",
              "perso": "20.0 h",
              "nom": "Electronique : Electronique et Capteurs, partie 3",
              "competencesBrutes": "Cet EC relève de l'unité d'enseignement  (UE42) et contribue aux compétences suivantes :  - Mettre en œuvre des composants électroniques analogiques et/ou numériques et identifier leur fonction au sein d'un montage (niveau 2)  -- Sous compétence : Conception et mise en œuvre de circuits numériques à l'aide du langage VHDL  --- Capacité : Ecrire la description correspondant au fonctionnement d'un circuit avec les instructions VHDL appropriées --- Capacité : Mettre en oeuvre les différentes étapes du flot de conception avec les outils appropriés pour implémenter des fonctions logiques simples --- Capacité : Ecrire les bancs de test pour la réalisation de simulations fonctionnelles --- Capacité : Tester et valider un circuit numérique à l'aide d'un analyseur logique  --- Connaissance : Principes généraux et fondamentaux du langage VHDL --- Connaissance : Electronique numérique (systèmes logiques)  - Mettre en œuvre les propriétés physiques des matériaux pour le domaine du génie électrique (niveau 2)  -- Sous compétence : Mettre en œuvre les propriétés physiques des matériaux pour l'optoélectronique  --- Capacité : Dimensionner une fibre optique pour les applications en télécommunication --- Capacité : Dimensionner une diode laser  --- Connaissance : Capteurs couleurs CCD, CMOS --- Connaissance : Physique du semiconducteur pour l'optoélectronique --- Connaissance : Propagation de la lumière dans un milieu transparent  - Concevoir et réaliser des systèmes électroniques pour l'acquisition, le traitement, la commande et la communication de données (niveau 2)  -- Sous compétence : Conception de systèmes numériques à l'aide du langage VHDL  --- Capacité : Concevoir des systèmes numériques répondant aux besoins d'un cahier des charges --- Capacité : Configurer le FPGA pour qu'il communique avec des périphériques (CAN, CNA, etc) --- Capacité : Tester et valider un système numérique à l'aide d'un analyseur logique  --- Connaissance : Principes généraux et fondamentaux du langage VHDL --- Connaissance : Electronique analogique et numériques, capteurs  -- Sous compétence : Conception de systèmes d'interfaçage optoélectroniques  --- Capacité : Dimensionner un système électronique basé sur des optocoupleurs  --- Connaissance : Fonctions de base de l'électronique analogique --- Connaissance : Composants optoélectroniques  De plus, elle nécessite de mobiliser les compétences suivantes :   -- Analyser un système (ou un problème) réel ou virtuel -- Exploiter un modèle d'un système réel ou virtuel -- Concevoir un système répondant à un cahier des charges -- Communiquer une analyse ou une démarche scientifique -- Travailler, apprendre, évoluer de manière autonome -- Interagir avec les autres, travailler en équipe",
              "capacite": [
                "Capacité : Ecrire la description correspondant au fonctionnement d'un circuit avec les instructions VHDL appropriées",
                "Capacité : Mettre en oeuvre les différentes étapes du flot de conception avec les outils appropriés pour implémenter des fonctions logiques simples",
                "Capacité : Ecrire les bancs de test pour la réalisation de simulations fonctionnelles",
                "Capacité : Tester et valider un circuit numérique à l'aide d'un analyseur logique",
                "Capacité : Dimensionner une fibre optique pour les applications en télécommunication",
                "Capacité : Dimensionner une diode laser",
                "Capacité : Concevoir des systèmes numériques répondant aux besoins d'un cahier des charges",
                "Capacité : Configurer le FPGA pour qu'il communique avec des périphériques (CAN, CNA, etc)",
                "Capacité : Tester et valider un système numérique à l'aide d'un analyseur logique",
                "Capacité : Dimensionner un système électronique basé sur des optocoupleurs"
              ],
              "connaissance": [
                "Connaissance : Principes généraux et fondamentaux du langage VHDL",
                "Connaissance : Electronique numérique (systèmes logiques)",
                "Connaissance : Capteurs couleurs CCD, CMOS",
                "Connaissance : Physique du semiconducteur pour l'optoélectronique",
                "Connaissance : Propagation de la lumière dans un milieu transparent",
                "Connaissance : Principes généraux et fondamentaux du langage VHDL",
                "Connaissance : Electronique analogique et numériques, capteurs",
                "Connaissance : Fonctions de base de l'électronique analogique",
                "Connaissance : Composants optoélectroniques"
              ],
              "competenceToCapaciteEtConnaissance": {
                "GEA-C1": [
                  "Capacité : Ecrire la description correspondant au fonctionnement d'un circuit avec les instructions VHDL appropriées",
                  "Capacité : Mettre en oeuvre les différentes étapes du flot de conception avec les outils appropriés pour implémenter des fonctions logiques simples",
                  "Capacité : Ecrire les bancs de test pour la réalisation de simulations fonctionnelles",
                  "Capacité : Tester et valider un circuit numérique à l'aide d'un analyseur logique",
                  "Connaissance : Principes généraux et fondamentaux du langage VHDL",
                  "Connaissance : Electronique numérique (systèmes logiques)"
                ],
                "GEA-C2": [
                  "Capacité : Dimensionner une fibre optique pour les applications en télécommunication",
                  "Capacité : Dimensionner une diode laser",
                  "Connaissance : Capteurs couleurs CCD, CMOS",
                  "Connaissance : Physique du semiconducteur pour l'optoélectronique",
                  "Connaissance : Propagation de la lumière dans un milieu transparent"
                ],
                "GEA-C5": [
                  "Capacité : Concevoir des systèmes numériques répondant aux besoins d'un cahier des charges",
                  "Capacité : Configurer le FPGA pour qu'il communique avec des périphériques (CAN, CNA, etc)",
                  "Capacité : Tester et valider un système numérique à l'aide d'un analyseur logique",
                  "Connaissance : Principes généraux et fondamentaux du langage VHDL",
                  "Connaissance : Electronique analogique et numériques, capteurs",
                  "Capacité : Dimensionner un système électronique basé sur des optocoupleurs",
                  "Connaissance : Fonctions de base de l'électronique analogique",
                  "Connaissance : Composants optoélectroniques"
                ]
              },
              "listeComp": [
                {
                  "code": "C1",
                  "val": "Mettre en œuvre des composants électroniques analogiques et/ou numériques et identifier leur fonction au sein d'un montage",
                  "valAnglais": "Implement analog and / or digital electronic components and identify their function within an assembly",
                  "niveau": "2"
                },
                {
                  "code": "C2",
                  "val": "Mettre en œuvre les propriétés physiques des matériaux pour le domaine du génie électrique",
                  "valAnglais": "Implement the physical properties of materials for the field of electrical engineering",
                  "niveau": "2"
                },
                {
                  "code": "C5",
                  "val": "Concevoir et réaliser des systèmes électroniques pour l'acquisition, le traitement, la commande et la communication de données",
                  "valAnglais": "Design and build electronic systems for data acquisition, processing, control and communication",
                  "niveau": "2"
                }
              ],
              "listeCompMobilise": [
                "Analyser un système (ou un problème) réel ou virtuel",
                "Exploiter un modèle d'un système réel ou virtuel",
                "Concevoir un système répondant à un cahier des charges",
                "Communiquer une analyse ou une démarche scientifique",
                "Travailler, apprendre, évoluer de manière autonome",
                "Interagir avec les autres, travailler en équipe"
              ]
            }
          },
          {
            "UE": "Humanités et Education Sportive (GEA-4-UE43)",
            "url": "http://planete.insa-lyon.fr/scolpeda/f/ects?id=39495&_lang=fr",
            "detail": {
              "code": "GEA-4-SHS3",
              "ects": "2.0",
              "cours": "40.0 h",
              "td": "0.0 h",
              "tp": "0.0 h",
              "projet": "0.0 h",
              "perso": "0.0 h",
              "nom": "Sciences Humaines et Sociales : Sciences Humaines et Sociales",
              "competencesBrutes": "Cet EC relève de l'unité d'enseignement  (UE43) et contribue aux compétences suivantes :  -- Travailler, apprendre, évoluer de manière autonome (niveau 2)  --- Capacité : Gérer ses activités --- Capacité : Manager les problèmes  --- Connaissance : Management : la gestion du temps, des priorités --- Connaissance : Le rendre compte --- Connaissance : Les instances : facteur clé d'une autonomie résussie  -- Interagir avec les autres, travailler en équipe (niveau 2)  --- Capacité : Comprendre la structure, l'organisation et la culture de son environnement de travail --- Capacité : Animer, motiver une équipe  --- Connaissance : Management : Sociologie des organisations --- Connaissance : Le rôle du manager, la notion d'quipe, la place de chacun au sein de l'organisation --- Connaissance : Comprendre  les leviers de la motivation  -- Faire preuve de créativité, innover, entreprendre (niveau 1)  --- Capacité : Manager des activités novatrices en intégrant les paramètres de réussite des différentes composantes.  -- Agir de manière responsable dans un monde complexe (niveau 2)  --- Capacité : Parfaire sa compréhension de la structure, l'organisation et la culture de son environnement de travail --- Capacité : Gérer les situations conflictuelles adaptée --- Capacité : Repérer les facteurs de motivation et de démotivation --- Capacité : Comprendre la structure, l'organisation et la culture de son environnement de travail --- Capacité : Appréhender son envrionnement de travail --- Capacité : Manager des collaborateurs d'horizons divers.  --- Connaissance : Management: Les différents styles de management selon le degré d'autonomie des collaborateurs  De plus, elle nécessite de mobiliser les compétences suivantes :  -- Se connaître, se gérer physiquement et mentalement -- Se situer, travailler, évoluer dans une entreprise, une organisation socio-productive -- Travailler dans un contexte international et interculturel",
              "capacite": [
                "Capacité : Gérer ses activités",
                "Capacité : Manager les problèmes",
                "Capacité : Comprendre la structure, l'organisation et la culture de son environnement de travail",
                "Capacité : Animer, motiver une équipe",
                "Capacité : Manager des activités novatrices en intégrant les paramètres de réussite des différentes composantes.  -- Agir de manière responsable dans un monde complexe (niveau 2)",
                "Capacité : Parfaire sa compréhension de la structure, l'organisation et la culture de son environnement de travail",
                "Capacité : Gérer les situations conflictuelles adaptée",
                "Capacité : Repérer les facteurs de motivation et de démotivation",
                "Capacité : Comprendre la structure, l'organisation et la culture de son environnement de travail",
                "Capacité : Appréhender son envrionnement de travail",
                "Capacité : Manager des collaborateurs d'horizons divers."
              ],
              "connaissance": [
                "Connaissance : Management : la gestion du temps, des priorités",
                "Connaissance : Le rendre compte",
                "Connaissance : Les instances : facteur clé d'une autonomie résussie  -- Interagir avec les autres, travailler en équipe (niveau 2)",
                "Connaissance : Management : Sociologie des organisations",
                "Connaissance : Le rôle du manager, la notion d'quipe, la place de chacun au sein de l'organisation",
                "Connaissance : Comprendre  les leviers de la motivation  -- Faire preuve de créativité, innover, entreprendre (niveau 1)",
                "Connaissance : Management: Les différents styles de management selon le degré d'autonomie des collaborateurs"
              ],
              "competenceToCapaciteEtConnaissance": {
                "B2": [
                  "Capacité : Gérer ses activités",
                  "Capacité : Manager les problèmes",
                  "Connaissance : Management : la gestion du temps, des priorités",
                  "Connaissance : Le rendre compte",
                  "Connaissance : Les instances : facteur clé d'une autonomie résussie  -- Interagir avec les autres, travailler en équipe (niveau 2)",
                  "Capacité : Comprendre la structure, l'organisation et la culture de son environnement de travail",
                  "Capacité : Animer, motiver une équipe",
                  "Connaissance : Management : Sociologie des organisations",
                  "Connaissance : Le rôle du manager, la notion d'quipe, la place de chacun au sein de l'organisation",
                  "Connaissance : Comprendre  les leviers de la motivation  -- Faire preuve de créativité, innover, entreprendre (niveau 1)",
                  "Capacité : Manager des activités novatrices en intégrant les paramètres de réussite des différentes composantes.  -- Agir de manière responsable dans un monde complexe (niveau 2)",
                  "Capacité : Parfaire sa compréhension de la structure, l'organisation et la culture de son environnement de travail",
                  "Capacité : Gérer les situations conflictuelles adaptée",
                  "Capacité : Repérer les facteurs de motivation et de démotivation",
                  "Capacité : Comprendre la structure, l'organisation et la culture de son environnement de travail",
                  "Capacité : Appréhender son envrionnement de travail",
                  "Capacité : Manager des collaborateurs d'horizons divers.",
                  "Connaissance : Management: Les différents styles de management selon le degré d'autonomie des collaborateurs"
                ]
              },
              "listeComp": [
                {
                  "code": "B2",
                  "val": "Travailler, apprendre, évoluer de manière autonome",
                  "valAnglais": "Work, learn, progress autonomously",
                  "bs": "24",
                  "niveau": "2"
                }
              ],
              "listeCompMobilise": [
                "Se connaître, se gérer physiquement et mentalement",
                "Se situer, travailler, évoluer dans une entreprise, une organisation socio-productive",
                "Travailler dans un contexte international et interculturel"
              ]
            }
          },
          {
            "UE": "Humanités et Education Sportive (GEA-4-UE43)",
            "url": "http://planete.insa-lyon.fr/scolpeda/f/ects?id=39494&_lang=fr",
            "detail": {
              "code": "GEA-4-EPS3",
              "ects": "1.0",
              "cours": "0.0 h",
              "td": "30.0 h",
              "tp": "0.0 h",
              "projet": "0.0 h",
              "perso": "0.0 h",
              "nom": "Education Physique et Sportive : Education Physique et Sportive",
              "competencesBrutes": "- Comprendre les notions de compétition et d'affrontement au travers d'une activité sportive d'opposition. - Expérimenter des stratégies pour gérer la confiance en soi. - Etre capable de faire un bilan de ses atouts et des faiblesses de son adversaire.",
              "capacite": [],
              "connaissance": [],
              "competenceToCapaciteEtConnaissance": {}
            }
          },
          {
            "UE": "Humanités et Education Sportive (GEA-4-UE43)",
            "url": "http://planete.insa-lyon.fr/scolpeda/f/ects?id=39496&_lang=fr",
            "detail": {
              "code": "GEA-4-LA3",
              "ects": "2.0",
              "cours": "36.0 h",
              "td": "0.0 h",
              "tp": "0.0 h",
              "projet": "0.0 h",
              "perso": "0.0 h",
              "nom": "Langues Étrangères : Langues vivantes - Troisième Semestre",
              "competencesBrutes": "Cet EC relève de l'unité d'enseignement  (UE43) et contribue aux compétences suivantes :  - Travailler dans un contexte international et interculturel (niveau 2)  --- Capacité : Obtenir le score minimum de 785 au TOEIC --- Capacité : Comprendre le contenu essentiel de sujets concrets ou abstraits dans un texte complexe, y compris une discussion technique dans votre spécialité --- Capacité : Etre capable d'interagir efficacement lors d'un entretien d'embauche.  --- Connaissance : Lexique, syntaxe, grammaire --- Connaissance : Expression orale --- Connaissance : compréhension orale et écrite  De plus, elle nécessite de mobiliser les compétences suivantes :  -- Communiquer une analyse ou une démarche scientifique",
              "capacite": [
                "Capacité : Obtenir le score minimum de 785 au TOEIC",
                "Capacité : Comprendre le contenu essentiel de sujets concrets ou abstraits dans un texte complexe, y compris une discussion technique dans votre spécialité",
                "Capacité : Etre capable d'interagir efficacement lors d'un entretien d'embauche."
              ],
              "connaissance": [
                "Connaissance : Lexique, syntaxe, grammaire",
                "Connaissance : Expression orale",
                "Connaissance : compréhension orale et écrite"
              ],
              "competenceToCapaciteEtConnaissance": {
                "B7": [
                  "Capacité : Obtenir le score minimum de 785 au TOEIC",
                  "Capacité : Comprendre le contenu essentiel de sujets concrets ou abstraits dans un texte complexe, y compris une discussion technique dans votre spécialité",
                  "Capacité : Etre capable d'interagir efficacement lors d'un entretien d'embauche.",
                  "Connaissance : Lexique, syntaxe, grammaire",
                  "Connaissance : Expression orale",
                  "Connaissance : compréhension orale et écrite"
                ]
              },
              "listeComp": [
                {
                  "code": "B7",
                  "val": "Travailler dans un contexte international et interculturel",
                  "valAnglais": "Work in an international, intercultural context",
                  "bs": "29",
                  "niveau": "2"
                }
              ],
              "listeCompMobilise": [
                "Communiquer une analyse ou une démarche scientifique"
              ]
            }
          },
          {
            "UE": "Projet Entreprise (GEA-4-UE44)",
            "url": "http://planete.insa-lyon.fr/scolpeda/f/ects?id=39189&_lang=fr",
            "detail": {
              "code": "GEA-4-PE3",
              "ects": "14.0",
              "cours": "0.0 h",
              "td": "0.0 h",
              "tp": "0.0 h",
              "projet": "1.0 h",
              "perso": "0.0 h",
              "nom": "Entreprise : Période en entreprise 3",
              "competencesBrutes": "Cet EC relève de l'unité d'enseignement  (UE44) et contribue aux compétences suivantes :  -- Se situer, travailler, évoluer dans une entreprise, une organisation socio-productive (niveau 2)  --- Capacité : Prendre en compte les enjeux économiques d'un projet. --- Capacité : Participer à l'élaboration d'd'un budget et/ou au suivi des coûts. --- Capacité : Contacter des clients ou des fournisseurs pour établir des devis ou répondre à des offres.  --- Connaissance : Enjeux économiques  -- Travailler, apprendre, évoluer de manière autonome (niveau 2)  --- Capacité : Respecter les objectifs et le planning prévisionnel fixé par le projet. --- Capacité : Formaliser avec le Maitre d'Apprentissage les objectifs du projet avec des indicateurs de résultats et un planning prévisionnel pour son travail personnel --- Capacité : Etre force de proposition de solution technique  --- Connaissance : Gestion du temps --- Connaissance : Démarche projet  -- Interagir avec les autres, travailler en équipe (niveau )  --- Capacité : Etre capable de présenter un projet dans sa globalité à l'écrit ou devant un public --- Capacité : Savoir chercher l'information auprès des bonnes personnes.  --- Connaissance : communication, esprit de synthèse  - Mettre en œuvre ses compétences scientifiques et technologiques dans le domaine de l'EEAIIT dans un cadre industriel et appliqué à des problématiques réelles en conduisant les étapes du cycle de conception (niveau )  --- Capacité : Etre associé à plusieurs étapes du cycle en V --- Capacité : mettre en œuvre des sous ensembles multi domaines de l'EEAIIT et/ou multiphysique. --- Capacité : Outils de modélisations et simulation multidomaines --- Capacité : Ecriture de spécifications fonctionnelles et techniques  --- Connaissance : Mise en œuvre de composants ou sous ensemble fonctionnels, Prototypage --- Connaissance : utilisation CAO / DAO, simulation performance.",
              "capacite": [
                "Capacité : Prendre en compte les enjeux économiques d'un projet.",
                "Capacité : Participer à l'élaboration d'd'un budget et/ou au suivi des coûts.",
                "Capacité : Contacter des clients ou des fournisseurs pour établir des devis ou répondre à des offres.",
                "Capacité : Respecter les objectifs et le planning prévisionnel fixé par le projet.",
                "Capacité : Formaliser avec le Maitre d'Apprentissage les objectifs du projet avec des indicateurs de résultats et un planning prévisionnel pour son travail personnel",
                "Capacité : Etre force de proposition de solution technique",
                "Capacité : Etre capable de présenter un projet dans sa globalité à l'écrit ou devant un public",
                "Capacité : Savoir chercher l'information auprès des bonnes personnes.",
                "Capacité : Etre associé à plusieurs étapes du cycle en V",
                "Capacité : mettre en œuvre des sous ensembles multi domaines de l'EEAIIT et/ou multiphysique.",
                "Capacité : Outils de modélisations et simulation multidomaines",
                "Capacité : Ecriture de spécifications fonctionnelles et techniques"
              ],
              "connaissance": [
                "Connaissance : Enjeux économiques  -- Travailler, apprendre, évoluer de manière autonome (niveau 2)",
                "Connaissance : Gestion du temps",
                "Connaissance : Démarche projet  -- Interagir avec les autres, travailler en équipe (niveau )",
                "Connaissance : communication, esprit de synthèse",
                "Connaissance : Mise en œuvre de composants ou sous ensemble fonctionnels, Prototypage",
                "Connaissance : utilisation CAO / DAO, simulation performance."
              ],
              "competenceToCapaciteEtConnaissance": {
                "B6": [
                  "Capacité : Prendre en compte les enjeux économiques d'un projet.",
                  "Capacité : Participer à l'élaboration d'd'un budget et/ou au suivi des coûts.",
                  "Capacité : Contacter des clients ou des fournisseurs pour établir des devis ou répondre à des offres.",
                  "Connaissance : Enjeux économiques  -- Travailler, apprendre, évoluer de manière autonome (niveau 2)",
                  "Capacité : Respecter les objectifs et le planning prévisionnel fixé par le projet.",
                  "Capacité : Formaliser avec le Maitre d'Apprentissage les objectifs du projet avec des indicateurs de résultats et un planning prévisionnel pour son travail personnel",
                  "Capacité : Etre force de proposition de solution technique",
                  "Connaissance : Gestion du temps",
                  "Connaissance : Démarche projet  -- Interagir avec les autres, travailler en équipe (niveau )",
                  "Capacité : Etre capable de présenter un projet dans sa globalité à l'écrit ou devant un public",
                  "Capacité : Savoir chercher l'information auprès des bonnes personnes.",
                  "Connaissance : communication, esprit de synthèse"
                ],
                "GEA-C9": [
                  "Capacité : Etre associé à plusieurs étapes du cycle en V",
                  "Capacité : mettre en œuvre des sous ensembles multi domaines de l'EEAIIT et/ou multiphysique.",
                  "Capacité : Outils de modélisations et simulation multidomaines",
                  "Capacité : Ecriture de spécifications fonctionnelles et techniques",
                  "Connaissance : Mise en œuvre de composants ou sous ensemble fonctionnels, Prototypage",
                  "Connaissance : utilisation CAO / DAO, simulation performance."
                ]
              },
              "listeComp": [
                {
                  "code": "B6",
                  "val": "Se situer, travailler, évoluer dans une entreprise, une organisation socio-productive",
                  "valAnglais": "Position oneself, work, and evolve within a company or a socio-productive organization",
                  "bs": "28",
                  "niveau": "2"
                },
                {
                  "code": "C9",
                  "val": "Mettre en œuvre ses compétences scientifiques et technologiques dans le domaine de l'EEAIIT dans un cadre industriel et appliqué à des problématiques réelles en conduisant les étapes du cycle de conception",
                  "valAnglais": "Apply scientific and technological competences in the field of the EEAIIT in an industrial framework and to real problems by leading the stages of the cycle of conception",
                  "niveau": ""
                }
              ]
            }
          }
        ]
      },
      {
        "url": "/fr/formation/parcours/1165/4/2",
        "ecs": [
          {
            "UE": "Enseignements Transversaux (GEA-4-UE45)",
            "url": "http://planete.insa-lyon.fr/scolpeda/f/ects?id=37644&_lang=fr",
            "detail": {
              "code": "GEA-4-MA3",
              "ects": "2.0",
              "cours": "25.0 h",
              "td": "25.0 h",
              "tp": "0.0 h",
              "projet": "0.0 h",
              "perso": "40.0 h",
              "nom": "Mathématiques : Probabilités et Statistiques",
              "competencesBrutes": "COMPETENCES : Modélisation et résolution de situations non déterministes Connaissance et compréhension des outils statistiques de base",
              "capacite": [],
              "connaissance": [],
              "competenceToCapaciteEtConnaissance": {}
            }
          },
          {
            "UE": "Enseignements Transversaux (GEA-4-UE45)",
            "url": "http://planete.insa-lyon.fr/scolpeda/f/ects?id=39190&_lang=fr",
            "detail": {
              "code": "GEA-4-IF4",
              "ects": "1.0",
              "cours": "8.0 h",
              "td": "8.0 h",
              "tp": "0.0 h",
              "projet": "0.0 h",
              "perso": "15.0 h",
              "nom": "Informatique Industrielle : Informatique Industrielle - Multi-tâche et temps réel",
              "competencesBrutes": "Cet EC relève de l'unité d'enseignement  (UE45) et contribue aux compétences suivantes :  - Concevoir et développer des logiciels haut et bas niveau pour des systèmes (traitement et gestion de l'information) (niveau 2)  --- Capacité : Etre capable de mettre en œuvre des principes et stratégies d'ordonnancement --- Capacité : Etre capable de mettre en œuvre des principes et stratégies de gestion des utilisateurs --- Capacité : Etre capable de mettre en œuvre des principes et stratégies de gestion des tâches  --- Connaissance : Base des systèmes multi-tâches (POSIX) et multi utilisateurs (UNIX) --- Connaissance : Echange de données entre tâches (PIPE),Gestion des signaux, Gestion des ressources (verrous et sémaphores) --- Connaissance : Principes d'ordonnancement  - Mettre en œuvre des principes et stratégies d'ordonnancements des tâches et de gestion (niveau 3)  --- Capacité : Etre capable de réaliser un ordonnancement de tâches --- Capacité : Etre capable de mettre en œuvre des logiciels temps réel  --- Connaissance : Bases et stratégies des systèmes temps-réel --- Connaissance : Ordonnancement statique et dynamique --- Connaissance : Stratégies des serveurs de tâches apériodiques  De plus, elle nécessite de mobiliser les compétences suivantes :  -- Analyser un système (ou un problème) réel ou virtuel -- Exploiter un modèle d'un système réel ou virtuel -- Mettre en œuvre une démarche expérimentale -- Traiter des données -- Communiquer une analyse ou une démarche scientifique -- Se situer, travailler, évoluer dans une entreprise, une organisation socio-productive",
              "capacite": [
                "Capacité : Etre capable de mettre en œuvre des principes et stratégies d'ordonnancement",
                "Capacité : Etre capable de mettre en œuvre des principes et stratégies de gestion des utilisateurs",
                "Capacité : Etre capable de mettre en œuvre des principes et stratégies de gestion des tâches",
                "Capacité : Etre capable de réaliser un ordonnancement de tâches",
                "Capacité : Etre capable de mettre en œuvre des logiciels temps réel"
              ],
              "connaissance": [
                "Connaissance : Base des systèmes multi-tâches (POSIX) et multi utilisateurs (UNIX)",
                "Connaissance : Echange de données entre tâches (PIPE),Gestion des signaux, Gestion des ressources (verrous et sémaphores)",
                "Connaissance : Principes d'ordonnancement",
                "Connaissance : Bases et stratégies des systèmes temps-réel",
                "Connaissance : Ordonnancement statique et dynamique",
                "Connaissance : Stratégies des serveurs de tâches apériodiques"
              ],
              "competenceToCapaciteEtConnaissance": {
                "GEA-C7": [
                  "Capacité : Etre capable de mettre en œuvre des principes et stratégies d'ordonnancement",
                  "Capacité : Etre capable de mettre en œuvre des principes et stratégies de gestion des utilisateurs",
                  "Capacité : Etre capable de mettre en œuvre des principes et stratégies de gestion des tâches",
                  "Connaissance : Base des systèmes multi-tâches (POSIX) et multi utilisateurs (UNIX)",
                  "Connaissance : Echange de données entre tâches (PIPE),Gestion des signaux, Gestion des ressources (verrous et sémaphores)",
                  "Connaissance : Principes d'ordonnancement"
                ],
                "GEA-C8": [
                  "Capacité : Etre capable de réaliser un ordonnancement de tâches",
                  "Capacité : Etre capable de mettre en œuvre des logiciels temps réel",
                  "Connaissance : Bases et stratégies des systèmes temps-réel",
                  "Connaissance : Ordonnancement statique et dynamique",
                  "Connaissance : Stratégies des serveurs de tâches apériodiques"
                ]
              },
              "listeComp": [
                {
                  "code": "C7",
                  "val": "Concevoir et développer des logiciels haut et bas niveau pour des systèmes (traitement et gestion de l'information)",
                  "valAnglais": "Design and develop high and low level software for systems (information processing and management)",
                  "niveau": "2"
                },
                {
                  "code": "C8",
                  "val": "Mettre en œuvre des principes et stratégies d'ordonnancements des tâches et de gestion",
                  "valAnglais": "Implement principles and strategies for scheduling tasks and managing",
                  "niveau": "3"
                }
              ],
              "listeCompMobilise": [
                "Analyser un système (ou un problème) réel ou virtuel",
                "Exploiter un modèle d'un système réel ou virtuel",
                "Mettre en œuvre une démarche expérimentale",
                "Traiter des données",
                "Communiquer une analyse ou une démarche scientifique",
                "Se situer, travailler, évoluer dans une entreprise, une organisation socio-productive"
              ]
            }
          },
          {
            "UE": "Enseignements Transversaux (GEA-4-UE45)",
            "url": "http://planete.insa-lyon.fr/scolpeda/f/ects?id=39264&_lang=fr",
            "detail": {
              "code": "GEA-4-TC22",
              "ects": "2.0",
              "cours": "20.5 h",
              "td": "20.5 h",
              "tp": "16.0 h",
              "projet": "0.0 h",
              "perso": "20.0 h",
              "nom": "Télécommunications : Télécommunications niveau 2",
              "competencesBrutes": "Cet EC relève de l'unité d'enseignement  (UE45) et contribue aux compétences suivantes :  - Mettre en œuvre des composants électroniques analogiques et/ou numériques et identifier leur fonction au sein d'un montage (niveau 3)  -- Sous compétence : Mettre en œuvre des antennes filaires et patch  --- Capacité : Décrire le fonctionnement physique d'une antenne (domaine RF) --- Capacité : calculer le diagramme de rayonnement d'une antenne --- Capacité : Simuler et analyser le fonctionnement électromagnétique et électrique d'une antenne patch --- Capacité : Ecrire et analyser un bilan de liaison hertzienne  --- Connaissance : Types d'antennes, caractéristiques physiques et électriques --- Connaissance : Identifier la structure d'un bilan de liaison hertzienne --- Connaissance : Fonctionnement physique d'une antenne filaire  -- Sous compétence : Mettre en œuvre des circuits radiofréquences  --- Capacité : Caractériser et simuler un amplificateur radiofréquence faible bruit (LNA) --- Capacité : Caractériser et simuler un oscillateur radiofréquence (VCO) --- Capacité : Caractériser et simuler un amplificateur de puissance radiofréquence (PA) à partir d'un cahier des charges --- Capacité : Caractériser et simuler un mélangeur radiofréquence (MIXER) à partir d'un cahier des charges --- Capacité : Etudier et modéliser des circuits radiofréquences non linéaires via le simulateur ADS d'Agilent Technologies  --- Connaissance : Dispostifs d'adaptation en puissance RF (types, caractéristiques, techniques d'optimisation) --- Connaissance : Simulations DC, S parameters, Harmonic Balance, LF et Phase Noise --- Connaissance : Caractéristiques électriques des circuits actifs  (DC, petit-signal, bruit, fort- signal)  - Concevoir et réaliser des systèmes électroniques pour l'acquisition, le traitement, la commande et la communication de données (niveau 3)  --- Capacité : Concevoir un amplificateur radiofréquence faible bruit (LNA) à partir d'un cahier des charges --- Capacité : Concevoir un oscillateur radiofréquence (VCO) à partir d'un cahier des charges --- Capacité : Concevoir un amplificateur de puissance radiofréquence (PA) à partir d'un cahier des charges --- Capacité : Concevoir un mélangeur radiofréquence (MIXER) à partir d'un cahier des charges --- Capacité : Concevoir une antenne (filaire, patch) à partir d'un cahier des charges  --- Connaissance : Couverture et planification radio --- Connaissance : Sensibilité, dynamique et sélectivité d'un système d'émission-réception RF --- Connaissance : Architecture des circuits radiofréquences d'émission et de réception  - Mettre en œuvre des principes et stratégies d'ordonnancements des tâches et de gestion (niveau 2)  --- Capacité : Organiser et partitioner un travail de recherche et de conception CAO entre 6 et 10 personnes --- Capacité : Planifier les différentes taches de conception CAO à partir de cahier de charge --- Capacité : Respecter les délais et les objectifs du maitre d'ouvrage   --- Connaissance : Apprentissage par projets - Etude de cas --- Connaissance : Gestion de projet de recherche documentaire et de création d'entreprise --- Connaissance : Lecture et analyse d'un cahier des charges  -- Analyser un système (ou un problème) réel ou virtuel (niveau 2)  -- Concevoir un système répondant à un cahier des charges (niveau 3)  De plus, elle nécessite de mobiliser les compétences suivantes :  -- Exploiter un modèle d'un système réel ou virtuel -- Traiter des données -- Communiquer une analyse ou une démarche scientifique -- Travailler, apprendre, évoluer de manière autonome -- Interagir avec les autres, travailler en équipe",
              "capacite": [
                "Capacité : Décrire le fonctionnement physique d'une antenne (domaine RF)",
                "Capacité : calculer le diagramme de rayonnement d'une antenne",
                "Capacité : Simuler et analyser le fonctionnement électromagnétique et électrique d'une antenne patch",
                "Capacité : Ecrire et analyser un bilan de liaison hertzienne",
                "Capacité : Caractériser et simuler un amplificateur radiofréquence faible bruit (LNA)",
                "Capacité : Caractériser et simuler un oscillateur radiofréquence (VCO)",
                "Capacité : Caractériser et simuler un amplificateur de puissance radiofréquence (PA) à partir d'un cahier des charges",
                "Capacité : Caractériser et simuler un mélangeur radiofréquence (MIXER) à partir d'un cahier des charges",
                "Capacité : Etudier et modéliser des circuits radiofréquences non linéaires via le simulateur ADS d'Agilent Technologies",
                "Capacité : Concevoir un amplificateur radiofréquence faible bruit (LNA) à partir d'un cahier des charges",
                "Capacité : Concevoir un oscillateur radiofréquence (VCO) à partir d'un cahier des charges",
                "Capacité : Concevoir un amplificateur de puissance radiofréquence (PA) à partir d'un cahier des charges",
                "Capacité : Concevoir un mélangeur radiofréquence (MIXER) à partir d'un cahier des charges",
                "Capacité : Concevoir une antenne (filaire, patch) à partir d'un cahier des charges",
                "Capacité : Organiser et partitioner un travail de recherche et de conception CAO entre 6 et 10 personnes",
                "Capacité : Planifier les différentes taches de conception CAO à partir de cahier de charge",
                "Capacité : Respecter les délais et les objectifs du maitre d'ouvrage"
              ],
              "connaissance": [
                "Connaissance : Types d'antennes, caractéristiques physiques et électriques",
                "Connaissance : Identifier la structure d'un bilan de liaison hertzienne",
                "Connaissance : Fonctionnement physique d'une antenne filaire",
                "Connaissance : Dispostifs d'adaptation en puissance RF (types, caractéristiques, techniques d'optimisation)",
                "Connaissance : Simulations DC, S parameters, Harmonic Balance, LF et Phase Noise",
                "Connaissance : Caractéristiques électriques des circuits actifs  (DC, petit-signal, bruit, fort- signal)",
                "Connaissance : Couverture et planification radio",
                "Connaissance : Sensibilité, dynamique et sélectivité d'un système d'émission-réception RF",
                "Connaissance : Architecture des circuits radiofréquences d'émission et de réception",
                "Connaissance : Apprentissage par projets"
              ],
              "competenceToCapaciteEtConnaissance": {
                "GEA-C1": [
                  "Capacité : Décrire le fonctionnement physique d'une antenne (domaine RF)",
                  "Capacité : calculer le diagramme de rayonnement d'une antenne",
                  "Capacité : Simuler et analyser le fonctionnement électromagnétique et électrique d'une antenne patch",
                  "Capacité : Ecrire et analyser un bilan de liaison hertzienne",
                  "Connaissance : Types d'antennes, caractéristiques physiques et électriques",
                  "Connaissance : Identifier la structure d'un bilan de liaison hertzienne",
                  "Connaissance : Fonctionnement physique d'une antenne filaire",
                  "Capacité : Caractériser et simuler un amplificateur radiofréquence faible bruit (LNA)",
                  "Capacité : Caractériser et simuler un oscillateur radiofréquence (VCO)",
                  "Capacité : Caractériser et simuler un amplificateur de puissance radiofréquence (PA) à partir d'un cahier des charges",
                  "Capacité : Caractériser et simuler un mélangeur radiofréquence (MIXER) à partir d'un cahier des charges",
                  "Capacité : Etudier et modéliser des circuits radiofréquences non linéaires via le simulateur ADS d'Agilent Technologies",
                  "Connaissance : Dispostifs d'adaptation en puissance RF (types, caractéristiques, techniques d'optimisation)",
                  "Connaissance : Simulations DC, S parameters, Harmonic Balance, LF et Phase Noise",
                  "Connaissance : Caractéristiques électriques des circuits actifs  (DC, petit-signal, bruit, fort- signal)"
                ],
                "GEA-C5": [
                  "Capacité : Concevoir un amplificateur radiofréquence faible bruit (LNA) à partir d'un cahier des charges",
                  "Capacité : Concevoir un oscillateur radiofréquence (VCO) à partir d'un cahier des charges",
                  "Capacité : Concevoir un amplificateur de puissance radiofréquence (PA) à partir d'un cahier des charges",
                  "Capacité : Concevoir un mélangeur radiofréquence (MIXER) à partir d'un cahier des charges",
                  "Capacité : Concevoir une antenne (filaire, patch) à partir d'un cahier des charges",
                  "Connaissance : Couverture et planification radio",
                  "Connaissance : Sensibilité, dynamique et sélectivité d'un système d'émission-réception RF",
                  "Connaissance : Architecture des circuits radiofréquences d'émission et de réception"
                ],
                "GEA-C8": [
                  "Capacité : Organiser et partitioner un travail de recherche et de conception CAO entre 6 et 10 personnes",
                  "Capacité : Planifier les différentes taches de conception CAO à partir de cahier de charge",
                  "Capacité : Respecter les délais et les objectifs du maitre d'ouvrage",
                  "Connaissance : Apprentissage par projets"
                ]
              },
              "listeCompMobilise": [
                "Exploiter un modèle d'un système réel ou virtuel",
                "Traiter des données",
                "Communiquer une analyse ou une démarche scientifique",
                "Travailler, apprendre, évoluer de manière autonome",
                "Interagir avec les autres, travailler en équipe"
              ]
            }
          },
          {
            "UE": "Enseignements Techniques (GEA-4-UE46)",
            "url": "http://planete.insa-lyon.fr/scolpeda/f/ects?id=37643&_lang=fr",
            "detail": {
              "code": "GEA-4-AU3",
              "ects": "2.0",
              "cours": "13.0 h",
              "td": "17.0 h",
              "tp": "12.0 h",
              "projet": "0.0 h",
              "perso": "18.0 h",
              "nom": "Automatique : Automatique SED (Systèmes à événements discrets)",
              "competencesBrutes": "Cet EC relève de l'unité d'enseignement  (UE46) et contribue aux compétences suivantes :  - Spécifier, modéliser et concevoir les méthodes et algorithmes pour le traitement et la gestion de l'information véhiculée par les signaux et les images (niveau 3)  -- Sous compétence : Spécifier, modéliser et concevoir les méthodes et algorithmes pour le traitement et la gestion de des flux de production  --- Capacité : Appréhender la lecture et l'écriture d'un cahier des charges --- Capacité : Modéliser un système de production en vue de son analyse de performances et /ou son dimensionnement --- Capacité : Analyser les propriétés du modèle liées au marquage initial : vivacité, bornage et réinitialisation --- Capacité : Analyser les performances d'un système et le dimensionner --- Capacité : Transférer ses connaissances à d'autres types de systèmes qui ne concernent pas la production  --- Connaissance : Connaître l'outil Réseau de Petri --- Connaissance : Méthodologie pour modéliser un système de Production via les réseaux de Petri --- Connaissance : Méthodologie pour analyser les perfromances et/ou le dimensionnement d'un système de production  - Mettre en œuvre les étapes permettant le contrôle du fonctionnement d'un système discret ou continu (niveau 3)  -- Sous compétence : Développer la communication dans un système automatisé  --- Capacité : Implémenter la commande d'équipements industriels communicant en Modbus/ TCP --- Capacité : Conception d'Interface Homme Machine accessible via le Web  -- Sous compétence : Développer la commande d'un système discret  --- Capacité : Modéliser la facette commande d'un système du point de vue fonctionnel --- Capacité : Encapsuler le savoir-faire dans un composant logiciel --- Capacité : Capitaliser les savoir-faire et les rendre réutilisables --- Capacité : Mise en œuvre dans un atelier logiciel industriel de programmation d'API  --- Connaissance : Initiation aux réseaux de terrain industriels --- Connaissance : Sensibilisation à la cyber-sécurité --- Connaissance : Appréhender les concepts de l'ingénierie système --- Connaissance : Appréhender le cycle de vie d'un système --- Connaissance : Modélisation SysML  - Concevoir et développer des logiciels haut et bas niveau pour des systèmes (traitement et gestion de l'information) (niveau 2)  --- Capacité : Simuler un système de production et le modéliser par un réseau de Petri --- Capacité : Analyser, via un logiciel de simulation, les propriétés structurelles d'un système de production complexe --- Capacité : Analyser, via un logiciel de simulation, les propriétés liées au marquage initial d'un système de production complexe  --- Connaissance : Mise en œuvre du savoir-faire en Réseau de Petri sur un logiciel de simulation --- Connaissance : Analyser les résultats issus de la simulation et les critiquer   - Mettre en œuvre des principes et stratégies d'ordonnancements des tâches et de gestion (niveau 2)  --- Capacité : Spécifier des contraintes d'ordonnancement dans un cahier des charges --- Capacité : Modéliser des contraintes d'ordonnancement via les réseaux de Petri --- Capacité : Calculer les invariants issus de l'ordonnancement --- Capacité : Comprendre l'influence de l'ordonnancement sur les propriétés structurelles d'un réseau de Petri  --- Connaissance : Notion de base d'ordonnancement dans un système de production --- Connaissance : Connaître l'influence de l'ordonnancement sur les propriétés du système de production  De plus, elle nécessite de mobiliser les compétences suivantes :  -- Analyser un système (ou un problème) réel ou virtuel -- Exploiter un modèle d'un système réel ou virtuel -- Mettre en œuvre une démarche expérimentale -- Concevoir un système répondant à un cahier des charges -- Traiter des données -- Communiquer une analyse ou une démarche scientifique -- Agir de manière responsable dans un monde complexe -- Se situer, travailler, évoluer dans une entreprise, une organisation socio-productive",
              "capacite": [
                "Capacité : Appréhender la lecture et l'écriture d'un cahier des charges",
                "Capacité : Modéliser un système de production en vue de son analyse de performances et /ou son dimensionnement",
                "Capacité : Analyser les propriétés du modèle liées au marquage initial : vivacité, bornage et réinitialisation",
                "Capacité : Analyser les performances d'un système et le dimensionner",
                "Capacité : Transférer ses connaissances à d'autres types de systèmes qui ne concernent pas la production",
                "Capacité : Implémenter la commande d'équipements industriels communicant en Modbus/ TCP",
                "Capacité : Conception d'Interface Homme Machine accessible via le Web",
                "Capacité : Modéliser la facette commande d'un système du point de vue fonctionnel",
                "Capacité : Encapsuler le savoir-faire dans un composant logiciel",
                "Capacité : Capitaliser les savoir-faire et les rendre réutilisables",
                "Capacité : Mise en œuvre dans un atelier logiciel industriel de programmation d'API",
                "Capacité : Simuler un système de production et le modéliser par un réseau de Petri",
                "Capacité : Analyser, via un logiciel de simulation, les propriétés structurelles d'un système de production complexe",
                "Capacité : Analyser, via un logiciel de simulation, les propriétés liées au marquage initial d'un système de production complexe",
                "Capacité : Spécifier des contraintes d'ordonnancement dans un cahier des charges",
                "Capacité : Modéliser des contraintes d'ordonnancement via les réseaux de Petri",
                "Capacité : Calculer les invariants issus de l'ordonnancement",
                "Capacité : Comprendre l'influence de l'ordonnancement sur les propriétés structurelles d'un réseau de Petri"
              ],
              "connaissance": [
                "Connaissance : Connaître l'outil Réseau de Petri",
                "Connaissance : Méthodologie pour modéliser un système de Production via les réseaux de Petri",
                "Connaissance : Méthodologie pour analyser les perfromances et/ou le dimensionnement d'un système de production",
                "Connaissance : Initiation aux réseaux de terrain industriels",
                "Connaissance : Sensibilisation à la cyber-sécurité",
                "Connaissance : Appréhender les concepts de l'ingénierie système",
                "Connaissance : Appréhender le cycle de vie d'un système",
                "Connaissance : Modélisation SysML",
                "Connaissance : Mise en œuvre du savoir-faire en Réseau de Petri sur un logiciel de simulation",
                "Connaissance : Analyser les résultats issus de la simulation et les critiquer",
                "Connaissance : Notion de base d'ordonnancement dans un système de production",
                "Connaissance : Connaître l'influence de l'ordonnancement sur les propriétés du système de production"
              ],
              "competenceToCapaciteEtConnaissance": {
                "GEA-C4": [
                  "Capacité : Appréhender la lecture et l'écriture d'un cahier des charges",
                  "Capacité : Modéliser un système de production en vue de son analyse de performances et /ou son dimensionnement",
                  "Capacité : Analyser les propriétés du modèle liées au marquage initial : vivacité, bornage et réinitialisation",
                  "Capacité : Analyser les performances d'un système et le dimensionner",
                  "Capacité : Transférer ses connaissances à d'autres types de systèmes qui ne concernent pas la production",
                  "Connaissance : Connaître l'outil Réseau de Petri",
                  "Connaissance : Méthodologie pour modéliser un système de Production via les réseaux de Petri",
                  "Connaissance : Méthodologie pour analyser les perfromances et/ou le dimensionnement d'un système de production"
                ],
                "GEA-C6": [
                  "Capacité : Implémenter la commande d'équipements industriels communicant en Modbus/ TCP",
                  "Capacité : Conception d'Interface Homme Machine accessible via le Web",
                  "Capacité : Modéliser la facette commande d'un système du point de vue fonctionnel",
                  "Capacité : Encapsuler le savoir-faire dans un composant logiciel",
                  "Capacité : Capitaliser les savoir-faire et les rendre réutilisables",
                  "Capacité : Mise en œuvre dans un atelier logiciel industriel de programmation d'API",
                  "Connaissance : Initiation aux réseaux de terrain industriels",
                  "Connaissance : Sensibilisation à la cyber-sécurité",
                  "Connaissance : Appréhender les concepts de l'ingénierie système",
                  "Connaissance : Appréhender le cycle de vie d'un système",
                  "Connaissance : Modélisation SysML"
                ],
                "GEA-C7": [
                  "Capacité : Simuler un système de production et le modéliser par un réseau de Petri",
                  "Capacité : Analyser, via un logiciel de simulation, les propriétés structurelles d'un système de production complexe",
                  "Capacité : Analyser, via un logiciel de simulation, les propriétés liées au marquage initial d'un système de production complexe",
                  "Connaissance : Mise en œuvre du savoir-faire en Réseau de Petri sur un logiciel de simulation",
                  "Connaissance : Analyser les résultats issus de la simulation et les critiquer"
                ],
                "GEA-C8": [
                  "Capacité : Spécifier des contraintes d'ordonnancement dans un cahier des charges",
                  "Capacité : Modéliser des contraintes d'ordonnancement via les réseaux de Petri",
                  "Capacité : Calculer les invariants issus de l'ordonnancement",
                  "Capacité : Comprendre l'influence de l'ordonnancement sur les propriétés structurelles d'un réseau de Petri",
                  "Connaissance : Notion de base d'ordonnancement dans un système de production",
                  "Connaissance : Connaître l'influence de l'ordonnancement sur les propriétés du système de production"
                ]
              },
              "listeComp": [
                {
                  "code": "C4",
                  "val": "Spécifier, modéliser et concevoir les méthodes et algorithmes pour le traitement et la gestion de l'information véhiculée par les signaux et les images",
                  "valAnglais": "Specify, model and design methods and algorithms for the processing and management of information conveyed by signals and images",
                  "niveau": "3"
                },
                {
                  "code": "C6",
                  "val": "Mettre en œuvre les étapes permettant le contrôle du fonctionnement d'un système discret ou continu",
                  "valAnglais": "Implement steps to control the operation of a discrete or continuous system",
                  "niveau": "3"
                },
                {
                  "code": "C7",
                  "val": "Concevoir et développer des logiciels haut et bas niveau pour des systèmes (traitement et gestion de l'information)",
                  "valAnglais": "Design and develop high and low level software for systems (information processing and management)",
                  "niveau": "2"
                },
                {
                  "code": "C8",
                  "val": "Mettre en œuvre des principes et stratégies d'ordonnancements des tâches et de gestion",
                  "valAnglais": "Implement principles and strategies for scheduling tasks and managing",
                  "niveau": "2"
                }
              ],
              "listeCompMobilise": [
                "Analyser un système (ou un problème) réel ou virtuel",
                "Exploiter un modèle d'un système réel ou virtuel",
                "Mettre en œuvre une démarche expérimentale",
                "Concevoir un système répondant à un cahier des charges",
                "Traiter des données",
                "Communiquer une analyse ou une démarche scientifique",
                "Agir de manière responsable dans un monde complexe",
                "Se situer, travailler, évoluer dans une entreprise, une organisation socio-productive"
              ]
            }
          },
          {
            "UE": "Enseignements Techniques (GEA-4-UE46)",
            "url": "http://planete.insa-lyon.fr/scolpeda/f/ects?id=39191&_lang=fr",
            "detail": {
              "code": "GEA-4-AU4",
              "ects": "2.0",
              "cours": "15.0 h",
              "td": "15.0 h",
              "tp": "12.0 h",
              "projet": "0.0 h",
              "perso": "18.0 h",
              "nom": "Automatique : Automatique Avancé",
              "competencesBrutes": "Cet EC relève de l'unité d'enseignement  (UE46) et contribue aux compétences suivantes :  - Mettre en œuvre les différents éléments de production d'énergie, de transport d'énergie électrique et de conversion d'énergie (niveau 2)  --- Capacité : Extraire une vue d'ensemble schématique du transfert d'énergie dans un système pluridisciplinaire --- Capacité : Avoir une vue système des interconnexions entre éléments de stockage, de conversion et de transformation de l'énérgie --- Capacité : Transférer une partie de ces connaissances sur les systèmes électriques à des systèmes hydrauliques, pneumatiques, mécaniques  --- Connaissance : Appréhender le principe de la causalité dans l'étude des systèmes avec une approche énergétique (Bond-Graph) --- Connaissance : Connaissance sur les composants d'un système pluridisciplinaire --- Connaissance : Connaissance transversale : Electricité et Fluid Power et Mécatronique  - Spécifier, modéliser et concevoir les méthodes et algorithmes pour le traitement et la gestion de l'information véhiculée par les signaux et les images (niveau 3)  --- Capacité : Modéliser d'un système pluridisciplinaire --- Capacité : Obtenir un modèle linéaire autour d'un point de fonctionnment --- Capacité : Analyser le modèle linéaire en terme de stabilité, commandabilité et observabilité  --- Connaissance : Connaître la modélisation système --- Connaissance : Connaître les notions de stabilité, commandabilité et observabilité  - Mettre en œuvre les étapes permettant le contrôle du fonctionnement d'un système discret ou continu (niveau 3)  -- Sous compétence : Mettre en oeuvre expérimentalement le contrôle d'un système continu  --- Capacité : Mettre en œuvre des stratégies de commande sur des cartes de prototypage rapide de lois de commande --- Capacité : Mettre en œuvre des capteurs logiciels (observateurs) sur des cartes de prototypage rapide de lois de commande --- Capacité : Identifier des systèmes physiques à partir de mesures expérimentales  -- Sous compétence : Mettre en oeuvre les étapes permettant le contrôle du fonctionnement d'un système continu  --- Capacité : Calculer les pôles d'un système continu et effectuer du placement de pôles --- Capacité : Synthèser une commande par retour d'état  -- Sous compétence : Mettre en oeuvre les étapes permettant la conception d'un système pluridisciplinaire  --- Connaissance : Savoir utiliser des cartes de protypage rapide de lois de commande --- Connaissance : Avoir des notions sur différents algorithmes d'identification et leur mise en œuvre --- Connaissance : Limites des régulateurs PID --- Connaissance : Connaître l'approche par variables d'état et savoir la comparer à une approche entrée/sortie --- Connaissance : Connaître la commande par retour d'état  De plus, elle nécessite de mobiliser les compétences suivantes :   -- Analyser un système (ou un problème) réel ou virtuel -- Exploiter un modèle d'un système réel ou virtuel -- Mettre en œuvre une démarche expérimentale -- Concevoir un système répondant à un cahier des charges -- Traiter des données -- Communiquer une analyse ou une démarche scientifique -- Se situer, travailler, évoluer dans une entreprise, une organisation socio-productive",
              "capacite": [
                "Capacité : Extraire une vue d'ensemble schématique du transfert d'énergie dans un système pluridisciplinaire",
                "Capacité : Avoir une vue système des interconnexions entre éléments de stockage, de conversion et de transformation de l'énérgie",
                "Capacité : Transférer une partie de ces connaissances sur les systèmes électriques à des systèmes hydrauliques, pneumatiques, mécaniques",
                "Capacité : Modéliser d'un système pluridisciplinaire",
                "Capacité : Obtenir un modèle linéaire autour d'un point de fonctionnment",
                "Capacité : Analyser le modèle linéaire en terme de stabilité, commandabilité et observabilité",
                "Capacité : Mettre en œuvre des stratégies de commande sur des cartes de prototypage rapide de lois de commande",
                "Capacité : Mettre en œuvre des capteurs logiciels (observateurs) sur des cartes de prototypage rapide de lois de commande",
                "Capacité : Identifier des systèmes physiques à partir de mesures expérimentales",
                "Capacité : Calculer les pôles d'un système continu et effectuer du placement de pôles",
                "Capacité : Synthèser une commande par retour d'état"
              ],
              "connaissance": [
                "Connaissance : Appréhender le principe de la causalité dans l'étude des systèmes avec une approche énergétique (Bond-Graph)",
                "Connaissance : Connaissance sur les composants d'un système pluridisciplinaire",
                "Connaissance : Connaissance transversale : Electricité et Fluid Power et Mécatronique",
                "Connaissance : Connaître la modélisation système",
                "Connaissance : Connaître les notions de stabilité, commandabilité et observabilité",
                "Connaissance : Savoir utiliser des cartes de protypage rapide de lois de commande",
                "Connaissance : Avoir des notions sur différents algorithmes d'identification et leur mise en œuvre",
                "Connaissance : Limites des régulateurs PID",
                "Connaissance : Connaître l'approche par variables d'état et savoir la comparer à une approche entrée/sortie",
                "Connaissance : Connaître la commande par retour d'état"
              ],
              "competenceToCapaciteEtConnaissance": {
                "GEA-C3": [
                  "Capacité : Extraire une vue d'ensemble schématique du transfert d'énergie dans un système pluridisciplinaire",
                  "Capacité : Avoir une vue système des interconnexions entre éléments de stockage, de conversion et de transformation de l'énérgie",
                  "Capacité : Transférer une partie de ces connaissances sur les systèmes électriques à des systèmes hydrauliques, pneumatiques, mécaniques",
                  "Connaissance : Appréhender le principe de la causalité dans l'étude des systèmes avec une approche énergétique (Bond-Graph)",
                  "Connaissance : Connaissance sur les composants d'un système pluridisciplinaire",
                  "Connaissance : Connaissance transversale : Electricité et Fluid Power et Mécatronique"
                ],
                "GEA-C4": [
                  "Capacité : Modéliser d'un système pluridisciplinaire",
                  "Capacité : Obtenir un modèle linéaire autour d'un point de fonctionnment",
                  "Capacité : Analyser le modèle linéaire en terme de stabilité, commandabilité et observabilité",
                  "Connaissance : Connaître la modélisation système",
                  "Connaissance : Connaître les notions de stabilité, commandabilité et observabilité"
                ],
                "GEA-C6": [
                  "Capacité : Mettre en œuvre des stratégies de commande sur des cartes de prototypage rapide de lois de commande",
                  "Capacité : Mettre en œuvre des capteurs logiciels (observateurs) sur des cartes de prototypage rapide de lois de commande",
                  "Capacité : Identifier des systèmes physiques à partir de mesures expérimentales",
                  "Capacité : Calculer les pôles d'un système continu et effectuer du placement de pôles",
                  "Capacité : Synthèser une commande par retour d'état",
                  "Connaissance : Savoir utiliser des cartes de protypage rapide de lois de commande",
                  "Connaissance : Avoir des notions sur différents algorithmes d'identification et leur mise en œuvre",
                  "Connaissance : Limites des régulateurs PID",
                  "Connaissance : Connaître l'approche par variables d'état et savoir la comparer à une approche entrée/sortie",
                  "Connaissance : Connaître la commande par retour d'état"
                ]
              },
              "listeComp": [
                {
                  "code": "C3",
                  "val": "Mettre en œuvre les différents éléments de production d'énergie, de transport d'énergie électrique et de conversion d'énergie",
                  "valAnglais": "Implement the various elements of energy production, transport of electrical energy and energy conversion",
                  "niveau": "2"
                },
                {
                  "code": "C4",
                  "val": "Spécifier, modéliser et concevoir les méthodes et algorithmes pour le traitement et la gestion de l'information véhiculée par les signaux et les images",
                  "valAnglais": "Specify, model and design methods and algorithms for the processing and management of information conveyed by signals and images",
                  "niveau": "3"
                },
                {
                  "code": "C6",
                  "val": "Mettre en œuvre les étapes permettant le contrôle du fonctionnement d'un système discret ou continu",
                  "valAnglais": "Implement steps to control the operation of a discrete or continuous system",
                  "niveau": "3"
                }
              ],
              "listeCompMobilise": [
                "Analyser un système (ou un problème) réel ou virtuel",
                "Exploiter un modèle d'un système réel ou virtuel",
                "Mettre en œuvre une démarche expérimentale",
                "Concevoir un système répondant à un cahier des charges",
                "Traiter des données",
                "Communiquer une analyse ou une démarche scientifique",
                "Se situer, travailler, évoluer dans une entreprise, une organisation socio-productive"
              ]
            }
          },
          {
            "UE": "Enseignements Techniques (GEA-4-UE46)",
            "url": "http://planete.insa-lyon.fr/scolpeda/f/ects?id=37642&_lang=fr",
            "detail": {
              "code": "GEA-4-ETEP3",
              "ects": "3.0",
              "cours": "15.5 h",
              "td": "15.5 h",
              "tp": "24.0 h",
              "projet": "0.0 h",
              "perso": "28.0 h",
              "nom": "Electrotechnique et Electronique de Puissance : Electrotechnique et Electronique de puissance - 3eme niveau",
              "competencesBrutes": "Cet EC relève de l'unité d'enseignement  (UE46) et contribue aux compétences suivantes :  - Mettre en œuvre des composants électroniques analogiques et/ou numériques et identifier leur fonction au sein d'un montage (niveau 3)  -- Sous compétence : Mettre en oeuvre des composants électroniques de puissance et identifier leur fonction au sein d'un montage  --- Capacité : Savoir calculer des caractéristiques liées à des performances sur les convertisseurs classiques et les associer à des valeurs de composants --- Capacité : Etre capable d'analyser pour comprendre le fonctionnement d'un convertisseur  --- Connaissance : Connaître les particularités de l'utilisation des composants passifs pour la conversion statique d'énergie électrique --- Connaissance : Connaître les notions de base sur les composants semi-conducteurs de puissance en commutation --- Connaissance : Connaître les règles d'association des sources  - Mettre en œuvre les propriétés physiques des matériaux pour le domaine du génie électrique (niveau 2)  -- Sous compétence : Mettre en oeuvre les propriétés magnétiques et semi-conductrices pour la conversion statique d'énergie  --- Capacité : Etre capable d'analyser le fonctionnement d'un composant magnétique dans le cas de la conversion continu/continu --- Capacité : Etre capable de dimensionner des éléments composant une cellule de commutation  --- Connaissance : Connaître les règles de dimensionnement de circuit magnétique et électronique appliquées au convertisseur de puissance --- Connaissance : Connaître les notions de transfert d'énergie et leur implication sur le rendement du dispositif  - Mettre en œuvre les différents éléments de production d'énergie, de transport d'énergie électrique et de conversion d'énergie (niveau 3)  -- Sous compétence : Mettre en œuvre les architectures de conversion statique d'énergie  --- Capacité : Etre capable de proposer des pistes de solutions  pour les principaux problèmes rencontrés dans le domaine de la conversion statique d'énergie --- Capacité : Etre capable d'identifier les paramètres d'une machine alternative expérimentalement --- Capacité : Savoir analyser un système constitué d'une machine électrique et de son alimentation  --- Connaissance : Connaître les architectures des convertisseurs DC-DC classiques (Buck, Boost, Buck-Boost, Flyback, Forward, bras de pont, pont complet) --- Connaissance : Connaître les architectures des onduleurs classiques --- Connaissance : Sélection d'une architecture en fonction d'un cahier des charges défini  - Mettre en œuvre les étapes permettant le contrôle du fonctionnement d'un système discret ou continu (niveau 1)  -- Sous compétence : Mettre en oeuvre les étapes permettant le contrôle d'un convertisseur de puissance   --- Capacité : Analyser des systèmes de variation de vitesse --- Capacité : Sélection de bloc fonctionnel pour la commande d'actionneur  --- Connaissance : Connaître certaines modulations pour la commande des onduleurs monophasés et triphasés  De plus, elle nécessite de mobiliser les compétences suivantes :  -- Analyser un système (ou un problème) réel ou virtuel -- Exploiter un modèle d'un système réel ou virtuel -- Mettre en œuvre une démarche expérimentale -- Concevoir un système répondant à un cahier des charges -- Traiter des données -- Communiquer une analyse ou une démarche scientifique -- Se connaître, se gérer physiquement et mentalement -- Travailler, apprendre, évoluer de manière autonome -- Interagir avec les autres, travailler en équipe -- Agir de manière responsable dans un monde complexe",
              "capacite": [
                "Capacité : Savoir calculer des caractéristiques liées à des performances sur les convertisseurs classiques et les associer à des valeurs de composants",
                "Capacité : Etre capable d'analyser pour comprendre le fonctionnement d'un convertisseur",
                "Capacité : Etre capable d'analyser le fonctionnement d'un composant magnétique dans le cas de la conversion continu/continu",
                "Capacité : Etre capable de dimensionner des éléments composant une cellule de commutation",
                "Capacité : Etre capable de proposer des pistes de solutions  pour les principaux problèmes rencontrés dans le domaine de la conversion statique d'énergie",
                "Capacité : Etre capable d'identifier les paramètres d'une machine alternative expérimentalement",
                "Capacité : Savoir analyser un système constitué d'une machine électrique et de son alimentation",
                "Capacité : Analyser des systèmes de variation de vitesse",
                "Capacité : Sélection de bloc fonctionnel pour la commande d'actionneur"
              ],
              "connaissance": [
                "Connaissance : Connaître les particularités de l'utilisation des composants passifs pour la conversion statique d'énergie électrique",
                "Connaissance : Connaître les notions de base sur les composants semi-conducteurs de puissance en commutation",
                "Connaissance : Connaître les règles d'association des sources",
                "Connaissance : Connaître les règles de dimensionnement de circuit magnétique et électronique appliquées au convertisseur de puissance",
                "Connaissance : Connaître les notions de transfert d'énergie et leur implication sur le rendement du dispositif",
                "Connaissance : Connaître les architectures des convertisseurs DC-DC classiques (Buck, Boost, Buck-Boost, Flyback, Forward, bras de pont, pont complet)",
                "Connaissance : Connaître les architectures des onduleurs classiques",
                "Connaissance : Sélection d'une architecture en fonction d'un cahier des charges défini",
                "Connaissance : Connaître certaines modulations pour la commande des onduleurs monophasés et triphasés"
              ],
              "competenceToCapaciteEtConnaissance": {
                "GEA-C1": [
                  "Capacité : Savoir calculer des caractéristiques liées à des performances sur les convertisseurs classiques et les associer à des valeurs de composants",
                  "Capacité : Etre capable d'analyser pour comprendre le fonctionnement d'un convertisseur",
                  "Connaissance : Connaître les particularités de l'utilisation des composants passifs pour la conversion statique d'énergie électrique",
                  "Connaissance : Connaître les notions de base sur les composants semi-conducteurs de puissance en commutation",
                  "Connaissance : Connaître les règles d'association des sources"
                ],
                "GEA-C2": [
                  "Capacité : Etre capable d'analyser le fonctionnement d'un composant magnétique dans le cas de la conversion continu/continu",
                  "Capacité : Etre capable de dimensionner des éléments composant une cellule de commutation",
                  "Connaissance : Connaître les règles de dimensionnement de circuit magnétique et électronique appliquées au convertisseur de puissance",
                  "Connaissance : Connaître les notions de transfert d'énergie et leur implication sur le rendement du dispositif"
                ],
                "GEA-C3": [
                  "Capacité : Etre capable de proposer des pistes de solutions  pour les principaux problèmes rencontrés dans le domaine de la conversion statique d'énergie",
                  "Capacité : Etre capable d'identifier les paramètres d'une machine alternative expérimentalement",
                  "Capacité : Savoir analyser un système constitué d'une machine électrique et de son alimentation",
                  "Connaissance : Connaître les architectures des convertisseurs DC-DC classiques (Buck, Boost, Buck-Boost, Flyback, Forward, bras de pont, pont complet)",
                  "Connaissance : Connaître les architectures des onduleurs classiques",
                  "Connaissance : Sélection d'une architecture en fonction d'un cahier des charges défini"
                ],
                "GEA-C6": [
                  "Capacité : Analyser des systèmes de variation de vitesse",
                  "Capacité : Sélection de bloc fonctionnel pour la commande d'actionneur",
                  "Connaissance : Connaître certaines modulations pour la commande des onduleurs monophasés et triphasés"
                ]
              },
              "listeComp": [
                {
                  "code": "C1",
                  "val": "Mettre en œuvre des composants électroniques analogiques et/ou numériques et identifier leur fonction au sein d'un montage",
                  "valAnglais": "Implement analog and / or digital electronic components and identify their function within an assembly",
                  "niveau": "3"
                },
                {
                  "code": "C2",
                  "val": "Mettre en œuvre les propriétés physiques des matériaux pour le domaine du génie électrique",
                  "valAnglais": "Implement the physical properties of materials for the field of electrical engineering",
                  "niveau": "2"
                },
                {
                  "code": "C3",
                  "val": "Mettre en œuvre les différents éléments de production d'énergie, de transport d'énergie électrique et de conversion d'énergie",
                  "valAnglais": "Implement the various elements of energy production, transport of electrical energy and energy conversion",
                  "niveau": "3"
                },
                {
                  "code": "C6",
                  "val": "Mettre en œuvre les étapes permettant le contrôle du fonctionnement d'un système discret ou continu",
                  "valAnglais": "Implement steps to control the operation of a discrete or continuous system",
                  "niveau": "1"
                }
              ],
              "listeCompMobilise": [
                "Analyser un système (ou un problème) réel ou virtuel",
                "Exploiter un modèle d'un système réel ou virtuel",
                "Mettre en œuvre une démarche expérimentale",
                "Concevoir un système répondant à un cahier des charges",
                "Traiter des données",
                "Communiquer une analyse ou une démarche scientifique",
                "Se connaître, se gérer physiquement et mentalement",
                "Travailler, apprendre, évoluer de manière autonome",
                "Interagir avec les autres, travailler en équipe",
                "Agir de manière responsable dans un monde complexe"
              ]
            }
          },
          {
            "UE": "Humanités et Education Sportive (GEA-4-UE47)",
            "url": "http://planete.insa-lyon.fr/scolpeda/f/ects?id=39726&_lang=fr",
            "detail": {
              "code": "GEA-4-EPS4",
              "ects": "1.0",
              "cours": "0.0 h",
              "td": "30.0 h",
              "tp": "0.0 h",
              "projet": "0.0 h",
              "perso": "0.0 h",
              "nom": "Education Physique et Sportive : Education Physique et Sportive",
              "competencesBrutes": "Apprendre à dépasser ses limites en faisant confiance à son partenaire au travers d'une activité sportive à risque.",
              "capacite": [],
              "connaissance": [],
              "competenceToCapaciteEtConnaissance": {}
            }
          },
          {
            "UE": "Humanités et Education Sportive (GEA-4-UE47)",
            "url": "http://planete.insa-lyon.fr/scolpeda/f/ects?id=39497&_lang=fr",
            "detail": {
              "code": "GEA-4-SHS4",
              "ects": "2.0",
              "cours": "53.0 h",
              "td": "0.0 h",
              "tp": "0.0 h",
              "projet": "0.0 h",
              "perso": "0.0 h",
              "nom": "Sciences Humaines et Sociales : Sciences Humaines et Sociales",
              "competencesBrutes": "Cet EC relève de l'unité d'enseignement  (UE47) et contribue aux compétences suivantes :  -- Traiter des données (niveau 2)  --- Capacité : Intégrer le décalage de règlement ou d'encaissement dans le quotidien de l'entreprise --- Capacité : Appréhender la rentabilité et l'équilibre financier  --- Connaissance : Inition à la gestion  -- Communiquer une analyse ou une démarche scientifique (niveau 2)  --- Capacité : Etablir le budget d'un projet et d'en assurer le suivi (contrôle budgétaire et reporting) --- Capacité : Lire et de comprendre les états prévisionnels d'une entreprise (plans, budgets  --- Connaissance : Initiation à la gestion  -- Agir de manière responsable dans un monde complexe (niveau 2)  --- Capacité : Comprendre les grands principes du droit du travail --- Capacité : Comprendre la logique juridique pour pouvoir gérer du personnel --- Capacité : Savoir choisir un investissement, être capable d'établir son budget, justifier de sa rentabilité et savoir choisir son financement  --- Connaissance : Droit : principes du droit, textes de bases¿.les représetants du personnel, les sanctions  -- Se situer, travailler, évoluer dans une entreprise, une organisation socio-productive (niveau 2)  --- Capacité : Comprendre l'intérêt de la comptabilité générale et acquérir les principes de base (bilan, compte de résultat --- Capacité : Comprendre les notions essentielles de rentabilité et d'équilibre financier --- Capacité : Connaître les principales notions et outils d'analyse financière --- Capacité : Appréhender les différents cadres législatifs et réglementaires du droit travail selon le contexte. --- Capacité : Appréhender  les principales notions et outils d'analyse financière, en lien avec le contexte. (approche internationale et interculturelle)  --- Connaissance : Initiation à la gestion: l'entreprise et ses comptes, le bilan et le compte de résultat, --- Connaissance : Gestion budgétaire:  l'entreprise et la gestion, la gestion prévisionnelle : budgets, plans, comptes prévisionnel --- Connaissance : Suivi des réalisations : contrôle budgétaire, tableaux de bord, reporting --- Connaissance : Droit: mener une vielle liée au droit du travail  adaptée à la situation. --- Connaissance : les bases de la gestion --- Connaissance : Les bases de la gestion Financière  De plus, elle nécessite de mobiliser les compétences suivantes :  -- Travailler dans un contexte international et interculturel",
              "capacite": [
                "Capacité : Intégrer le décalage de règlement ou d'encaissement dans le quotidien de l'entreprise",
                "Capacité : Appréhender la rentabilité et l'équilibre financier",
                "Capacité : Etablir le budget d'un projet et d'en assurer le suivi (contrôle budgétaire et reporting)",
                "Capacité : Lire et de comprendre les états prévisionnels d'une entreprise (plans, budgets",
                "Capacité : Comprendre les grands principes du droit du travail",
                "Capacité : Comprendre la logique juridique pour pouvoir gérer du personnel",
                "Capacité : Savoir choisir un investissement, être capable d'établir son budget, justifier de sa rentabilité et savoir choisir son financement",
                "Capacité : Comprendre l'intérêt de la comptabilité générale et acquérir les principes de base (bilan, compte de résultat",
                "Capacité : Comprendre les notions essentielles de rentabilité et d'équilibre financier",
                "Capacité : Connaître les principales notions et outils d'analyse financière",
                "Capacité : Appréhender les différents cadres législatifs et réglementaires du droit travail selon le contexte.",
                "Capacité : Appréhender  les principales notions et outils d'analyse financière, en lien avec le contexte. (approche internationale et interculturelle)"
              ],
              "connaissance": [
                "Connaissance : Inition à la gestion  -- Communiquer une analyse ou une démarche scientifique (niveau 2)",
                "Connaissance : Initiation à la gestion  -- Agir de manière responsable dans un monde complexe (niveau 2)",
                "Connaissance : Droit : principes du droit, textes de bases'.les représetants du personnel, les sanctions  -- Se situer, travailler, évoluer dans une entreprise, une organisation socio-productive (niveau 2)",
                "Connaissance : Initiation à la gestion: l'entreprise et ses comptes, le bilan et le compte de résultat,",
                "Connaissance : Gestion budgétaire:  l'entreprise et la gestion, la gestion prévisionnelle : budgets, plans, comptes prévisionnel",
                "Connaissance : Suivi des réalisations : contrôle budgétaire, tableaux de bord, reporting",
                "Connaissance : Droit: mener une vielle liée au droit du travail  adaptée à la situation.",
                "Connaissance : les bases de la gestion",
                "Connaissance : Les bases de la gestion Financière"
              ],
              "competenceToCapaciteEtConnaissance": {
                "A5": [
                  "Capacité : Intégrer le décalage de règlement ou d'encaissement dans le quotidien de l'entreprise",
                  "Capacité : Appréhender la rentabilité et l'équilibre financier",
                  "Connaissance : Inition à la gestion  -- Communiquer une analyse ou une démarche scientifique (niveau 2)",
                  "Capacité : Etablir le budget d'un projet et d'en assurer le suivi (contrôle budgétaire et reporting)",
                  "Capacité : Lire et de comprendre les états prévisionnels d'une entreprise (plans, budgets",
                  "Connaissance : Initiation à la gestion  -- Agir de manière responsable dans un monde complexe (niveau 2)",
                  "Capacité : Comprendre les grands principes du droit du travail",
                  "Capacité : Comprendre la logique juridique pour pouvoir gérer du personnel",
                  "Capacité : Savoir choisir un investissement, être capable d'établir son budget, justifier de sa rentabilité et savoir choisir son financement",
                  "Connaissance : Droit : principes du droit, textes de bases'.les représetants du personnel, les sanctions  -- Se situer, travailler, évoluer dans une entreprise, une organisation socio-productive (niveau 2)",
                  "Capacité : Comprendre l'intérêt de la comptabilité générale et acquérir les principes de base (bilan, compte de résultat",
                  "Capacité : Comprendre les notions essentielles de rentabilité et d'équilibre financier",
                  "Capacité : Connaître les principales notions et outils d'analyse financière",
                  "Capacité : Appréhender les différents cadres législatifs et réglementaires du droit travail selon le contexte.",
                  "Capacité : Appréhender  les principales notions et outils d'analyse financière, en lien avec le contexte. (approche internationale et interculturelle)",
                  "Connaissance : Initiation à la gestion: l'entreprise et ses comptes, le bilan et le compte de résultat,",
                  "Connaissance : Gestion budgétaire:  l'entreprise et la gestion, la gestion prévisionnelle : budgets, plans, comptes prévisionnel",
                  "Connaissance : Suivi des réalisations : contrôle budgétaire, tableaux de bord, reporting",
                  "Connaissance : Droit: mener une vielle liée au droit du travail  adaptée à la situation.",
                  "Connaissance : les bases de la gestion",
                  "Connaissance : Les bases de la gestion Financière"
                ]
              },
              "listeComp": [
                {
                  "code": "A5",
                  "val": "Traiter des données",
                  "valAnglais": "Process data",
                  "bs": "5",
                  "niveau": "2"
                }
              ],
              "listeCompMobilise": [
                "Travailler dans un contexte international et interculturel"
              ]
            }
          },
          {
            "UE": "Humanités et Education Sportive (GEA-4-UE47)",
            "url": "http://planete.insa-lyon.fr/scolpeda/f/ects?id=38519&_lang=fr",
            "detail": {
              "code": "GEA-4-LA4",
              "ects": "2.0",
              "cours": "36.0 h",
              "td": "0.0 h",
              "tp": "0.0 h",
              "projet": "0.0 h",
              "perso": "0.0 h",
              "nom": "Langues Étrangères : Langues vivantes - Quatrième Semestre",
              "competencesBrutes": "Cet EC relève de l'unité d'enseignement  (UE47) et contribue aux compétences suivantes :  -- Interagir avec les autres, travailler en équipe (niveau 2)  --- Capacité : S'exprimer de façon claire et détaillée sur une grande quantité de sujets, d'émettre un avis sur un sujet d'actualité et exposer les avantages et les inconvénients de différentes solutions --- Capacité : Savoir animer une réunion avec prose de décision.  --- Connaissance : Lexique, syntaxe, grammaire --- Connaissance : Expression orale --- Connaissance : compréhension orale et écrite  -- Travailler dans un contexte international et interculturel (niveau 3)  --- Capacité : S'exprimer de façon claire et détaillée sur une grande quantité de sujets, d'émettre un avis sur un sujet d'actualité et exposer les avantages et les inconvénients de différentes solutions. --- Capacité : S'exprimer de façon claire et détaillée sur une grande quantité de sujets, d'émettre un avis sur un sujet d'actualité et exposer les avantages et les inconvénients de différentes solutions --- Capacité : Communiquer avec un degré de spontanéité et d'aisance tel qu'une conversation avec un interlocuteur natif --- Capacité : Obtenir le score minimum de 785 au TOEIC --- Capacité : Communiquer avec un degré de spontanéité et d'aisance tel qu'une conversation avec un interlocuteur natif --- Capacité : S'adapter rapidement à un environnement de travail international.  --- Connaissance : Lexique, syntaxe, grammaire --- Connaissance : Expression orale --- Connaissance : compréhension orale et écrite --- Connaissance : Les différences culturelles et organisationnelles impactant les relations professionnelles. --- Connaissance : Rédaction CV et lettre de motivation (ceux partant entre la la 2 et 3ème année)  De plus, elle nécessite de mobiliser les compétences suivantes :  -- Communiquer une analyse ou une démarche scientifique -- Travailler, apprendre, évoluer de manière autonome",
              "capacite": [
                "Capacité : S'exprimer de façon claire et détaillée sur une grande quantité de sujets, d'émettre un avis sur un sujet d'actualité et exposer les avantages et les inconvénients de différentes solutions",
                "Capacité : Savoir animer une réunion avec prose de décision.",
                "Capacité : S'exprimer de façon claire et détaillée sur une grande quantité de sujets, d'émettre un avis sur un sujet d'actualité et exposer les avantages et les inconvénients de différentes solutions.",
                "Capacité : S'exprimer de façon claire et détaillée sur une grande quantité de sujets, d'émettre un avis sur un sujet d'actualité et exposer les avantages et les inconvénients de différentes solutions",
                "Capacité : Communiquer avec un degré de spontanéité et d'aisance tel qu'une conversation avec un interlocuteur natif",
                "Capacité : Obtenir le score minimum de 785 au TOEIC",
                "Capacité : Communiquer avec un degré de spontanéité et d'aisance tel qu'une conversation avec un interlocuteur natif",
                "Capacité : S'adapter rapidement à un environnement de travail international."
              ],
              "connaissance": [
                "Connaissance : Lexique, syntaxe, grammaire",
                "Connaissance : Expression orale",
                "Connaissance : compréhension orale et écrite  -- Travailler dans un contexte international et interculturel (niveau 3)",
                "Connaissance : Lexique, syntaxe, grammaire",
                "Connaissance : Expression orale",
                "Connaissance : compréhension orale et écrite",
                "Connaissance : Les différences culturelles et organisationnelles impactant les relations professionnelles.",
                "Connaissance : Rédaction CV et lettre de motivation (ceux partant entre la la 2 et 3ème année)"
              ],
              "competenceToCapaciteEtConnaissance": {
                "B3": [
                  "Capacité : S'exprimer de façon claire et détaillée sur une grande quantité de sujets, d'émettre un avis sur un sujet d'actualité et exposer les avantages et les inconvénients de différentes solutions",
                  "Capacité : Savoir animer une réunion avec prose de décision.",
                  "Connaissance : Lexique, syntaxe, grammaire",
                  "Connaissance : Expression orale",
                  "Connaissance : compréhension orale et écrite  -- Travailler dans un contexte international et interculturel (niveau 3)",
                  "Capacité : S'exprimer de façon claire et détaillée sur une grande quantité de sujets, d'émettre un avis sur un sujet d'actualité et exposer les avantages et les inconvénients de différentes solutions.",
                  "Capacité : S'exprimer de façon claire et détaillée sur une grande quantité de sujets, d'émettre un avis sur un sujet d'actualité et exposer les avantages et les inconvénients de différentes solutions",
                  "Capacité : Communiquer avec un degré de spontanéité et d'aisance tel qu'une conversation avec un interlocuteur natif",
                  "Capacité : Obtenir le score minimum de 785 au TOEIC",
                  "Capacité : Communiquer avec un degré de spontanéité et d'aisance tel qu'une conversation avec un interlocuteur natif",
                  "Capacité : S'adapter rapidement à un environnement de travail international.",
                  "Connaissance : Lexique, syntaxe, grammaire",
                  "Connaissance : Expression orale",
                  "Connaissance : compréhension orale et écrite",
                  "Connaissance : Les différences culturelles et organisationnelles impactant les relations professionnelles.",
                  "Connaissance : Rédaction CV et lettre de motivation (ceux partant entre la la 2 et 3ème année)"
                ]
              },
              "listeComp": [
                {
                  "code": "B3",
                  "val": "Interagir avec les autres, travailler en équipe",
                  "valAnglais": "Interact with people and work in a team",
                  "bs": "25",
                  "niveau": "2"
                }
              ],
              "listeCompMobilise": [
                "Communiquer une analyse ou une démarche scientifique",
                "Travailler, apprendre, évoluer de manière autonome"
              ]
            }
          },
          {
            "UE": "Projet Entreprise (GEA-4-UE48)",
            "url": "http://planete.insa-lyon.fr/scolpeda/f/ects?id=37645&_lang=fr",
            "detail": {
              "code": "GEA-4-PE4",
              "ects": "13.0",
              "cours": "0.0 h",
              "td": "0.0 h",
              "tp": "0.0 h",
              "projet": "1.0 h",
              "perso": "0.0 h",
              "nom": "Entreprise : Période en entreprise 4",
              "competencesBrutes": "Cet EC relève de l'unité d'enseignement  (UE48) et contribue aux compétences suivantes :  -- Se situer, travailler, évoluer dans une entreprise, une organisation socio-productive (niveau 2)  --- Capacité : Prendre en compte les enjeux économiques d'un projet. --- Capacité : Participer à l'élaboration d'd'un budget et/ou au suivi des coûts. --- Capacité : Contacter des clients ou des fournisseurs pour établir des devis ou répondre à des offres.  --- Connaissance : Enjeux économiques  -- Travailler, apprendre, évoluer de manière autonome (niveau 2)  --- Capacité : Respecter les objectifs et le planning prévisionnel fixé par le projet. --- Capacité : Formaliser avec le Maitre d'Apprentissage les objectifs du projet avec des indicateurs de résultats et un planning prévisionnel pour son travail personnel --- Capacité : Etre force de proposition de solution technique  --- Connaissance : Gestion du temps --- Connaissance : Démarche projet  -- Interagir avec les autres, travailler en équipe (niveau )  --- Capacité : Etre capable de présenter un projet dans sa globalité à l'écrit ou devant un public --- Capacité : Savoir chercher l'information auprès des bonnes personnes.  --- Connaissance : communication, esprit de synthèse  - Mettre en œuvre ses compétences scientifiques et technologiques dans le domaine de l'EEAIIT dans un cadre industriel et appliqué à des problématiques réelles en conduisant les étapes du cycle de conception (niveau )  --- Capacité : Etre associé à plusieurs étapes du cycle en V --- Capacité : mettre en œuvre des sous ensembles multi domaines de l'EEAIIT et/ou multiphysique. --- Capacité : Outils de modélisations et simulation multidomaines --- Capacité : Ecriture de spécifications fonctionnelles et techniques  --- Connaissance : Mise en œuvre de composants ou sous ensemble fonctionnels, Prototypage --- Connaissance : utilisation CAO / DAO, simulation performance.",
              "capacite": [
                "Capacité : Prendre en compte les enjeux économiques d'un projet.",
                "Capacité : Participer à l'élaboration d'd'un budget et/ou au suivi des coûts.",
                "Capacité : Contacter des clients ou des fournisseurs pour établir des devis ou répondre à des offres.",
                "Capacité : Respecter les objectifs et le planning prévisionnel fixé par le projet.",
                "Capacité : Formaliser avec le Maitre d'Apprentissage les objectifs du projet avec des indicateurs de résultats et un planning prévisionnel pour son travail personnel",
                "Capacité : Etre force de proposition de solution technique",
                "Capacité : Etre capable de présenter un projet dans sa globalité à l'écrit ou devant un public",
                "Capacité : Savoir chercher l'information auprès des bonnes personnes.",
                "Capacité : Etre associé à plusieurs étapes du cycle en V",
                "Capacité : mettre en œuvre des sous ensembles multi domaines de l'EEAIIT et/ou multiphysique.",
                "Capacité : Outils de modélisations et simulation multidomaines",
                "Capacité : Ecriture de spécifications fonctionnelles et techniques"
              ],
              "connaissance": [
                "Connaissance : Enjeux économiques  -- Travailler, apprendre, évoluer de manière autonome (niveau 2)",
                "Connaissance : Gestion du temps",
                "Connaissance : Démarche projet  -- Interagir avec les autres, travailler en équipe (niveau )",
                "Connaissance : communication, esprit de synthèse",
                "Connaissance : Mise en œuvre de composants ou sous ensemble fonctionnels, Prototypage",
                "Connaissance : utilisation CAO / DAO, simulation performance."
              ],
              "competenceToCapaciteEtConnaissance": {
                "B6": [
                  "Capacité : Prendre en compte les enjeux économiques d'un projet.",
                  "Capacité : Participer à l'élaboration d'd'un budget et/ou au suivi des coûts.",
                  "Capacité : Contacter des clients ou des fournisseurs pour établir des devis ou répondre à des offres.",
                  "Connaissance : Enjeux économiques  -- Travailler, apprendre, évoluer de manière autonome (niveau 2)",
                  "Capacité : Respecter les objectifs et le planning prévisionnel fixé par le projet.",
                  "Capacité : Formaliser avec le Maitre d'Apprentissage les objectifs du projet avec des indicateurs de résultats et un planning prévisionnel pour son travail personnel",
                  "Capacité : Etre force de proposition de solution technique",
                  "Connaissance : Gestion du temps",
                  "Connaissance : Démarche projet  -- Interagir avec les autres, travailler en équipe (niveau )",
                  "Capacité : Etre capable de présenter un projet dans sa globalité à l'écrit ou devant un public",
                  "Capacité : Savoir chercher l'information auprès des bonnes personnes.",
                  "Connaissance : communication, esprit de synthèse"
                ],
                "GEA-C9": [
                  "Capacité : Etre associé à plusieurs étapes du cycle en V",
                  "Capacité : mettre en œuvre des sous ensembles multi domaines de l'EEAIIT et/ou multiphysique.",
                  "Capacité : Outils de modélisations et simulation multidomaines",
                  "Capacité : Ecriture de spécifications fonctionnelles et techniques",
                  "Connaissance : Mise en œuvre de composants ou sous ensemble fonctionnels, Prototypage",
                  "Connaissance : utilisation CAO / DAO, simulation performance."
                ]
              },
              "listeComp": [
                {
                  "code": "B6",
                  "val": "Se situer, travailler, évoluer dans une entreprise, une organisation socio-productive",
                  "valAnglais": "Position oneself, work, and evolve within a company or a socio-productive organization",
                  "bs": "28",
                  "niveau": "2"
                },
                {
                  "code": "C9",
                  "val": "Mettre en œuvre ses compétences scientifiques et technologiques dans le domaine de l'EEAIIT dans un cadre industriel et appliqué à des problématiques réelles en conduisant les étapes du cycle de conception",
                  "valAnglais": "Apply scientific and technological competences in the field of the EEAIIT in an industrial framework and to real problems by leading the stages of the cycle of conception",
                  "niveau": ""
                }
              ]
            }
          }
        ]
      },
      {
        "url": "/fr/formation/parcours/1165/5/1",
        "ecs": [
          {
            "UE": "Enseignements Transversaux (GEA-5-UE51)",
            "url": "http://planete.insa-lyon.fr/scolpeda/f/ects?id=37823&_lang=fr",
            "detail": {
              "code": "GEA-5-MA4",
              "ects": "2.0",
              "cours": "21.5 h",
              "td": "21.5 h",
              "tp": "0.0 h",
              "projet": "0.0 h",
              "perso": "10.0 h",
              "nom": "Mathématiques : Recherche Opérationnelle",
              "competencesBrutes": "COMPETENCES : Cet enseignement vise à développer les compétences suivantes : - définir des objectifs à optimiser pour une organisation - comprendre et modéliser un problème réel - utiliser et adapter des algorithmes d'optimisation - comprendre les limites des modèles et des résolutions informatiques (notamment la complexité)",
              "capacite": [],
              "connaissance": [],
              "competenceToCapaciteEtConnaissance": {}
            }
          },
          {
            "UE": "Enseignements Transversaux (GEA-5-UE51)",
            "url": "http://planete.insa-lyon.fr/scolpeda/f/ects?id=37377&_lang=fr",
            "detail": {
              "code": "GE-5-ISIP",
              "ects": "12.0",
              "cours": "76.0 h",
              "td": "10.0 h",
              "tp": "24.0 h",
              "projet": "78.0 h",
              "perso": "20.0 h",
              "nom": "Automatique : Ingénierie des Système Intégrés de Production",
              "competencesBrutes": "Cet EC relève de l'unité d'enseignement ISIP (UE54) et contribue aux compétences suivantes :  - Mettre en œuvre les étapes permettant le contrôle du fonctionnement d¿un système discret ou continu (niveau 3)  --- Capacité : Analyser le fonctionnement de l'entreprise de production selon le modèle inspiré de la pyramide CIM. --- Capacité : Niveau Process : Dimensionner des équipements en technologie pneumatique, électropneumatique. Commander un robot poly-articulé. --- Capacité : Niveau Contrôle - Commande : Développer la commande de procédés industriels de type manufacturier (API et IHM). --- Capacité : Développer la communication industrielle en implémentant les standards des réseaux de terrain, la technologie OPC, les Web Services.  --- Connaissance : Initiation aux capteurs et actionneurs spécifiques aux industries de process. --- Connaissance : Initiation à la commande de process continus en utilisant des SNCC (Systèmes Numériques de Contrôle Commande). --- Connaissance : Sensibilisation à la sécurité Machines et à la cyber-sécurité.  - Concevoir et développer des logiciels haut et bas niveau pour des systèmes (traitement et gestion de l'information) (niveau 3)  --- Capacité : Développer une application de MES (Manufacturing Execution System). --- Capacité : Développer, au sein d'un MES, les fonctionnalités d'exécution des fabrications et de suivi de la production (indicateurs de performance et gestion de la qualité).  --- Connaissance : Initiation aux différents types de systèmes d'information industriels en industries manufacturières et de process. --- Connaissance : Initiation aux spécificités des applications MES dans l'industrie de process.  - Mettre en œuvre des principes et stratégies d¿ordonnancements des tâches et de gestion (niveau 2)  --- Capacité : Réfléchir à l'organisation de l'entreprise en utilisant des démarches d'amélioration continue de type Lean Management. --- Capacité : Développer le travail collaboratif au sein d'équipes projets favorisant les technologies innovantes et utilisant les concepts de l'Ingénierie Système. --- Capacité : Analyser un système et mettre en place l'ordonnancement.  --- Connaissance : Initiation au droit du travail et des contrats.  De plus, elle nécessite de mobiliser les compétences suivantes :  - Compétences en sciences pour l'ingénieur : -- Analyser un système (ou un problème) réel ou virtuel. -- Exploiter un modèle d'un système réel ou virtuel. -- Mettre en œuvre une démarche expérimentale. -- Concevoir un système répondant à un cahier des charges. -- Traiter des données. -- Communiquer une analyse ou une démarche scientifique.   - Compétences en humanités, documentation et éducation physique et sportive : -- Se connaître, se gérer physiquement et mentalement. -- Travailler, apprendre, évoluer de manière autonome. -- Interagir avec les autres, travailler en équipe. -- Faire preuve de créativité, innover, entreprendre. -- Agir de manière responsable dans un monde complexe. -- Se situer, travailler, évoluer dans une entreprise, une organisation socio-productive. -- Travailler dans un contexte international et interculturel.",
              "capacite": [
                "Capacité : Analyser le fonctionnement de l'entreprise de production selon le modèle inspiré de la pyramide CIM.",
                "Capacité : Niveau Process : Dimensionner des équipements en technologie pneumatique, électropneumatique. Commander un robot poly-articulé.",
                "Capacité : Niveau Contrôle"
              ],
              "connaissance": [],
              "competenceToCapaciteEtConnaissance": {
                "GEA-C6": [
                  "Capacité : Analyser le fonctionnement de l'entreprise de production selon le modèle inspiré de la pyramide CIM.",
                  "Capacité : Niveau Process : Dimensionner des équipements en technologie pneumatique, électropneumatique. Commander un robot poly-articulé.",
                  "Capacité : Niveau Contrôle"
                ]
              },
              "listeCompMobilise": [
                "Analyser un système (ou un problème) réel ou virtuel",
                "Exploiter un modèle d'un système réel ou virtuel",
                "Mettre en œuvre une démarche expérimentale",
                "Concevoir un système répondant à un cahier des charges",
                "Traiter des données",
                "Communiquer une analyse ou une démarche scientifique",
                "Se connaître, se gérer physiquement et mentalement",
                "Travailler, apprendre, évoluer de manière autonome",
                "Interagir avec les autres, travailler en équipe",
                "Faire preuve de créativité, innover, entreprendre",
                "Agir de manière responsable dans un monde complexe",
                "Se situer, travailler, évoluer dans une entreprise, une organisation socio-productive",
                "Travailler dans un contexte international et interculturel"
              ]
            }
          },
          {
            "UE": "Enseignements Transversaux (GEA-5-UE51)",
            "url": "http://planete.insa-lyon.fr/scolpeda/f/ects?id=37592&_lang=fr",
            "detail": {
              "code": "GE-5-CEE",
              "ects": "12.0",
              "cours": "138.0 h",
              "td": "51.0 h",
              "tp": "0.0 h",
              "projet": "12.0 h",
              "perso": "55.0 h",
              "nom": "Electrotechnique et Electronique de Puissance : Conversion de l'Energie Electrique",
              "competencesBrutes": "Cet EC relève de l'unité d'enseignement CEE (UE54) et contribue aux compétences suivantes :  - Mettre en œuvre les propriétés physiques des matériaux pour le domaine du génie électrique (niveau 3)  -- Sous compétence : Mettre en œuvre des matériaux couplés pour la conversion d'énergie  --- Capacité : Mettre en place une loi de comportement. --- Capacité : Modéliser un élément et un système électro-actif. --- Capacité : Choisir une batterie ou un matériau électro-actif pour une application donnée.  --- Connaissance : Différents types de couplages et de conversion et leurs mécanismes. --- Connaissance : Caractéristiques importantes d¿un matériau électroactif. --- Connaissance : Procédés et méthodes de caractérisation de matériaux et systèmes électro-actifs.  - Mettre en œuvre les différents éléments de production d¿énergie, de transport d¿énergie électrique et de conversion d'énergie (niveau 3)  -- Sous compétence : Mettre en œuvre des solutions de production, distribution et stockage de l'énergie  --- Capacité : Dimensionner une installation éolienne ou photovoltaïque. --- Capacité : Identifier les problèmes sur un réseau de distribution électrique et les corriger.  --- Connaissance : Principes de fonctionnement de différents types d'installation de production d'énergie. --- Connaissance : Schéma de principe d¿une centrale thermique. --- Connaissance : Principes de fonctionnement et réglage d¿une turbine à vapeur et de la chaudière.  - Mettre en œuvre les étapes permettant le contrôle du fonctionnement d¿un système discret ou continu  --- Capacité : Mettre en œuvre et dimensionner un circuit de charge de batterie. --- Capacité : Simplifier un système multiphysique, le modéliser et choisir une technique d'analyse adaptée. --- Capacité : Interpréter les résultats d¿une simulation.  --- Connaissance : Principe d¿une régulation au maximum de puissance. --- Connaissance : Structure de charge de batteries. --- Connaissance : Applications typiques des matériaux électroactifs et architectures typiques de ces systèmes. --- Connaissance : Méthodes de représentation d¿un système.  De plus, elle nécessite de mobiliser les compétences suivantes :  - Compétences en sciences pour l'ingénieur : -- Analyser un système (ou un problème) réel ou virtuel. -- Exploiter un modèle d'un système réel ou virtuel. -- Concevoir un système répondant à un cahier des charges. -- Traiter des données. -- Communiquer une analyse ou une démarche scientifique.   - Compétences en humanités, documentation et éducation physique et sportive : -- Travailler, apprendre, évoluer de manière autonome. -- Interagir avec les autres, travailler en équipe. -- Faire preuve de créativité, innover, entreprendre. -- Agir de manière responsable dans un monde complexe. -- Se situer, travailler, évoluer dans une entreprise, une organisation socio-productive. -- Travailler dans un contexte international et interculturel.",
              "capacite": [
                "Capacité : Mettre en place une loi de comportement.",
                "Capacité : Modéliser un élément et un système électro-actif.",
                "Capacité : Choisir une batterie ou un matériau électro-actif pour une application donnée.",
                "Capacité : Dimensionner une installation éolienne ou photovoltaïque.",
                "Capacité : Identifier les problèmes sur un réseau de distribution électrique et les corriger.",
                "Capacité : Mettre en œuvre et dimensionner un circuit de charge de batterie.",
                "Capacité : Simplifier un système multiphysique, le modéliser et choisir une technique d'analyse adaptée.",
                "Capacité : Interpréter les résultats d'une simulation."
              ],
              "connaissance": [
                "Connaissance : Différents types de couplages et de conversion et leurs mécanismes.",
                "Connaissance : Caractéristiques importantes d'un matériau électroactif.",
                "Connaissance : Procédés et méthodes de caractérisation de matériaux et systèmes électro-actifs.",
                "Connaissance : Principes de fonctionnement de différents types d'installation de production d'énergie.",
                "Connaissance : Schéma de principe d'une centrale thermique.",
                "Connaissance : Principes de fonctionnement et réglage d'une turbine à vapeur et de la chaudière.",
                "Connaissance : Principe d'une régulation au maximum de puissance.",
                "Connaissance : Structure de charge de batteries.",
                "Connaissance : Applications typiques des matériaux électroactifs et architectures typiques de ces systèmes.",
                "Connaissance : Méthodes de représentation d'un système."
              ],
              "competenceToCapaciteEtConnaissance": {
                "GEA-C2": [
                  "Capacité : Mettre en place une loi de comportement.",
                  "Capacité : Modéliser un élément et un système électro-actif.",
                  "Capacité : Choisir une batterie ou un matériau électro-actif pour une application donnée.",
                  "Connaissance : Différents types de couplages et de conversion et leurs mécanismes.",
                  "Connaissance : Caractéristiques importantes d'un matériau électroactif.",
                  "Connaissance : Procédés et méthodes de caractérisation de matériaux et systèmes électro-actifs."
                ],
                "GEA-C3": [
                  "Capacité : Dimensionner une installation éolienne ou photovoltaïque.",
                  "Capacité : Identifier les problèmes sur un réseau de distribution électrique et les corriger.",
                  "Connaissance : Principes de fonctionnement de différents types d'installation de production d'énergie.",
                  "Connaissance : Schéma de principe d'une centrale thermique.",
                  "Connaissance : Principes de fonctionnement et réglage d'une turbine à vapeur et de la chaudière."
                ],
                "GEA-C6": [
                  "Capacité : Mettre en œuvre et dimensionner un circuit de charge de batterie.",
                  "Capacité : Simplifier un système multiphysique, le modéliser et choisir une technique d'analyse adaptée.",
                  "Capacité : Interpréter les résultats d'une simulation.",
                  "Connaissance : Principe d'une régulation au maximum de puissance.",
                  "Connaissance : Structure de charge de batteries.",
                  "Connaissance : Applications typiques des matériaux électroactifs et architectures typiques de ces systèmes.",
                  "Connaissance : Méthodes de représentation d'un système."
                ]
              },
              "listeComp": [
                {
                  "code": "C2",
                  "val": "Mettre en œuvre les propriétés physiques des matériaux pour le domaine du génie électrique",
                  "valAnglais": "Implement the physical properties of materials for the field of electrical engineering",
                  "niveau": "3"
                },
                {
                  "code": "C3",
                  "val": "Mettre en œuvre les différents éléments de production d'énergie, de transport d'énergie électrique et de conversion d'énergie",
                  "valAnglais": "Implement the various elements of energy production, transport of electrical energy and energy conversion",
                  "niveau": "3"
                },
                {
                  "code": "C6",
                  "val": "Mettre en œuvre les étapes permettant le contrôle du fonctionnement d'un système discret ou continu",
                  "valAnglais": "Implement steps to control the operation of a discrete or continuous system",
                  "niveau": 1
                }
              ],
              "listeCompMobilise": [
                "Analyser un système (ou un problème) réel ou virtuel",
                "Exploiter un modèle d'un système réel ou virtuel",
                "Concevoir un système répondant à un cahier des charges",
                "Traiter des données",
                "Communiquer une analyse ou une démarche scientifique",
                "Travailler, apprendre, évoluer de manière autonome",
                "Interagir avec les autres, travailler en équipe",
                "Faire preuve de créativité, innover, entreprendre",
                "Agir de manière responsable dans un monde complexe",
                "Se situer, travailler, évoluer dans une entreprise, une organisation socio-productive",
                "Travailler dans un contexte international et interculturel"
              ]
            }
          },
          {
            "UE": "Enseignements Transversaux (GEA-5-UE51)",
            "url": "http://planete.insa-lyon.fr/scolpeda/f/ects?id=37803&_lang=fr",
            "detail": {
              "code": "GE-5-CCSA",
              "ects": "12.0",
              "cours": "126.0 h",
              "td": "24.0 h",
              "tp": "112.0 h",
              "projet": "30.0 h",
              "perso": "0.0 h",
              "nom": "Electrotechnique et Electronique de Puissance : Commande des Convertisseurs et Systèmes d'Actionnement",
              "competencesBrutes": "Cet EC relève de l'unité d'enseignement de CCSA (UE54) et contribue aux compétences suivantes :  - Mettre en œuvre des composants électroniques analogiques et/ou numériques et identifier leur fonction au sein d'un montage (niveau 1)  --- Capacité : Etre capable de choisir un composant d'électronique de puissance pour la conversion d'énergie.  --- Connaissance : connaître les technologies pour pouvoir choisir un composant passif (condensateur, magnétiques). --- Connaissance : connaître les technologies de composants de puissance IGBT et MOSFET.  - Mettre en œuvre les différents éléments de production d'énergie, de transport d'énergie électrique et de conversion d'énergie (niveau 3).  --- Capacité : Etre capable de proposer des pistes de solutions pour les principaux problèmes rencontrés dans le domaine de la conversion statique d'énergie.  --- Connaissance : Connaître et différencier les différents moyens de stocker de l'énergie électrique (batterie, super-condensateurs). --- Connaissance : Connaître la constitution et la fabrication de machines synchrones et asynchrones. --- Connaissance : Connaître différentes topologies de convertisseurs résonnants ou quasi- résonnants. --- Connaissance : Avoir des notions sur les convertisseurs utilisés dans le domaine des réseaux haute tension continus et alternatifs. --- Connaissance : Appréhender la constitution d'un convertisseur industriel dans le domaine des transports. --- Connaissance : Avoir des notions sur les problèmes de compatibilité électromagnétique. --- Connaissance : Avoir des notions sur la constitution d'un réseau électrique d'un véhicule.  - Concevoir et réaliser des systèmes électroniques pour l'acquisition, le traitement, la commande et la communication de données (niveau 3)  --- Capacité : Etre capable de concevoir et de mettre en place expérimentalement une commande de machine synchrone à aimants. --- Capacité : Etre capable de modéliser pour la commande un système de conversion statique d'énergie.  --- Connaissance : Connaître les techniques de modulation pour onduleur et leurs impacts. --- Connaissance : Connaître la constitution d'une chaîne de traction dans le domaine ferroviaire.  - Mettre en œuvre les étapes permettant le contrôle du fonctionnement d'un système discret ou continu (niveau 3)  --- Capacité : Etre capable de synthétiser une loi de commande pour un convertisseur avec une approche directe. --- Capacité : Etre capable de synthétiser une loi de commande pour un convertisseur avec une approche par modèle moyen. --- Capacité : Analyser des systèmes non linéaires. --- Capacité : Etablir des propriétés structurelles d'un système non linéaire : indice caractéristique, dynamique résiduelle. --- Capacité : Etre capable de synthétiser une loi de commande pour une association onduleur/machine triphasée.   --- Connaissance : Etre initié à l'analyse de la stabilité des systèmes non linéaires. --- Connaissance : Etre initié à la commande des systèmes non linéaires. --- Connaissance : Avoir une vision sur l'intérêt du prototypage rapide de loi de commande pour la recherche et le développement.  De plus, elle nécessite de mobiliser les compétences suivantes :  - Compétences en sciences pour l'ingénieur : -- Analyser un système (ou un problème) réel ou virtuel. -- Exploiter un modèle d'un système réel ou virtuel. -- Mettre en œuvre une démarche expérimentale. -- Concevoir un système répondant à un cahier des charges. -- Traiter des données. -- Communiquer une analyse ou une démarche scientifique.  - Compétences en humanités, documentation et éducation physique et sportive : -- Se connaître, se gérer physiquement et mentalement. -- Travailler, apprendre, évoluer de manière autonome. -- Interagir avec les autres, travailler en équipe. -- Faire preuve de créativité, innover, entreprendre. -- Agir de manière responsable dans un monde complexe. -- Se situer, travailler, évoluer dans une entreprise, une organisation socio-productive. -- Travailler dans un contexte international et interculturel.",
              "capacite": [
                "Capacité : Etre capable de choisir un composant d'électronique de puissance pour la conversion d'énergie.",
                "Capacité : Etre capable de proposer des pistes de solutions pour les principaux problèmes rencontrés dans le domaine de la conversion statique d'énergie.",
                "Capacité : Etre capable de concevoir et de mettre en place expérimentalement une commande de machine synchrone à aimants.",
                "Capacité : Etre capable de modéliser pour la commande un système de conversion statique d'énergie.",
                "Capacité : Etre capable de synthétiser une loi de commande pour un convertisseur avec une approche directe.",
                "Capacité : Etre capable de synthétiser une loi de commande pour un convertisseur avec une approche par modèle moyen.",
                "Capacité : Analyser des systèmes non linéaires.",
                "Capacité : Etablir des propriétés structurelles d'un système non linéaire : indice caractéristique, dynamique résiduelle.",
                "Capacité : Etre capable de synthétiser une loi de commande pour une association onduleur/machine triphasée."
              ],
              "connaissance": [
                "Connaissance : connaître les technologies pour pouvoir choisir un composant passif (condensateur, magnétiques).",
                "Connaissance : connaître les technologies de composants de puissance IGBT et MOSFET.",
                "Connaissance : Connaître et différencier les différents moyens de stocker de l'énergie électrique (batterie, super-condensateurs).",
                "Connaissance : Connaître la constitution et la fabrication de machines synchrones et asynchrones.",
                "Connaissance : Connaître différentes topologies de convertisseurs résonnants ou quasi- résonnants.",
                "Connaissance : Avoir des notions sur les convertisseurs utilisés dans le domaine des réseaux haute tension continus et alternatifs.",
                "Connaissance : Appréhender la constitution d'un convertisseur industriel dans le domaine des transports.",
                "Connaissance : Avoir des notions sur les problèmes de compatibilité électromagnétique.",
                "Connaissance : Avoir des notions sur la constitution d'un réseau électrique d'un véhicule.",
                "Connaissance : Connaître les techniques de modulation pour onduleur et leurs impacts.",
                "Connaissance : Connaître la constitution d'une chaîne de traction dans le domaine ferroviaire.",
                "Connaissance : Etre initié à l'analyse de la stabilité des systèmes non linéaires.",
                "Connaissance : Etre initié à la commande des systèmes non linéaires.",
                "Connaissance : Avoir une vision sur l'intérêt du prototypage rapide de loi de commande pour la recherche et le développement."
              ],
              "competenceToCapaciteEtConnaissance": {
                "GEA-C1": [
                  "Capacité : Etre capable de choisir un composant d'électronique de puissance pour la conversion d'énergie.",
                  "Connaissance : connaître les technologies pour pouvoir choisir un composant passif (condensateur, magnétiques).",
                  "Connaissance : connaître les technologies de composants de puissance IGBT et MOSFET."
                ],
                "GEA-C3": [
                  "Capacité : Etre capable de proposer des pistes de solutions pour les principaux problèmes rencontrés dans le domaine de la conversion statique d'énergie.",
                  "Connaissance : Connaître et différencier les différents moyens de stocker de l'énergie électrique (batterie, super-condensateurs).",
                  "Connaissance : Connaître la constitution et la fabrication de machines synchrones et asynchrones.",
                  "Connaissance : Connaître différentes topologies de convertisseurs résonnants ou quasi- résonnants.",
                  "Connaissance : Avoir des notions sur les convertisseurs utilisés dans le domaine des réseaux haute tension continus et alternatifs.",
                  "Connaissance : Appréhender la constitution d'un convertisseur industriel dans le domaine des transports.",
                  "Connaissance : Avoir des notions sur les problèmes de compatibilité électromagnétique.",
                  "Connaissance : Avoir des notions sur la constitution d'un réseau électrique d'un véhicule."
                ],
                "GEA-C5": [
                  "Capacité : Etre capable de concevoir et de mettre en place expérimentalement une commande de machine synchrone à aimants.",
                  "Capacité : Etre capable de modéliser pour la commande un système de conversion statique d'énergie.",
                  "Connaissance : Connaître les techniques de modulation pour onduleur et leurs impacts.",
                  "Connaissance : Connaître la constitution d'une chaîne de traction dans le domaine ferroviaire."
                ],
                "GEA-C6": [
                  "Capacité : Etre capable de synthétiser une loi de commande pour un convertisseur avec une approche directe.",
                  "Capacité : Etre capable de synthétiser une loi de commande pour un convertisseur avec une approche par modèle moyen.",
                  "Capacité : Analyser des systèmes non linéaires.",
                  "Capacité : Etablir des propriétés structurelles d'un système non linéaire : indice caractéristique, dynamique résiduelle.",
                  "Capacité : Etre capable de synthétiser une loi de commande pour une association onduleur/machine triphasée.",
                  "Connaissance : Etre initié à l'analyse de la stabilité des systèmes non linéaires.",
                  "Connaissance : Etre initié à la commande des systèmes non linéaires.",
                  "Connaissance : Avoir une vision sur l'intérêt du prototypage rapide de loi de commande pour la recherche et le développement."
                ]
              },
              "listeComp": [
                {
                  "code": "C1",
                  "val": "Mettre en œuvre des composants électroniques analogiques et/ou numériques et identifier leur fonction au sein d'un montage",
                  "valAnglais": "Implement analog and / or digital electronic components and identify their function within an assembly",
                  "niveau": "1"
                },
                {
                  "code": "C3",
                  "val": "Mettre en œuvre les différents éléments de production d'énergie, de transport d'énergie électrique et de conversion d'énergie",
                  "valAnglais": "Implement the various elements of energy production, transport of electrical energy and energy conversion",
                  "niveau": "3"
                },
                {
                  "code": "C5",
                  "val": "Concevoir et réaliser des systèmes électroniques pour l'acquisition, le traitement, la commande et la communication de données",
                  "valAnglais": "Design and build electronic systems for data acquisition, processing, control and communication",
                  "niveau": "3"
                },
                {
                  "code": "C6",
                  "val": "Mettre en œuvre les étapes permettant le contrôle du fonctionnement d'un système discret ou continu",
                  "valAnglais": "Implement steps to control the operation of a discrete or continuous system",
                  "niveau": "3"
                }
              ],
              "listeCompMobilise": [
                "Analyser un système (ou un problème) réel ou virtuel",
                "Exploiter un modèle d'un système réel ou virtuel",
                "Mettre en œuvre une démarche expérimentale",
                "Concevoir un système répondant à un cahier des charges",
                "Traiter des données",
                "Communiquer une analyse ou une démarche scientifique",
                "Se connaître, se gérer physiquement et mentalement",
                "Travailler, apprendre, évoluer de manière autonome",
                "Interagir avec les autres, travailler en équipe",
                "Faire preuve de créativité, innover, entreprendre",
                "Agir de manière responsable dans un monde complexe",
                "Se situer, travailler, évoluer dans une entreprise, une organisation socio-productive",
                "Travailler dans un contexte international et interculturel"
              ]
            }
          },
          {
            "UE": "Enseignements Transversaux (GEA-5-UE51)",
            "url": "http://planete.insa-lyon.fr/scolpeda/f/ects?id=37373&_lang=fr",
            "detail": {
              "code": "GE-5-SEI",
              "ects": "12.0",
              "cours": "93.5 h",
              "td": "50.0 h",
              "tp": "36.0 h",
              "projet": "16.0 h",
              "perso": "64.0 h",
              "nom": "Electronique : Technologie et physique des composants à semiconducteur",
              "competencesBrutes": "Cet EC relève de l'unité d'enseignement SEI (UE54) et contribue aux compétences suivantes :  - Mettre en œuvre des composants électroniques analogiques et/ou numériques et identifier leur fonction au sein d'un montage (niveau 3)  -- Sous compétence : Mettre en œuvre des composants électroniques semi-conducteurs au sein d'un système électronique  --- Capacité : Mesurer l'impact d'une technologie de semi-conducteur sur les performances électriques d'un système électronique. --- Capacité : Dimensionner un système électronique en fonction des contraintes d'une technologie de semi-conducteur. --- Capacité : Décrire un circuit numérique destiné à être synthétisé via le langage de description matérielle VHDL.  --- Connaissance : Électronique analogique et numérique. --- Connaissance : Structures des composants semi-conducteurs. --- Connaissance : Langage de description matérielle VHDL.  - Mettre en œuvre les propriétés physiques des matériaux pour le domaine du génie électrique (niveau 3)  -- Sous compétence : Mettre en œuvre les propriétés physiques d'un matériau semi- conducteur dans la conception et la fabrication d'un composant électronique ou d'un circuit intégré  --- Capacité : Comprendre la physique du semi-conducteur et des composants semi- conducteurs pour concevoir des composants et des circuits intégrés qui répondent à des besoins identifiés. --- Capacité : Identifier les différents procédés technologiques de salle blanche et savoir les intégrer dans la conception d'un composant semi-conducteur. --- Capacité : Concevoir et modéliser un composant semi-conducteur par éléments finis en s'appuyant sur des modèles physiques ou empiriques existants. --- Capacité : Caractériser électriquement un composant semi-conducteur, en faire le lien avec la physique du composant et en mesurer l'impact au sein d'un système électronique.  --- Connaissance : Physique du semi-conducteur et des composants semi-conducteurs. --- Connaissance : Procédés technologiques de salle blanche. --- Connaissance : Modélisation par éléments finis. --- Connaissance : Caractérisations électriques sous pointes et en boîtier.  De plus, elle nécessite de mobiliser les compétences suivantes :  - Compétences en sciences pour l'ingénieur : -- Analyser un système (ou un problème) réel ou virtuel. -- Exploiter un modèle d'un système réel ou virtuel. -- Mettre en œuvre une démarche expérimentale. -- Concevoir un système répondant à un cahier des charges. -- Traiter des données. -- Communiquer une analyse ou une démarche scientifique.  - Compétences en humanités, documentation et éducation physique et sportive : -- Travailler, apprendre, évoluer de manière autonome. -- Interagir avec les autres, travailler en équipe. ¿ Traitement numérique des signaux et des images   Cet EC relève de l'unité d'enseignement TDSI (UE54) et contribue aux compétences suivantes :  - Spécifier, modéliser et concevoir les méthodes et algorithmes pour le traitement et la gestion de l'information véhiculée par les signaux et les images (niveau 3)  --- Capacité : Spécifier et réaliser un rendu d'une image et une synthèse d'image 3D. --- Capacité : Concevoir et spécifier une chaine de traitement du signal ou de l'image. --- Capacité : Modéliser des signaux en vue de leurs traitements ou analyses.  --- Connaissance : Fondamentaux du traitement des images (filtrages linéaire/non-linéaire, contours, segmentations, analyse). --- Connaissance : Fondamentaux théoriques et méthodes d'analyse et modélisation des signaux. --- Connaissance : Fondamentaux théorique et méthodes de la théorie de l'estimation, de la décision et de l'apprentissage pour les signaux. --- Connaissance : Initiation aux spécificités de traitements industrielles et médicales.  - Concevoir et réaliser des systèmes électroniques pour l'acquisition, le traitement, la commande et la communication de données (niveau 3)  --- Capacité : Déterminer la technologie d'acquisition adaptée à un contexte par rapport à sa physique ou son environnement. --- Capacité : Concevoir et réaliser des traitements ou commandes sur des systèmes à base de FPGA, DSP ou GPU respectant des con-traintes spécifiques. --- Capacité : Mettre en oeuvre un système d'acquisition (RGB, depth, US, RX).  --- Connaissance : Fondamentaux de l'imagerie optique, RX, US, RGB, de profondeur et la parole. --- Connaissance : Fondamentaux de l'architecture des FPGA, DSP et GPU ainsi que l'optimisation algorithmique adaptée à ces architectures. --- Connaissance : Initiation aux spécificités d'acquisition, transmission et stockage de données industrielles et médicales.  - Concevoir et développer des logiciels haut et bas niveau pour des systèmes (traitement et gestion de l'information) (niveau 3)  --- Capacité : Développer un logiciel de traitement d'image en appliquant une démarche d'ingénieur adaptée au problème. --- Capacité : Développer un traitement utilisant une architecture de calcul spécifique (GPP, FPGA, DSP ou GPU). --- Capacité : Mettre en œuvre des éléments existants afin de résoudre un problème complexe de traitement/analyse/représentation/modélisation de signaux ou d'images.  --- Connaissance : Langages de programmation pour le signal et l'image et leurs utilisations. --- Connaissance : Principes et solutions de réalités virtuelle et augmentée. --- Connaissance : Fondamentaux sur l'utilisation des FPGA, DSP et GPU ainsi que l'optimisation algorithmique adaptée à ces architectures.  De plus, elle nécessite de mobiliser les compétences suivantes :  - Compétences en sciences pour l'ingénieur : -- Analyser un système (ou un problème) réel ou virtuel. -- Exploiter un modèle d'un système réel ou virtuel. -- Mettre en œuvre une démarche expérimentale. -- Concevoir un système répondant à un cahier des charges. -- Traiter des données. -- Communiquer une analyse ou une démarche scientifique.  - Compétences en humanités, documentation et éducation physique et sportive : -- Se connaître, se gérer physiquement et mentalement. -- Travailler, apprendre, évoluer de manière autonome. -- Interagir avec les autres, travailler en équipe. -- Faire preuve de créativité, innover, entreprendre. -- Agir de manière responsable dans un monde complexe. -- Se situer, travailler, évoluer dans une entreprise, une organisation socio-productive. -- Travailler dans un contexte international et interculturel.",
              "capacite": [
                "Capacité : Spécifier et réaliser un rendu d'une image et une synthèse d'image 3D.",
                "Capacité : Concevoir et spécifier une chaine de traitement du signal ou de l'image.",
                "Capacité : Modéliser des signaux en vue de leurs traitements ou analyses.",
                "Capacité : Déterminer la technologie d'acquisition adaptée à un contexte par rapport à sa physique ou son environnement.",
                "Capacité : Concevoir et réaliser des traitements ou commandes sur des systèmes à base de FPGA, DSP ou GPU respectant des con-traintes spécifiques.",
                "Capacité : Mettre en oeuvre un système d'acquisition (RGB, depth, US, RX).",
                "Capacité : Développer un logiciel de traitement d'image en appliquant une démarche d'ingénieur adaptée au problème.",
                "Capacité : Développer un traitement utilisant une architecture de calcul spécifique (GPP, FPGA, DSP ou GPU).",
                "Capacité : Mettre en œuvre des éléments existants afin de résoudre un problème complexe de traitement/analyse/représentation/modélisation de signaux ou d'images."
              ],
              "connaissance": [
                "Connaissance : Fondamentaux du traitement des images (filtrages linéaire/non-linéaire, contours, segmentations, analyse).",
                "Connaissance : Fondamentaux théoriques et méthodes d'analyse et modélisation des signaux.",
                "Connaissance : Fondamentaux théorique et méthodes de la théorie de l'estimation, de la décision et de l'apprentissage pour les signaux.",
                "Connaissance : Initiation aux spécificités de traitements industrielles et médicales.",
                "Connaissance : Fondamentaux de l'imagerie optique, RX, US, RGB, de profondeur et la parole.",
                "Connaissance : Fondamentaux de l'architecture des FPGA, DSP et GPU ainsi que l'optimisation algorithmique adaptée à ces architectures.",
                "Connaissance : Initiation aux spécificités d'acquisition, transmission et stockage de données industrielles et médicales.",
                "Connaissance : Langages de programmation pour le signal et l'image et leurs utilisations.",
                "Connaissance : Principes et solutions de réalités virtuelle et augmentée.",
                "Connaissance : Fondamentaux sur l'utilisation des FPGA, DSP et GPU ainsi que l'optimisation algorithmique adaptée à ces architectures."
              ],
              "competenceToCapaciteEtConnaissance": {
                "GEA-C4": [
                  "Capacité : Spécifier et réaliser un rendu d'une image et une synthèse d'image 3D.",
                  "Capacité : Concevoir et spécifier une chaine de traitement du signal ou de l'image.",
                  "Capacité : Modéliser des signaux en vue de leurs traitements ou analyses.",
                  "Connaissance : Fondamentaux du traitement des images (filtrages linéaire/non-linéaire, contours, segmentations, analyse).",
                  "Connaissance : Fondamentaux théoriques et méthodes d'analyse et modélisation des signaux.",
                  "Connaissance : Fondamentaux théorique et méthodes de la théorie de l'estimation, de la décision et de l'apprentissage pour les signaux.",
                  "Connaissance : Initiation aux spécificités de traitements industrielles et médicales."
                ],
                "GEA-C5": [
                  "Capacité : Déterminer la technologie d'acquisition adaptée à un contexte par rapport à sa physique ou son environnement.",
                  "Capacité : Concevoir et réaliser des traitements ou commandes sur des systèmes à base de FPGA, DSP ou GPU respectant des con-traintes spécifiques.",
                  "Capacité : Mettre en oeuvre un système d'acquisition (RGB, depth, US, RX).",
                  "Connaissance : Fondamentaux de l'imagerie optique, RX, US, RGB, de profondeur et la parole.",
                  "Connaissance : Fondamentaux de l'architecture des FPGA, DSP et GPU ainsi que l'optimisation algorithmique adaptée à ces architectures.",
                  "Connaissance : Initiation aux spécificités d'acquisition, transmission et stockage de données industrielles et médicales."
                ],
                "GEA-C7": [
                  "Capacité : Développer un logiciel de traitement d'image en appliquant une démarche d'ingénieur adaptée au problème.",
                  "Capacité : Développer un traitement utilisant une architecture de calcul spécifique (GPP, FPGA, DSP ou GPU).",
                  "Capacité : Mettre en œuvre des éléments existants afin de résoudre un problème complexe de traitement/analyse/représentation/modélisation de signaux ou d'images.",
                  "Connaissance : Langages de programmation pour le signal et l'image et leurs utilisations.",
                  "Connaissance : Principes et solutions de réalités virtuelle et augmentée.",
                  "Connaissance : Fondamentaux sur l'utilisation des FPGA, DSP et GPU ainsi que l'optimisation algorithmique adaptée à ces architectures."
                ]
              },
              "listeComp": [
                {
                  "code": "C4",
                  "val": "Spécifier, modéliser et concevoir les méthodes et algorithmes pour le traitement et la gestion de l'information véhiculée par les signaux et les images",
                  "valAnglais": "Specify, model and design methods and algorithms for the processing and management of information conveyed by signals and images",
                  "niveau": "3"
                },
                {
                  "code": "C5",
                  "val": "Concevoir et réaliser des systèmes électroniques pour l'acquisition, le traitement, la commande et la communication de données",
                  "valAnglais": "Design and build electronic systems for data acquisition, processing, control and communication",
                  "niveau": "3"
                },
                {
                  "code": "C7",
                  "val": "Concevoir et développer des logiciels haut et bas niveau pour des systèmes (traitement et gestion de l'information)",
                  "valAnglais": "Design and develop high and low level software for systems (information processing and management)",
                  "niveau": "3"
                }
              ],
              "listeCompMobilise": [
                "Analyser un système (ou un problème) réel ou virtuel",
                "Exploiter un modèle d'un système réel ou virtuel",
                "Mettre en œuvre une démarche expérimentale",
                "Concevoir un système répondant à un cahier des charges",
                "Traiter des données",
                "Communiquer une analyse ou une démarche scientifique",
                "Travailler, apprendre, évoluer de manière autonome",
                "Analyser un système (ou un problème) réel ou virtuel",
                "Exploiter un modèle d'un système réel ou virtuel",
                "Mettre en œuvre une démarche expérimentale",
                "Concevoir un système répondant à un cahier des charges",
                "Traiter des données",
                "Communiquer une analyse ou une démarche scientifique",
                "Se connaître, se gérer physiquement et mentalement",
                "Travailler, apprendre, évoluer de manière autonome",
                "Interagir avec les autres, travailler en équipe",
                "Faire preuve de créativité, innover, entreprendre",
                "Agir de manière responsable dans un monde complexe",
                "Se situer, travailler, évoluer dans une entreprise, une organisation socio-productive",
                "Travailler dans un contexte international et interculturel"
              ]
            }
          },
          {
            "UE": "Enseignements Transversaux (GEA-5-UE51)",
            "url": "http://planete.insa-lyon.fr/scolpeda/f/ects?id=38263&_lang=fr",
            "detail": {
              "code": "GE-5-TdSI",
              "ects": "12.0",
              "cours": "94.0 h",
              "td": "46.0 h",
              "tp": "17.0 h",
              "projet": "20.0 h",
              "perso": "80.0 h",
              "nom": "Traitement du Signal : Traitement numérique des signaux et des images",
              "competencesBrutes": "Maîtriser les méthodes de base du traitement numérique du signal et leur mise en œuvre en temps réel avec des DSP et des FPGA. Maîtriser les principales méthodes de traitement de l'information et de l'image naturelle ou synthétique Maitriser les bases théoriques et la connaissance des applications typiques de la modélisation des signaux aléatoires, de la théorie de l'estimation et de la décision.",
              "capacite": [],
              "connaissance": [],
              "competenceToCapaciteEtConnaissance": {}
            }
          },
          {
            "UE": "Enseignements Transversaux (GEA-5-UE51)",
            "url": "http://planete.insa-lyon.fr/scolpeda/f/ects?id=39533&_lang=fr",
            "detail": {
              "code": "GE-5-SEC",
              "ects": "12.0",
              "cours": "100.0 h",
              "td": "70.0 h",
              "tp": "48.0 h",
              "projet": "30.0 h",
              "perso": "100.0 h",
              "nom": "Télécommunications : Systèmes Embarqués Communiquants",
              "competencesBrutes": "Cet EC relève de l'unité d'enseignement de SEC (UE54) et contribue aux compétences suivantes :  - Mettre en œuvre des composants électroniques analogiques et/ou numériques et identifier leur fonction au sein d'un montage (niveau 3)  --- Capacité : Identifier, caractériser et modéliser les différents composants optoélectronique d'une chaine de télécommunication optique. --- Capacité : Identifier, caractériser et modéliser les différents circuits et sous-systèmes RF et numérique d'une chaine radiocoms. --- Capacité : Identifier, caractériser et modéliser les différents types d'antennes intelligentes pour système radio SIMO et MIMO.  --- Connaissance : Composants DSP, composants optoélectroniques. --- Connaissance : CAO Circuits RF, CAO 3D Antennes. --- Connaissance : Couche physique et canal radio. --- Connaissance : Antennes intelligentes. --- Connaissance : Synthèse de fréquences; Amplification de puissance. --- Connaissance : Couche physique et canal radio.  - Spécifier, modéliser et concevoir les méthodes et algorithmes pour le traitement et la gestion de l'information véhiculée par les signaux et les images (niveau 3)  --- Capacité : Mettre en œuvre les principales méthodes de traitement numérique du signal avec des DSP. --- Capacité : Analyser des systèmes de radiocommunications et développement de méthodes de traitement des signaux. --- Capacité : Identifier les différents protocoles des communications et contraintes en énergie dans les réseaux de capteurs.  --- Connaissance : Radiocommunications. --- Connaissance : codage et modulations. --- Connaissance : théorie de l'information. --- Connaissance : Traitement numérique des signaux.  - Concevoir et réaliser des systèmes électroniques pour l'acquisition, le traitement, la commande et la communication de données (niveau 3)  --- Capacité : Concevoir et caractériser des systèmes d'émission-réception de radiocommunications. --- Capacité : Concevoir et caractériser des réseaux de capteurs autonomes en énergie (du hard au soft). --- Capacité : Mettre en œuvre et optimiser des architectures de traitement numérique des signaux à base de DSP.  --- Connaissance : Architecture des émetteur/récepteur radiocoms. --- Connaissance : Architecture des réseaux de communication. --- Connaissance : Réseaux de capteurs, objets connectés. --- Connaissance : Architecture des DSP.  De plus, elle nécessite de mobiliser les compétences suivantes :  - Compétences en sciences pour l'ingénieur : -- Analyser un système (ou un problème) réel ou virtuel. -- Exploiter un modèle d'un système réel ou virtuel. -- Concevoir un système répondant à un cahier des charges.   - Compétences en humanités, documentation et éducation physique et sportive : -- Travailler, apprendre, évoluer de manière autonome. -- Interagir avec les autres, travailler en équipe.",
              "capacite": [
                "Capacité : Identifier, caractériser et modéliser les différents composants optoélectronique d'une chaine de télécommunication optique.",
                "Capacité : Identifier, caractériser et modéliser les différents circuits et sous-systèmes RF et numérique d'une chaine radiocoms.",
                "Capacité : Identifier, caractériser et modéliser les différents types d'antennes intelligentes pour système radio SIMO et MIMO.",
                "Capacité : Mettre en œuvre les principales méthodes de traitement numérique du signal avec des DSP.",
                "Capacité : Analyser des systèmes de radiocommunications et développement de méthodes de traitement des signaux.",
                "Capacité : Identifier les différents protocoles des communications et contraintes en énergie dans les réseaux de capteurs.",
                "Capacité : Concevoir et caractériser des systèmes d'émission-réception de radiocommunications.",
                "Capacité : Concevoir et caractériser des réseaux de capteurs autonomes en énergie (du hard au soft).",
                "Capacité : Mettre en œuvre et optimiser des architectures de traitement numérique des signaux à base de DSP."
              ],
              "connaissance": [
                "Connaissance : Composants DSP, composants optoélectroniques.",
                "Connaissance : CAO Circuits RF, CAO 3D Antennes.",
                "Connaissance : Couche physique et canal radio.",
                "Connaissance : Antennes intelligentes.",
                "Connaissance : Synthèse de fréquences; Amplification de puissance.",
                "Connaissance : Couche physique et canal radio.",
                "Connaissance : Radiocommunications.",
                "Connaissance : codage et modulations.",
                "Connaissance : théorie de l'information.",
                "Connaissance : Traitement numérique des signaux.",
                "Connaissance : Architecture des émetteur/récepteur radiocoms.",
                "Connaissance : Architecture des réseaux de communication.",
                "Connaissance : Réseaux de capteurs, objets connectés.",
                "Connaissance : Architecture des DSP."
              ],
              "competenceToCapaciteEtConnaissance": {
                "GEA-C1": [
                  "Capacité : Identifier, caractériser et modéliser les différents composants optoélectronique d'une chaine de télécommunication optique.",
                  "Capacité : Identifier, caractériser et modéliser les différents circuits et sous-systèmes RF et numérique d'une chaine radiocoms.",
                  "Capacité : Identifier, caractériser et modéliser les différents types d'antennes intelligentes pour système radio SIMO et MIMO.",
                  "Connaissance : Composants DSP, composants optoélectroniques.",
                  "Connaissance : CAO Circuits RF, CAO 3D Antennes.",
                  "Connaissance : Couche physique et canal radio.",
                  "Connaissance : Antennes intelligentes.",
                  "Connaissance : Synthèse de fréquences; Amplification de puissance.",
                  "Connaissance : Couche physique et canal radio."
                ],
                "GEA-C4": [
                  "Capacité : Mettre en œuvre les principales méthodes de traitement numérique du signal avec des DSP.",
                  "Capacité : Analyser des systèmes de radiocommunications et développement de méthodes de traitement des signaux.",
                  "Capacité : Identifier les différents protocoles des communications et contraintes en énergie dans les réseaux de capteurs.",
                  "Connaissance : Radiocommunications.",
                  "Connaissance : codage et modulations.",
                  "Connaissance : théorie de l'information.",
                  "Connaissance : Traitement numérique des signaux."
                ],
                "GEA-C5": [
                  "Capacité : Concevoir et caractériser des systèmes d'émission-réception de radiocommunications.",
                  "Capacité : Concevoir et caractériser des réseaux de capteurs autonomes en énergie (du hard au soft).",
                  "Capacité : Mettre en œuvre et optimiser des architectures de traitement numérique des signaux à base de DSP.",
                  "Connaissance : Architecture des émetteur/récepteur radiocoms.",
                  "Connaissance : Architecture des réseaux de communication.",
                  "Connaissance : Réseaux de capteurs, objets connectés.",
                  "Connaissance : Architecture des DSP."
                ]
              },
              "listeComp": [
                {
                  "code": "C1",
                  "val": "Mettre en œuvre des composants électroniques analogiques et/ou numériques et identifier leur fonction au sein d'un montage",
                  "valAnglais": "Implement analog and / or digital electronic components and identify their function within an assembly",
                  "niveau": "3"
                },
                {
                  "code": "C4",
                  "val": "Spécifier, modéliser et concevoir les méthodes et algorithmes pour le traitement et la gestion de l'information véhiculée par les signaux et les images",
                  "valAnglais": "Specify, model and design methods and algorithms for the processing and management of information conveyed by signals and images",
                  "niveau": "3"
                },
                {
                  "code": "C5",
                  "val": "Concevoir et réaliser des systèmes électroniques pour l'acquisition, le traitement, la commande et la communication de données",
                  "valAnglais": "Design and build electronic systems for data acquisition, processing, control and communication",
                  "niveau": "3"
                }
              ],
              "listeCompMobilise": [
                "Analyser un système (ou un problème) réel ou virtuel",
                "Exploiter un modèle d'un système réel ou virtuel",
                "Concevoir un système répondant à un cahier des charges",
                "Travailler, apprendre, évoluer de manière autonome",
                "Interagir avec les autres, travailler en équipe"
              ]
            }
          },
          {
            "UE": "Enseignements Transversaux (GEA-5-UE51)",
            "url": "http://planete.insa-lyon.fr/scolpeda/f/ects?id=37989&_lang=fr",
            "detail": {
              "code": "GE-5-REEL",
              "ects": "12.0",
              "cours": "119.0 h",
              "td": "40.0 h",
              "tp": "28.0 h",
              "projet": "30.0 h",
              "perso": "100.0 h",
              "nom": "Réseaux : REseaux ELectriques",
              "competencesBrutes": "Réseaux Electriques  Cet EC relève de l'unité d'enseignement de REEL (UE54) et contribue aux compétences suivantes :  - Mettre en œuvre les différents éléments de production d'énergie, de transport d'énergie électrique et de conversion d'énergie (niveau 3)  -- Sous compétence : La topologie et la modélisation des réseaux  --- Capacité : Décrire les relations qui relient les grandeurs électriques, du générateur, celles de la ligne et du récepteur afin de déterminer les réglages qui vont définir le fonctionnement de l'ensemble. --- Capacité : Etablir les matrices de réseau à partir d'une topologie définie et réaliser un calcul de répartition de charges à l'aide d'un phaseur. --- Capacité : Identifier les problèmes de transit (congestion, chute de tension) sur un réseau électrique et les corriger.  --- Connaissance : Connaître les facteurs de développement historiques des réseaux électriques (guerre des courants, ouverture des marchés, ... --- Connaissance : Connaître l'architecture et la topologie des réseaux électriques AC (transport, répartition, distribution). --- Connaissance : Connaître les concepts de valeurs réduites.  - Mettre en œuvre les différents éléments de production d'énergie, de transport d'énergie électrique et de conversion d'énergie (niveau 3)  -- Sous compétence : Mettre en œuvre un réseau de distribution d'énergie électrique  --- Capacité : Lire et expliquer un schéma unifilaire d'un réseau de distribution industriel. --- Capacité : Evaluer les seuils de réglages d'une protection, ampérométrique, wattmétrique ou distante. --- Capacité : Traiter des systèmes déséquilibrés à l'aide de la modélisation adaptée.  --- Connaissance : Connaître l'impact des sources de production décentralisées sur le réseau de distribution. --- Connaissance : Connaître les règles d'interconnexion (Grid Code) des sources de productions distribuées (éolien, PV). --- Connaissance : Connaître les concepts de puissance de court-circuit.  - Mettre en œuvre les étapes permettant le contrôle du fonctionnement d'un système discret ou continu (niveau 3)  -- Sous compétence : L'exploitation et la conduite des réseaux  --- Capacité : Réaliser l'étude de stabilité d'un réseau (cascade de charge, perte de synchronisme, ...). --- Capacité : Identifier des parades permettant de limiter les risques de congestion et de blackout. --- Capacité : Identifier les flux physiques et financier entre les différents acteurs du système électrique. --- Capacité : Réaliser la synthèse des régulateurs tension/fréquence d'une génératrice synchrone. --- Capacité : Réaliser la synthèse des régulateurs P/Q d'un FACTS. --- Capacité : Réaliser une étude en simulation de type EMT (transitoire électro magnétique).   --- Connaissance : Connaître la dynamique des moyens de production et l'approche économique de l'exploitation. --- Connaissance : Connaître les mécanismes de planification et les mécanismes d'ajustement de la production en lien avec les mécanismes marché de l'électricité. --- Connaissance : Connaître les acteurs institutionnels et privés du système électrique. --- Connaissance : Connaître l'intérêt et la topologie des systèmes qui apportent de la flexibilité (FACTS, STEP, liaison continue). --- Connaissance : Connaître le principe des régalages primaires, secondaires et tertiaires de tension/fréquence. --- Connaissance : Connaître les lois de commande des convertisseurs de type VSC et LCC. --- Connaissance : Connaître les lois de commande des systèmes flexibles de transport et de distribution.  De plus, elle nécessite de mobiliser les compétences suivantes :  - Compétences en sciences pour l'ingénieur : -- Mettre en œuvre les étapes permettant le contrôle du fonctionnement d'un système discret ou continu. -- Analyser un système (ou un problème) réel ou virtuel. -- Exploiter un modèle d'un système réel ou virtuel. -- Mettre en œuvre une démarche expérimentale. -- Concevoir un système r��pondant à un cahier des charges. -- Traiter des données. -- Communiquer une analyse ou une démarche scientifique.  - Compétences en humanités, documentation et éducation physique et sportive : -- Se connaître, se gérer physiquement et mentalement. -- Travailler, apprendre, évoluer de manière autonome. -- Interagir avec les autres, travailler en équipe. -- Faire preuve de créativité, innover, entreprendre. -- Agir de manière responsable dans un monde complexe. -- Se situer, travailler, évoluer dans une entreprise, une organisation socio-productive. -- Travailler dans un contexte international et interculturel.",
              "capacite": [
                "Capacité : Décrire les relations qui relient les grandeurs électriques, du générateur, celles de la ligne et du récepteur afin de déterminer les réglages qui vont définir le fonctionnement de l'ensemble.",
                "Capacité : Etablir les matrices de réseau à partir d'une topologie définie et réaliser un calcul de répartition de charges à l'aide d'un phaseur.",
                "Capacité : Identifier les problèmes de transit (congestion, chute de tension) sur un réseau électrique et les corriger.",
                "Capacité : Lire et expliquer un schéma unifilaire d'un réseau de distribution industriel.",
                "Capacité : Evaluer les seuils de réglages d'une protection, ampérométrique, wattmétrique ou distante.",
                "Capacité : Traiter des systèmes déséquilibrés à l'aide de la modélisation adaptée.",
                "Capacité : Réaliser l'étude de stabilité d'un réseau (cascade de charge, perte de synchronisme, ...).",
                "Capacité : Identifier des parades permettant de limiter les risques de congestion et de blackout.",
                "Capacité : Identifier les flux physiques et financier entre les différents acteurs du système électrique.",
                "Capacité : Réaliser la synthèse des régulateurs tension/fréquence d'une génératrice synchrone.",
                "Capacité : Réaliser la synthèse des régulateurs P/Q d'un FACTS.",
                "Capacité : Réaliser une étude en simulation de type EMT (transitoire électro magnétique)."
              ],
              "connaissance": [
                "Connaissance : Connaître les facteurs de développement historiques des réseaux électriques (guerre des courants, ouverture des marchés, ...",
                "Connaissance : Connaître l'architecture et la topologie des réseaux électriques AC (transport, répartition, distribution).",
                "Connaissance : Connaître les concepts de valeurs réduites.",
                "Connaissance : Connaître l'impact des sources de production décentralisées sur le réseau de distribution.",
                "Connaissance : Connaître les règles d'interconnexion (Grid Code) des sources de productions distribuées (éolien, PV).",
                "Connaissance : Connaître les concepts de puissance de court-circuit.",
                "Connaissance : Connaître la dynamique des moyens de production et l'approche économique de l'exploitation.",
                "Connaissance : Connaître les mécanismes de planification et les mécanismes d'ajustement de la production en lien avec les mécanismes marché de l'électricité.",
                "Connaissance : Connaître les acteurs institutionnels et privés du système électrique.",
                "Connaissance : Connaître l'intérêt et la topologie des systèmes qui apportent de la flexibilité (FACTS, STEP, liaison continue).",
                "Connaissance : Connaître le principe des régalages primaires, secondaires et tertiaires de tension/fréquence.",
                "Connaissance : Connaître les lois de commande des convertisseurs de type VSC et LCC.",
                "Connaissance : Connaître les lois de commande des systèmes flexibles de transport et de distribution."
              ],
              "competenceToCapaciteEtConnaissance": {
                "GEA-C3": [
                  "Capacité : Décrire les relations qui relient les grandeurs électriques, du générateur, celles de la ligne et du récepteur afin de déterminer les réglages qui vont définir le fonctionnement de l'ensemble.",
                  "Capacité : Etablir les matrices de réseau à partir d'une topologie définie et réaliser un calcul de répartition de charges à l'aide d'un phaseur.",
                  "Capacité : Identifier les problèmes de transit (congestion, chute de tension) sur un réseau électrique et les corriger.",
                  "Connaissance : Connaître les facteurs de développement historiques des réseaux électriques (guerre des courants, ouverture des marchés, ...",
                  "Connaissance : Connaître l'architecture et la topologie des réseaux électriques AC (transport, répartition, distribution).",
                  "Connaissance : Connaître les concepts de valeurs réduites.",
                  "Capacité : Lire et expliquer un schéma unifilaire d'un réseau de distribution industriel.",
                  "Capacité : Evaluer les seuils de réglages d'une protection, ampérométrique, wattmétrique ou distante.",
                  "Capacité : Traiter des systèmes déséquilibrés à l'aide de la modélisation adaptée.",
                  "Connaissance : Connaître l'impact des sources de production décentralisées sur le réseau de distribution.",
                  "Connaissance : Connaître les règles d'interconnexion (Grid Code) des sources de productions distribuées (éolien, PV).",
                  "Connaissance : Connaître les concepts de puissance de court-circuit."
                ],
                "GEA-C6": [
                  "Capacité : Réaliser l'étude de stabilité d'un réseau (cascade de charge, perte de synchronisme, ...).",
                  "Capacité : Identifier des parades permettant de limiter les risques de congestion et de blackout.",
                  "Capacité : Identifier les flux physiques et financier entre les différents acteurs du système électrique.",
                  "Capacité : Réaliser la synthèse des régulateurs tension/fréquence d'une génératrice synchrone.",
                  "Capacité : Réaliser la synthèse des régulateurs P/Q d'un FACTS.",
                  "Capacité : Réaliser une étude en simulation de type EMT (transitoire électro magnétique).",
                  "Connaissance : Connaître la dynamique des moyens de production et l'approche économique de l'exploitation.",
                  "Connaissance : Connaître les mécanismes de planification et les mécanismes d'ajustement de la production en lien avec les mécanismes marché de l'électricité.",
                  "Connaissance : Connaître les acteurs institutionnels et privés du système électrique.",
                  "Connaissance : Connaître l'intérêt et la topologie des systèmes qui apportent de la flexibilité (FACTS, STEP, liaison continue).",
                  "Connaissance : Connaître le principe des régalages primaires, secondaires et tertiaires de tension/fréquence.",
                  "Connaissance : Connaître les lois de commande des convertisseurs de type VSC et LCC.",
                  "Connaissance : Connaître les lois de commande des systèmes flexibles de transport et de distribution."
                ]
              },
              "listeComp": [
                {
                  "code": "C3",
                  "val": "Mettre en œuvre les différents éléments de production d'énergie, de transport d'énergie électrique et de conversion d'énergie",
                  "valAnglais": "Implement the various elements of energy production, transport of electrical energy and energy conversion",
                  "niveau": "3"
                },
                {
                  "code": "C3",
                  "val": "Mettre en œuvre les différents éléments de production d'énergie, de transport d'énergie électrique et de conversion d'énergie",
                  "valAnglais": "Implement the various elements of energy production, transport of electrical energy and energy conversion",
                  "niveau": "3"
                },
                {
                  "code": "C6",
                  "val": "Mettre en œuvre les étapes permettant le contrôle du fonctionnement d'un système discret ou continu",
                  "valAnglais": "Implement steps to control the operation of a discrete or continuous system",
                  "niveau": "3"
                }
              ],
              "listeCompMobilise": [
                "Mettre en œuvre les étapes permettant le contrôle du fonctionnement d'un système discret ou continu",
                "Analyser un système (ou un problème) réel ou virtuel",
                "Exploiter un modèle d'un système réel ou virtuel",
                "Mettre en œuvre une démarche expérimentale",
                "Traiter des données",
                "Communiquer une analyse ou une démarche scientifique",
                "Se connaître, se gérer physiquement et mentalement",
                "Travailler, apprendre, évoluer de manière autonome",
                "Interagir avec les autres, travailler en équipe",
                "Faire preuve de créativité, innover, entreprendre",
                "Agir de manière responsable dans un monde complexe",
                "Se situer, travailler, évoluer dans une entreprise, une organisation socio-productive",
                "Travailler dans un contexte international et interculturel"
              ]
            }
          },
          {
            "UE": "Environnement - Qualité - Sécurité (GEA-5-UE52)",
            "url": "http://planete.insa-lyon.fr/scolpeda/f/ects?id=37824&_lang=fr",
            "detail": {
              "code": "GEA-5-SHS5",
              "ects": "2.0",
              "cours": "0.0 h",
              "td": "32.0 h",
              "tp": "0.0 h",
              "projet": "0.0 h",
              "perso": "0.0 h",
              "nom": "Sciences Humaines et Sociales : Environnement - Qualité - Sécurité",
              "competencesBrutes": "Cet EC relève de l'unité d'enseignement  (UE52) et contribue aux compétences suivantes :  -- Agir de manière responsable dans un monde complexe (niveau 2)  --- Capacité : Savoir maîtriser les risques liés à l'environnement --- Capacité : Mettre en évidence les contraintes réglementaires liées à la Sécurité au Travail et leurs conséquences pour l'employeur  --- Connaissance : Le rôle des Managers dans le déploiement et l'animation des référentiels --- Connaissance : Les grands principes liés à la qualité / les riques / la préventionprévention --- Connaissance : Méthodologie et déploiement de l'analyse des risques  -- Se situer, travailler, évoluer dans une entreprise, une organisation socio-productive (niveau 1)  --- Capacité : Être informé sur la législation environnementale --- Capacité : Etre en mesure d'être un relai et pilote efficace pour le SMQSEEn de l'entreprise. --- Capacité : Acquérir des réflexes pour intégrer l'Analyse de Risque au quotidien dans l'entreprise. --- Capacité : Mettre en évidence ce qui est attendu des managers dans le cadre du pilotage des Systèmes de management d'Entreprise QSE --- Capacité : Acquérir des réflexes pour intégrer l'Analyse de Risque au quotidien dans l'entreprise. --- Capacité : Acquérir des réflexes pour intégrer l'Analyse de Risque au quotidien dans l'entreprise. --- Capacité : Acquérir des réflexes pour intégrer l'Analyse de Risque au quotidien dans l'entreprise. --- Capacité : Comprendre les enjeux et impératifs du développement durable : --- Capacité : Identifier l'impact d'une démarche de développement durable sur le fonctionnement de l'entreprise et intégrer les problématiques environnementales dans la conception de produits --- Capacité : Mettre en évidence les contraintes réglementaires liées à la Sécurité au Travail et leurs conséquences --- Capacité : Être informé sur la législation environnementale, apprendre à maîtriser les risques liés à l'environnement. --- Capacité : Acquérir des réflexes pour intégrer l'Analyse de Risque au quotidien dans l'entreprise. --- Capacité : Acquérir des réflexes pour intégrer l'Analyse de Risque au quotidien dans l'entreprise.  --- Connaissance : Le SMQSEEn (Système de Management Qualité Sécurité Environnement Energie) --- Connaissance : Le Système de Management de l'Entreprise et les référentiels associés --- Connaissance : Socle réglementaire et légal SST, responsabilité de l'employeur, les acteurs SST --- Connaissance : Le rôle des Managers dans le déploiement es différentes démarches,  et leurs animations  De plus, elle nécessite de mobiliser les compétences suivantes :  -- Interagir avec les autres, travailler en équipe -- Faire preuve de créativité, innover, entreprendre -- Travailler dans un contexte international et interculturel",
              "capacite": [
                "Capacité : Savoir maîtriser les risques liés à l'environnement",
                "Capacité : Mettre en évidence les contraintes réglementaires liées à la Sécurité au Travail et leurs conséquences pour l'employeur",
                "Capacité : Être informé sur la législation environnementale",
                "Capacité : Etre en mesure d'être un relai et pilote efficace pour le SMQSEEn de l'entreprise.",
                "Capacité : Acquérir des réflexes pour intégrer l'Analyse de Risque au quotidien dans l'entreprise.",
                "Capacité : Mettre en évidence ce qui est attendu des managers dans le cadre du pilotage des Systèmes de management d'Entreprise QSE",
                "Capacité : Acquérir des réflexes pour intégrer l'Analyse de Risque au quotidien dans l'entreprise.",
                "Capacité : Acquérir des réflexes pour intégrer l'Analyse de Risque au quotidien dans l'entreprise.",
                "Capacité : Acquérir des réflexes pour intégrer l'Analyse de Risque au quotidien dans l'entreprise.",
                "Capacité : Comprendre les enjeux et impératifs du développement durable :",
                "Capacité : Identifier l'impact d'une démarche de développement durable sur le fonctionnement de l'entreprise et intégrer les problématiques environnementales dans la conception de produits",
                "Capacité : Mettre en évidence les contraintes réglementaires liées à la Sécurité au Travail et leurs conséquences",
                "Capacité : Être informé sur la législation environnementale, apprendre à maîtriser les risques liés à l'environnement.",
                "Capacité : Acquérir des réflexes pour intégrer l'Analyse de Risque au quotidien dans l'entreprise.",
                "Capacité : Acquérir des réflexes pour intégrer l'Analyse de Risque au quotidien dans l'entreprise."
              ],
              "connaissance": [
                "Connaissance : Le rôle des Managers dans le déploiement et l'animation des référentiels",
                "Connaissance : Les grands principes liés à la qualité / les riques / la préventionprévention",
                "Connaissance : Méthodologie et déploiement de l'analyse des risques  -- Se situer, travailler, évoluer dans une entreprise, une organisation socio-productive (niveau 1)",
                "Connaissance : Le SMQSEEn (Système de Management Qualité Sécurité Environnement Energie)",
                "Connaissance : Le Système de Management de l'Entreprise et les référentiels associés",
                "Connaissance : Socle réglementaire et légal SST, responsabilité de l'employeur, les acteurs SST",
                "Connaissance : Le rôle des Managers dans le déploiement es différentes démarches,  et leurs animations"
              ],
              "competenceToCapaciteEtConnaissance": {
                "B5": [
                  "Capacité : Savoir maîtriser les risques liés à l'environnement",
                  "Capacité : Mettre en évidence les contraintes réglementaires liées à la Sécurité au Travail et leurs conséquences pour l'employeur",
                  "Connaissance : Le rôle des Managers dans le déploiement et l'animation des référentiels",
                  "Connaissance : Les grands principes liés à la qualité / les riques / la préventionprévention",
                  "Connaissance : Méthodologie et déploiement de l'analyse des risques  -- Se situer, travailler, évoluer dans une entreprise, une organisation socio-productive (niveau 1)",
                  "Capacité : Être informé sur la législation environnementale",
                  "Capacité : Etre en mesure d'être un relai et pilote efficace pour le SMQSEEn de l'entreprise.",
                  "Capacité : Acquérir des réflexes pour intégrer l'Analyse de Risque au quotidien dans l'entreprise.",
                  "Capacité : Mettre en évidence ce qui est attendu des managers dans le cadre du pilotage des Systèmes de management d'Entreprise QSE",
                  "Capacité : Acquérir des réflexes pour intégrer l'Analyse de Risque au quotidien dans l'entreprise.",
                  "Capacité : Acquérir des réflexes pour intégrer l'Analyse de Risque au quotidien dans l'entreprise.",
                  "Capacité : Acquérir des réflexes pour intégrer l'Analyse de Risque au quotidien dans l'entreprise.",
                  "Capacité : Comprendre les enjeux et impératifs du développement durable :",
                  "Capacité : Identifier l'impact d'une démarche de développement durable sur le fonctionnement de l'entreprise et intégrer les problématiques environnementales dans la conception de produits",
                  "Capacité : Mettre en évidence les contraintes réglementaires liées à la Sécurité au Travail et leurs conséquences",
                  "Capacité : Être informé sur la législation environnementale, apprendre à maîtriser les risques liés à l'environnement.",
                  "Capacité : Acquérir des réflexes pour intégrer l'Analyse de Risque au quotidien dans l'entreprise.",
                  "Capacité : Acquérir des réflexes pour intégrer l'Analyse de Risque au quotidien dans l'entreprise.",
                  "Connaissance : Le SMQSEEn (Système de Management Qualité Sécurité Environnement Energie)",
                  "Connaissance : Le Système de Management de l'Entreprise et les référentiels associés",
                  "Connaissance : Socle réglementaire et légal SST, responsabilité de l'employeur, les acteurs SST",
                  "Connaissance : Le rôle des Managers dans le déploiement es différentes démarches,  et leurs animations"
                ]
              },
              "listeComp": [
                {
                  "code": "B5",
                  "val": "Agir de manière responsable dans un monde complexe",
                  "valAnglais": "Act responsibly in a complex world",
                  "bs": "27",
                  "niveau": "2"
                }
              ],
              "listeCompMobilise": [
                "Interagir avec les autres, travailler en équipe",
                "Faire preuve de créativité, innover, entreprendre",
                "Travailler dans un contexte international et interculturel"
              ]
            }
          },
          {
            "UE": "Environnement - Qualité - Sécurité (GEA-5-UE52)",
            "url": "http://planete.insa-lyon.fr/scolpeda/f/ects?id=37825&_lang=fr",
            "detail": {
              "code": "GEA-5-LA5",
              "ects": "2.0",
              "cours": "0.0 h",
              "td": "36.0 h",
              "tp": "0.0 h",
              "projet": "0.0 h",
              "perso": "0.0 h",
              "nom": "Langues Étrangères : Communication professionnelle",
              "competencesBrutes": "Cet EC relève de l'unité d'enseignement  (UE52) et contribue aux compétences suivantes :  -- Interagir avec les autres, travailler en équipe (niveau 2)  --- Capacité : S'exprimer de façon claire et détaillée sur une grande quantité de sujets, d'émettre un avis sur un sujet d'actualité et exposer les avantages et les inconvénients de différentes solutions  -- Travailler dans un contexte international et interculturel (niveau 2)  --- Capacité : S'exprimer de façon claire et détaillée sur une grande quantité de sujets, d'émettre un avis sur un sujet d'actualité et exposer les avantages et les inconvénients de différentes solutions. --- Capacité : S'exprimer de façon claire et détaillée sur une grande quantité de sujets, d'émettre un avis sur un sujet d'actualité et exposer les avantages et les inconvénients de différentes solutions --- Capacité : Communiquer avec un degré de spontanéité et d'aisance tel qu'une conversation avec un interlocuteur natif --- Capacité : Obtenir le score minimum de 785 au TOEIC --- Capacité : S'exprimer sur des sujets complexes de façon claire et bien structurée et de manifester votre contrôle des outils d'organisation, d'articulation et de cohésion du discours --- Capacité : Utiliser la langue de façon efficace et souple dans sa vie sociale, professionnelle ou académique  --- Connaissance : Lexique, syntaxe, grammaire --- Connaissance : Expression orale --- Connaissance : compréhension orale et écrite --- Connaissance : Les différences culturelles et organisationnelles impactant les relations professionnelles. --- Connaissance : Rédaction CV et lettre de motivation  De plus, elle nécessite de mobiliser les compétences suivantes :  -- Communiquer une analyse ou une démarche scientifique -- Travailler, apprendre, évoluer de manière autonome",
              "capacite": [
                "Capacité : S'exprimer de façon claire et détaillée sur une grande quantité de sujets, d'émettre un avis sur un sujet d'actualité et exposer les avantages et les inconvénients de différentes solutions  -- Travailler dans un contexte international et interculturel (niveau 2)",
                "Capacité : S'exprimer de façon claire et détaillée sur une grande quantité de sujets, d'émettre un avis sur un sujet d'actualité et exposer les avantages et les inconvénients de différentes solutions.",
                "Capacité : S'exprimer de façon claire et détaillée sur une grande quantité de sujets, d'émettre un avis sur un sujet d'actualité et exposer les avantages et les inconvénients de différentes solutions",
                "Capacité : Communiquer avec un degré de spontanéité et d'aisance tel qu'une conversation avec un interlocuteur natif",
                "Capacité : Obtenir le score minimum de 785 au TOEIC",
                "Capacité : S'exprimer sur des sujets complexes de façon claire et bien structurée et de manifester votre contrôle des outils d'organisation, d'articulation et de cohésion du discours",
                "Capacité : Utiliser la langue de façon efficace et souple dans sa vie sociale, professionnelle ou académique"
              ],
              "connaissance": [
                "Connaissance : Lexique, syntaxe, grammaire",
                "Connaissance : Expression orale",
                "Connaissance : compréhension orale et écrite",
                "Connaissance : Les différences culturelles et organisationnelles impactant les relations professionnelles.",
                "Connaissance : Rédaction CV et lettre de motivation"
              ],
              "competenceToCapaciteEtConnaissance": {
                "B3": [
                  "Capacité : S'exprimer de façon claire et détaillée sur une grande quantité de sujets, d'émettre un avis sur un sujet d'actualité et exposer les avantages et les inconvénients de différentes solutions  -- Travailler dans un contexte international et interculturel (niveau 2)",
                  "Capacité : S'exprimer de façon claire et détaillée sur une grande quantité de sujets, d'émettre un avis sur un sujet d'actualité et exposer les avantages et les inconvénients de différentes solutions.",
                  "Capacité : S'exprimer de façon claire et détaillée sur une grande quantité de sujets, d'émettre un avis sur un sujet d'actualité et exposer les avantages et les inconvénients de différentes solutions",
                  "Capacité : Communiquer avec un degré de spontanéité et d'aisance tel qu'une conversation avec un interlocuteur natif",
                  "Capacité : Obtenir le score minimum de 785 au TOEIC",
                  "Capacité : S'exprimer sur des sujets complexes de façon claire et bien structurée et de manifester votre contrôle des outils d'organisation, d'articulation et de cohésion du discours",
                  "Capacité : Utiliser la langue de façon efficace et souple dans sa vie sociale, professionnelle ou académique",
                  "Connaissance : Lexique, syntaxe, grammaire",
                  "Connaissance : Expression orale",
                  "Connaissance : compréhension orale et écrite",
                  "Connaissance : Les différences culturelles et organisationnelles impactant les relations professionnelles.",
                  "Connaissance : Rédaction CV et lettre de motivation"
                ]
              },
              "listeComp": [
                {
                  "code": "B3",
                  "val": "Interagir avec les autres, travailler en équipe",
                  "valAnglais": "Interact with people and work in a team",
                  "bs": "25",
                  "niveau": "2"
                }
              ],
              "listeCompMobilise": [
                "Communiquer une analyse ou une démarche scientifique",
                "Travailler, apprendre, évoluer de manière autonome"
              ]
            }
          },
          {
            "UE": "Environnement - Qualité - Sécurité (GEA-5-UE52)",
            "url": "http://planete.insa-lyon.fr/scolpeda/f/ects?id=37826&_lang=fr",
            "detail": {
              "code": "GEA-5-EPS5",
              "ects": "1.0",
              "cours": "0.0 h",
              "td": "30.0 h",
              "tp": "0.0 h",
              "projet": "0.0 h",
              "perso": "0.0 h",
              "nom": "Education Physique et Sportive : Education Physique et Sportive",
              "competencesBrutes": "Apprendre à dépasser ses limites en faisant confiance à son partenaire au travers d'une activité sportive à risque.",
              "capacite": [],
              "connaissance": [],
              "competenceToCapaciteEtConnaissance": {}
            }
          },
          {
            "UE": "Projet Fin d'Etude 1 (GEA-5-UE53)",
            "url": "http://planete.insa-lyon.fr/scolpeda/f/ects?id=37827&_lang=fr",
            "detail": {
              "code": "GEA-5-PFE1",
              "ects": "11.0",
              "cours": "0.0 h",
              "td": "2.0 h",
              "tp": "0.0 h",
              "projet": "0.0 h",
              "perso": "400.0 h",
              "nom": "Projets de fin d'études : Projet Fin d'Etude 1",
              "competencesBrutes": "Cet EC relève de l'unité d'enseignement  (UE53) et contribue aux compétences suivantes :  -- Se situer, travailler, évoluer dans une entreprise, une organisation socio-productive (niveau 2)  --- Capacité : Etre capable de travailler avec différents services ou sur plusieurs affaires en respectant l'organisation, les délais et les contraintes de chacun. --- Capacité : Etre capable de chiffrer /budgeter/estimer les coûts en autonomie  -- Travailler, apprendre, évoluer de manière autonome (niveau 2)  --- Capacité : Pilotage d'un projet en autonomie avec réalisation du découpage en sous tâche et élaboration d'un Gantt.  -- Interagir avec les autres, travailler en équipe (niveau )  --- Capacité : Etre capable d'animer une réunion en autonomie --- Capacité : Savoir mobiliser les acteurs pour faire aboutir son projet  - Mettre en œuvre ses compétences scientifiques et technologiques dans le domaine de l'EEAIIT dans un cadre industriel et appliqué à des problématiques réelles en conduisant les étapes du cycle de conception (niveau )  --- Capacité : Etre capable de concevoir ou mettre en oeuvre un système électrique en comprenant les enjeux de l'installation complète. --- Capacité : Intégrer les besoins des autres corps d'ingéniérie. --- Capacité : Participer à la mise en œuvre complète du cycle en V",
              "capacite": [
                "Capacité : Etre capable de travailler avec différents services ou sur plusieurs affaires en respectant l'organisation, les délais et les contraintes de chacun.",
                "Capacité : Etre capable de chiffrer /budgeter/estimer les coûts en autonomie  -- Travailler, apprendre, évoluer de manière autonome (niveau 2)",
                "Capacité : Pilotage d'un projet en autonomie avec réalisation du découpage en sous tâche et élaboration d'un Gantt.  -- Interagir avec les autres, travailler en équipe (niveau )",
                "Capacité : Etre capable d'animer une réunion en autonomie",
                "Capacité : Savoir mobiliser les acteurs pour faire aboutir son projet",
                "Capacité : Etre capable de concevoir ou mettre en oeuvre un système électrique en comprenant les enjeux de l'installation complète.",
                "Capacité : Intégrer les besoins des autres corps d'ingéniérie.",
                "Capacité : Participer à la mise en œuvre complète du cycle en V"
              ],
              "connaissance": [],
              "competenceToCapaciteEtConnaissance": {
                "B6": [
                  "Capacité : Etre capable de travailler avec différents services ou sur plusieurs affaires en respectant l'organisation, les délais et les contraintes de chacun.",
                  "Capacité : Etre capable de chiffrer /budgeter/estimer les coûts en autonomie  -- Travailler, apprendre, évoluer de manière autonome (niveau 2)",
                  "Capacité : Pilotage d'un projet en autonomie avec réalisation du découpage en sous tâche et élaboration d'un Gantt.  -- Interagir avec les autres, travailler en équipe (niveau )",
                  "Capacité : Etre capable d'animer une réunion en autonomie",
                  "Capacité : Savoir mobiliser les acteurs pour faire aboutir son projet"
                ],
                "GEA-C9": [
                  "Capacité : Etre capable de concevoir ou mettre en oeuvre un système électrique en comprenant les enjeux de l'installation complète.",
                  "Capacité : Intégrer les besoins des autres corps d'ingéniérie.",
                  "Capacité : Participer à la mise en œuvre complète du cycle en V"
                ]
              },
              "listeComp": [
                {
                  "code": "B6",
                  "val": "Se situer, travailler, évoluer dans une entreprise, une organisation socio-productive",
                  "valAnglais": "Position oneself, work, and evolve within a company or a socio-productive organization",
                  "bs": "28",
                  "niveau": "2"
                },
                {
                  "code": "C9",
                  "val": "Mettre en œuvre ses compétences scientifiques et technologiques dans le domaine de l'EEAIIT dans un cadre industriel et appliqué à des problématiques réelles en conduisant les étapes du cycle de conception",
                  "valAnglais": "Apply scientific and technological competences in the field of the EEAIIT in an industrial framework and to real problems by leading the stages of the cycle of conception",
                  "niveau": ""
                }
              ]
            }
          }
        ]
      },
      {
        "url": "/fr/formation/parcours/1165/5/2",
        "ecs": [
          {
            "UE": "Mission à l'Etranger (GEA-5-UE54)",
            "url": "http://planete.insa-lyon.fr/scolpeda/f/ects?id=37828&_lang=fr",
            "detail": {
              "code": "GEA-5-MET",
              "ects": "10.0",
              "cours": "0.0 h",
              "td": "300.0 h",
              "tp": "0.0 h",
              "projet": "0.0 h",
              "perso": "0.0 h",
              "nom": "Mobilitité Internationnale des Etudiants : Mission à l'Etranger",
              "competencesBrutes": "Cet EC relève de l'unité d'enseignement  (UE54) et contribue aux compétences suivantes :  -- Travailler dans un contexte international et interculturel (niveau 2)  --- Capacité : S'intégrer dans un environnement socio-économique nouveau --- Capacité : S'approprier les enjeux économiques internationaux --- Capacité : Communiquer dans une langue étrangère  --- Connaissance : Organisation d'un milieu professionnel étranger --- Connaissance : Contexte économique mondial  -- Travailler, apprendre, évoluer de manière autonome (niveau 2)  --- Capacité : Gérer son temps et son projet --- Capacité : Analyser et rédiger des documents professionnels --- Capacité : Construire et argumenter une candidature --- Capacité : S'intégrer dans une équipe, contribuer à l'animer, à l'organiser et à la faire évoluer --- Capacité : Utiliser les différents moyens de communication au sein de l'entreprise en s'adaptant à son interlocuteur --- Capacité : Exposer efficacement un travail à l'écrit et à l'oral dans une langue étrangère ; s'adapter à l'auditoire  --- Connaissance : Recherche de stage --- Connaissance : Démarche projet --- Connaissance : Compétences métier --- Connaissance : Relations humaines, communication  De plus, elle nécessite de mobiliser les compétences suivantes :  -- Interagir avec les autres, travailler en équipe",
              "capacite": [
                "Capacité : S'intégrer dans un environnement socio-économique nouveau",
                "Capacité : S'approprier les enjeux économiques internationaux",
                "Capacité : Communiquer dans une langue étrangère",
                "Capacité : Gérer son temps et son projet",
                "Capacité : Analyser et rédiger des documents professionnels",
                "Capacité : Construire et argumenter une candidature",
                "Capacité : S'intégrer dans une équipe, contribuer à l'animer, à l'organiser et à la faire évoluer",
                "Capacité : Utiliser les différents moyens de communication au sein de l'entreprise en s'adaptant à son interlocuteur",
                "Capacité : Exposer efficacement un travail à l'écrit et à l'oral dans une langue étrangère ; s'adapter à l'auditoire"
              ],
              "connaissance": [
                "Connaissance : Organisation d'un milieu professionnel étranger",
                "Connaissance : Contexte économique mondial  -- Travailler, apprendre, évoluer de manière autonome (niveau 2)",
                "Connaissance : Recherche de stage",
                "Connaissance : Démarche projet",
                "Connaissance : Compétences métier",
                "Connaissance : Relations humaines, communication"
              ],
              "competenceToCapaciteEtConnaissance": {
                "B7": [
                  "Capacité : S'intégrer dans un environnement socio-économique nouveau",
                  "Capacité : S'approprier les enjeux économiques internationaux",
                  "Capacité : Communiquer dans une langue étrangère",
                  "Connaissance : Organisation d'un milieu professionnel étranger",
                  "Connaissance : Contexte économique mondial  -- Travailler, apprendre, évoluer de manière autonome (niveau 2)",
                  "Capacité : Gérer son temps et son projet",
                  "Capacité : Analyser et rédiger des documents professionnels",
                  "Capacité : Construire et argumenter une candidature",
                  "Capacité : S'intégrer dans une équipe, contribuer à l'animer, à l'organiser et à la faire évoluer",
                  "Capacité : Utiliser les différents moyens de communication au sein de l'entreprise en s'adaptant à son interlocuteur",
                  "Capacité : Exposer efficacement un travail à l'écrit et à l'oral dans une langue étrangère ; s'adapter à l'auditoire",
                  "Connaissance : Recherche de stage",
                  "Connaissance : Démarche projet",
                  "Connaissance : Compétences métier",
                  "Connaissance : Relations humaines, communication"
                ]
              },
              "listeComp": [
                {
                  "code": "B7",
                  "val": "Travailler dans un contexte international et interculturel",
                  "valAnglais": "Work in an international, intercultural context",
                  "bs": "29",
                  "niveau": "2"
                }
              ],
              "listeCompMobilise": [
                "Interagir avec les autres, travailler en équipe"
              ]
            }
          },
          {
            "UE": "Projet Fin d'Etude 2 (GEA-5-UE55)",
            "url": "http://planete.insa-lyon.fr/scolpeda/f/ects?id=37829&_lang=fr",
            "detail": {
              "code": "GEA-5-PFE2",
              "ects": "20.0",
              "cours": "0.0 h",
              "td": "2.0 h",
              "tp": "0.0 h",
              "projet": "0.0 h",
              "perso": "400.0 h",
              "nom": "Projets de fin d'études : Projet Fin d'Etude 2",
              "competencesBrutes": "Cet EC relève de l'unité d'enseignement  (UE55) et contribue aux compétences suivantes :  -- Se situer, travailler, évoluer dans une entreprise, une organisation socio-productive (niveau 2)  --- Capacité : Etre capable de travailler avec différents services ou sur plusieurs affaires en respectant l'organisation, les délais et les contraintes de chacun. --- Capacité : Etre capable de chiffrer /budgeter/estimer les coûts en autonomie  -- Travailler, apprendre, évoluer de manière autonome (niveau 2)  --- Capacité : Pilotage d'un projet en autonomie avec réalisation du découpage en sous tâche et élaboration d'un Gantt.  -- Interagir avec les autres, travailler en équipe (niveau )  --- Capacité : Etre capable d'animer une réunion en autonomie --- Capacité : Savoir mobiliser les acteurs pour faire aboutir son projet  - Mettre en œuvre ses compétences scientifiques et technologiques dans le domaine de l'EEAIIT dans un cadre industriel et appliqué à des problématiques réelles en conduisant les étapes du cycle de conception (niveau )  --- Capacité : Etre capable de concevoir ou mettre en oeuvre un système électrique en comprenant les enjeux de l'installation complète. --- Capacité : Intégrer les besoins des autres corps d'ingéniérie. --- Capacité : Participer à la mise en œuvre complète du cycle en V",
              "capacite": [
                "Capacité : Etre capable de travailler avec différents services ou sur plusieurs affaires en respectant l'organisation, les délais et les contraintes de chacun.",
                "Capacité : Etre capable de chiffrer /budgeter/estimer les coûts en autonomie  -- Travailler, apprendre, évoluer de manière autonome (niveau 2)",
                "Capacité : Pilotage d'un projet en autonomie avec réalisation du découpage en sous tâche et élaboration d'un Gantt.  -- Interagir avec les autres, travailler en équipe (niveau )",
                "Capacité : Etre capable d'animer une réunion en autonomie",
                "Capacité : Savoir mobiliser les acteurs pour faire aboutir son projet",
                "Capacité : Etre capable de concevoir ou mettre en oeuvre un système électrique en comprenant les enjeux de l'installation complète.",
                "Capacité : Intégrer les besoins des autres corps d'ingéniérie.",
                "Capacité : Participer à la mise en œuvre complète du cycle en V"
              ],
              "connaissance": [],
              "competenceToCapaciteEtConnaissance": {
                "B6": [
                  "Capacité : Etre capable de travailler avec différents services ou sur plusieurs affaires en respectant l'organisation, les délais et les contraintes de chacun.",
                  "Capacité : Etre capable de chiffrer /budgeter/estimer les coûts en autonomie  -- Travailler, apprendre, évoluer de manière autonome (niveau 2)",
                  "Capacité : Pilotage d'un projet en autonomie avec réalisation du découpage en sous tâche et élaboration d'un Gantt.  -- Interagir avec les autres, travailler en équipe (niveau )",
                  "Capacité : Etre capable d'animer une réunion en autonomie",
                  "Capacité : Savoir mobiliser les acteurs pour faire aboutir son projet"
                ],
                "GEA-C9": [
                  "Capacité : Etre capable de concevoir ou mettre en oeuvre un système électrique en comprenant les enjeux de l'installation complète.",
                  "Capacité : Intégrer les besoins des autres corps d'ingéniérie.",
                  "Capacité : Participer à la mise en œuvre complète du cycle en V"
                ]
              },
              "listeComp": [
                {
                  "code": "B6",
                  "val": "Se situer, travailler, évoluer dans une entreprise, une organisation socio-productive",
                  "valAnglais": "Position oneself, work, and evolve within a company or a socio-productive organization",
                  "bs": "28",
                  "niveau": "2"
                },
                {
                  "code": "C9",
                  "val": "Mettre en œuvre ses compétences scientifiques et technologiques dans le domaine de l'EEAIIT dans un cadre industriel et appliqué à des problématiques réelles en conduisant les étapes du cycle de conception",
                  "valAnglais": "Apply scientific and technological competences in the field of the EEAIIT in an industrial framework and to real problems by leading the stages of the cycle of conception",
                  "niveau": ""
                }
              ]
            }
          }
        ]
      }
    ]
  }
]
